Workbook
Name Slicer_Make: #N/A

Sheet Raw Data
A1: Car | B1: Condition | C1: Mileage | D1: Price | E1: Basics Info | F1: Vehicle History Info | G1: Vehicle Reviews Info | H1: Seller Rating | I1: Seller Rating Count | J1: Seller Address
A2: 2024 Lexus LC 500 Base | B2: New | C2: 0 mi. | D2: $112,865MSRP $118,865 | E2: {'Exterior color': ' Caviar ', 'Interior color': 'Black ', 'Drivetrain': 'Rear-wheel Drive ', 'MPG': ' 15â€“25Based on EPA mileage ratings. Use for comparison purposes only. Actual mileage will vary depending on driving conditions, driving habits, vehicle maintenance, and other factors.', 'Fuel type': 'Gasoline ', 'Transmission': '10-Speed Automatic', 'Engine': '5.0L V8 32V PDI DOHC', 'VIN': ' JTHNPAAY2RA108024 ', 'Stock #': ' R087 ', 'Mileage': ' 0 mi. '} | F2: {} | G2: {} | H2: 4.7 | I2: (1,261 reviews) | J2: 1250 W Division St Chicago, IL 60642
A3: 2007 Acura TSX Base | B3: Used | C3: 61,110 mi. | D3: 11295 | E3: {'Exterior color': ' Alabaster Silver Metallic ', 'Interior color': 'â€“ ', 'Drivetrain': 'Front-wheel Drive ', 'MPG': ' 22â€“31Based on EPA mileage ratings. Use for comparison purposes only. Actual mileage will vary depending on driving conditions, driving habits, vehicle maintenance, and other factors.', 'Fuel type': 'Gasoline ', 'Transmission': 'Automatic', 'Engine': '2.4L I-4 DOHC, i-VTEC variable valve control, premium unleaded,', 'VIN': ' JH4CL96827C013765 ', 'Stock #': ' A40896A ', 'Mileage': ' 61,110 mi. '} | F3: {'Accidents or damage': 'At least 1 accident or damage reported', '1-owner vehicle': 'Yes', 'Personal use only': 'Yes'} | G3: {} | H3: 4.2 | I3: (440 reviews) | J3: 1301 N Elston Ave Chicago, IL 60642
A4: 2016 McLaren 675LT Base | B4: Used | C4: 6,305 mi. | D4: $219,997$5,464 price drop | E4: {'Exterior color': ' McLaren Orange ', 'Interior color': 'Carbon Black ', 'Drivetrain': 'Rear-wheel Drive ', 'MPG': ' â€“', 'Fuel type': 'Gasoline ', 'Transmission': '7-Speed Automatic with Auto-Shift', 'Engine': '3.8L V8 32V MPFI DOHC Twin Turbo', 'VIN': ' SBM11RAA7GW675095 ', 'Stock #': ' K2338 ', 'Mileage': ' 6,305 mi. '} | F4: {'Accidents or damage': 'At least 1 accident or damage reported', '1-owner vehicle': 'No', 'Personal use only': 'No'} | G4: {'Comfort': '5.0', 'Interior': '5.0', 'Performance': '5.0', 'Value': '5.0', 'Exterior': '5.0', 'Reliability': '5.0'} | H4: 3.1 | I4: (421 reviews) | J4: 1561 N Fremont St Chicago, IL 60642
A5: 2016 Audi TTS 2.0T quattro | B5: Used | C5: 65,715 mi. | D5: 23999 | E5: {'Exterior color': ' Black ', 'Interior color': 'Black ', 'Drivetrain': 'All-wheel Drive ', 'MPG': ' 23â€“27Based on EPA mileage ratings. Use for comparison purposes only. Actual mileage will vary depending on driving conditions, driving habits, vehicle maintenance, and other factors.', 'Fuel type': 'Gasoline ', 'Transmission': '6-Speed Automatic with Auto-Shift', 'Engine': '2.0L I4 16V GDI DOHC Turbo', 'VIN': ' TRUC1AFV1G1019119 ', 'Stock #': ' 3949 ', 'Mileage': ' 65,715 mi. '} | F5: {'Accidents or damage': 'At least 1 accident or damage reported', 'Clean title': 'Yes', '1-owner vehicle': 'No', 'Personal use only': 'Yes'} | G5: {'Comfort': '3.0', 'Interior': '5.0', 'Performance': '5.0', 'Value': '5.0', 'Exterior': '5.0', 'Reliability': '5.0'} | H5: 3.6 | I5: (123 reviews) | J5: 560 E North Ave West Chicago, IL 60185
A6: 2018 BMW 740e xDrive iPerformance | B6: Used | C6: 19,830 mi. | D6: $39,799$100 price drop | E6: {'Exterior color': ' Imperial Blue Metallic ', 'Interior color': 'Black ', 'Drivetrain': 'All-wheel Drive ', 'MPG': ' 0â€“0Based on EPA mileage ratings. Use for comparison purposes only. Actual mileage will vary depending on driving conditions, driving habits, vehicle maintenance, and other factors.', 'Fuel type': 'Gasoline ', 'Transmission': '8-Speed Automatic', 'Engine': '2L I-4 gasoline direct injection, DOHC, Double VANOS variable va', 'VIN': ' WBA7J2C57JG938534 ', 'Stock #': ' A6006 ', 'Mileage': ' 19,830 mi. '} | F6: {'Accidents or damage': 'None reported', 'Clean title': 'Yes', '1-owner vehicle': 'Yes', 'Personal use only': 'No'} | G6: {'Comfort': '5.0', 'Interior': '5.0', 'Performance': '5.0', 'Value': '5.0', 'Exterior': '5.0', 'Reliability': '5.0'} | H6: 4.4 | I6: (91 reviews) | J6: 6539 Ogden Ave Berwyn, IL 60402
A7: 2019 Jeep Cherokee Limited | B7: Used | C7: 52,245 mi. | D7: $22,966$173 price drop | E7: {'Exterior color': ' Diamond Black ', 'Interior color': 'Black ', 'Drivetrain': 'Four-wheel Drive ', 'MPG': ' 19â€“27Based on EPA mileage ratings. Use for comparison purposes only. Actual mileage will vary depending on driving conditions, driving habits, vehicle maintenance, and other factors.', 'Fuel type': 'Gasoline ', 'Transmission': '9-Speed Automatic', 'Engine': '3.2L V6 24V MPFI DOHC', 'VIN': ' 1C4PJMDX4KD139201 ', 'Stock #': ' Y17217A ', 'Mileage': ' 52,245 mi. '} | F7: {'Accidents or damage': 'At least 1 accident or damage reported', '1-owner vehicle': 'No', 'Personal use only': 'No'} | G7: {} | H7: 4.2 | I7: (3,030 reviews) | J7: 6750 W Grand Ave Chicago, IL 60707
A8: 2019 Cadillac CT6 3.6L Luxury | B8: Used | C8: 94,008 mi. | D8: $26,995$183 price drop | E8: {'Exterior color': ' Black ', 'Interior color': 'Black ', 'Drivetrain': 'All-wheel Drive ', 'MPG': ' 18â€“27Based on EPA mileage ratings. Use for comparison purposes only. Actual mileage will vary depending on driving conditions, driving habits, vehicle maintenance, and other factors.', 'Fuel type': 'Gasoline ', 'Transmission': 'Automatic', 'Engine': '3.6L V-6 gasoline direct injection, DOHC, VVT variable valve con', 'VIN': ' 1G6KB5RS1KU131814 ', 'Stock #': ' 8378 ', 'Mileage': ' 94,008 mi. '} | F8: {'Accidents or damage': 'At least 1 accident or damage reported', '1-owner vehicle': 'No', 'Personal use only': 'No'} | G8: {} | H8: 4.1 | I8: (50 reviews) | J8: 7158 Harlem Ave Bridgeview, IL 60455
A9: 2012 Nissan NV Cargo S | B9: Used | C9: 110,202 mi. | D9: 14985 | E9: {'Exterior color': ' Blizzard ', 'Interior color': 'Gray ', 'Drivetrain': 'Rear-wheel Drive ', 'MPG': ' â€“', 'Fuel type': 'Gasoline ', 'Transmission': 'Automatic', 'Engine': '5.6L V8 32V MPFI DOHC', 'VIN': ' 1N6AF0KX9CN103838 ', 'Stock #': ' 8418 ', 'Mileage': ' 110,202 mi. '} | F9: {'Accidents or damage': 'At least 1 accident or damage reported', 'Clean title': 'Yes', '1-owner vehicle': 'No', 'Personal use only': 'No'} | G9: {'Comfort': '5.0', 'Interior': '5.0', 'Performance': '5.0', 'Value': '4.0', 'Exterior': '4.0', 'Reliability': '3.0'} | H9: 3.6 | I9: (64 reviews) | J9: 6007 S Archer Rd Summit, IL 60501
A10: 2008 Chrysler Sebring Touring | B10: Used | C10: 77,893 mi. | D10: 7995 | E10: {'Exterior color': ' Silver ', 'Interior color': 'Gray ', 'Drivetrain': 'Front-wheel Drive ', 'MPG': ' 26â€“26Based on EPA mileage ratings. Use for comparison purposes only. Actual mileage will vary depending on driving conditions, driving habits, vehicle maintenance, and other factors.', 'Fuel type': 'E85 Flex Fuel ', 'Transmission': 'Automatic 4-Speed', 'Engine': '2.7L V6', 'VIN': ' 1C3LC55R58N689769 ', 'Stock #': ' 8N689769STK ', 'Mileage': ' 77,893 mi. '} | F10: {'Accidents or damage': 'None reported', '1-owner vehicle': 'No', 'Personal use only': 'Yes'} | G10: {} | H10: 3.5 | I10: (43 reviews) | J10: 1210 25th Ave Melrose Park, IL 60160
A11: 2012 Ford E250 Cargo | B11: Used | C11: 106,430 mi. | D11: $15,750$540 price drop | E11: {'Exterior color': ' White ', 'Interior color': 'Gray ', 'Drivetrain': 'Rear-wheel Drive ', 'MPG': ' 17â€“17Based on EPA mileage ratings. Use for comparison purposes only. Actual mileage will vary depending on driving conditions, driving habits, vehicle maintenance, and other factors.', 'Fuel type': 'E85 Flex Fuel ', 'Transmission': 'Automatic 4-Speed', 'Engine': '4.6L V8', 'VIN': ' 1FTNE2EW9CDA52319 ', 'Stock #': ' T0137 ', 'Mileage': ' 106,430 mi. '} | F11: {'Accidents or damage': 'None reported', 'Clean title': 'No', '1-owner vehicle': 'No', 'Personal use only': 'No'} | G11: {'Comfort': '4.0', 'Interior': '4.0', 'Performance': '4.0', 'Value': '5.0', 'Exterior': '4.0', 'Reliability': '5.0'} | J11: 6400 Harlem Ave Summit, IL 60501
A12: 2013 Toyota Prius v Five | B12: Used | C12: 155,600 mi. | D12: 12995 | E12: {'Exterior color': ' Blue ', 'Interior color': 'Gray ', 'Drivetrain': 'Front-wheel Drive ', 'MPG': ' 44â€“40Based on EPA mileage ratings. Use for comparison purposes only. Actual mileage will vary depending on driving conditions, driving habits, vehicle maintenance, and other factors.', 'Fuel type': 'Gasoline ', 'Transmission': 'Automatic', 'Engine': '1.8L I-4 DOHC, VVT-i variable valve control, regular unleaded, e', 'VIN': ' JTDZN3EU9D3206492 ', 'Stock #': ' GA-206492 ', 'Mileage': ' 155,600 mi. '} | F12: {'Accidents or damage': 'At least 1 accident or damage reported', '1-owner vehicle': 'No', 'Personal use only': 'Yes'} | G12: {'Comfort': '5.0', 'Interior': '4.0', 'Performance': '4.0', 'Value': '5.0', 'Exterior': '4.0', 'Reliability': '5.0'} | J12: 5050 Dempster Street Skokie, IL 60077
A13: 2002 BMW 745 Li | B13: Used | C13: 146,000 mi. | D13: 4599 | E13: {'Exterior color': ' White ', 'Interior color': 'Beige ', 'Drivetrain': 'Rear-wheel Drive ', 'Fuel type': 'Gasoline ', 'Transmission': 'A/T', 'Engine': '325.0HP 4.4L 8 Cylinder Engine Gasoline Fuel', 'VIN': ' WBAGN634X2DR03993 ', 'Mileage': ' 146,000 mi. '} | F13: {'Accidents or damage': 'None reported', 'Clean title': 'Yes', '1-owner vehicle': 'No', 'Personal use only': 'Yes'} | G13: {}
A14: 2020 INFINITI Q60 3.0t Red Sport 400 | B14: Used | C14: 22,901 mi. | D14: 38713 | E14: {'Exterior color': ' Iridium Blue ', 'Interior color': 'Blue ', 'Drivetrain': 'Rear-wheel Drive ', 'MPG': ' 20â€“27Based on EPA mileage ratings. Use for comparison purposes only. Actual mileage will vary depending on driving conditions, driving habits, vehicle maintenance, and other factors.', 'Fuel type': 'Gasoline ', 'Transmission': '7-Speed Automatic', 'Engine': '3.0L V6 24V GDI DOHC Twin Turbo', 'VIN': ' JN1FV7EK1LM400180 ', 'Stock #': ' M91221 ', 'Mileage': ' 22,901 mi. '} | F14: {'Accidents or damage': 'None reported', '1-owner vehicle': 'Yes', 'Personal use only': 'Yes'} | G14: {} | H14: 4.1 | I14: (591 reviews) | J14: 6750 West 95th Street Oak Lawn, IL 60453
A15: 2014 Volkswagen Beetle 1.8T | B15: Used | C15: 48,650 mi. | D15: 16988 | E15: {'Exterior color': ' Platinum Gray Metallic ', 'Interior color': 'Titan Black ', 'Drivetrain': 'Front-wheel Drive ', 'MPG': ' 25â€“33Based on EPA mileage ratings. Use for comparison purposes only. Actual mileage will vary depending on driving conditions, driving habits, vehicle maintenance, and other factors.', 'Fuel type': 'Gasoline ', 'Transmission': '6-Speed Automatic', 'Engine': '1.8L I4 16V GDI DOHC Turbo', 'VIN': ' 3VWJ17AT3EM659954 ', 'Stock #': ' P7459VW ', 'Mileage': ' 48,650 mi. '} | F15: {'Accidents or damage': 'None reported', '1-owner vehicle': 'Yes', 'Personal use only': 'Yes'} | G15: {} | H15: 4.5 | I15: (1,555 reviews) | J15: 241 Waukegan Rd Glenview, IL 60025
A16: 2015 BMW M235 i | B16: Used | C16: 73,660 mi. | D16: 22843 | E16: {'Exterior color': ' Glacier Silver Metallic ', 'Interior color': 'â€“ ', 'Drivetrain': 'Rear-wheel Drive ', 'MPG': ' 21â€“32Based on EPA mileage ratings. Use for comparison purposes only. Actual mileage will vary depending on driving conditions, driving habits, vehicle maintenance, and other factors.', 'Fuel type': 'Gasoline ', 'Transmission': '8-Speed Automatic', 'Engine': '3.0L I6 24V GDI DOHC Turbo', 'VIN': ' WBA1J7C59FV358577 ', 'Stock #': ' R6301 ', 'Mileage': ' 73,660 mi. '} | F16: {'Accidents or damage': 'None reported', 'Clean title': 'Yes', '1-owner vehicle': 'No', 'Personal use only': 'Yes'} | G16: {} | H16: 4 | I16: (288 reviews) | J16: 11201 S Harlem Ave Worth, IL 60482
A17: 2004 BMW 745 745i | B17: Used | C17: 119,263 mi. | D17: 7999 | E17: {'Exterior color': ' Gold ', 'Interior color': 'Tan ', 'Drivetrain': 'Rear-wheel Drive ', 'MPG': ' 18â€“26Based on EPA mileage ratings. Use for comparison purposes only. Actual mileage will vary depending on driving conditions, driving habits, vehicle maintenance, and other factors.', 'Fuel type': 'Gasoline ', 'Transmission': '6-speed Steptronic automatic transmission w/OD-inc', 'Engine': '4.4L (268) DOHC EFI 32-valve aluminum V8 engine w/variable valve', 'VIN': ' WBAGL63424DP69960 ', 'Stock #': ' EM-P69960 ', 'Mileage': ' 119,263 mi. '} | F17: {'Accidents or damage': 'None reported', '1-owner vehicle': 'No', 'Personal use only': 'Yes'} | G17: {} | H17: 4.3 | I17: (77 reviews) | J17: 530 W Grand Ave Elmhurst, IL 60126
A18: 2024 Chevrolet Blazer EV RS | B18: New | C18: 2,210 mi. | D18: $52,715MSRP $60,215 | E18: {'Exterior color': ' Summit White ', 'Interior color': 'Black ', 'Drivetrain': 'All-wheel Drive ', 'Transmission': '1-Speed Automatic', 'Engine': 'Electric', 'VIN': ' 3GNKDCRJ4RS113831 ', 'Stock #': ' V23091 ', 'Mileage': ' 2,210 mi. '} | F18: {} | G18: {} | H18: 4.1 | I18: (1,154 reviews) | J18: 400 E Roosevelt Rd Villa Park, IL 60181
A19: 2000 Jaguar XK8 | B19: Used | C19: 62,022 mi. | D19: 13995 | E19: {'Exterior color': ' Platinum Metallic ', 'Interior color': 'Ivory ', 'Drivetrain': 'Rear-wheel Drive ', 'MPG': ' 18â€“25Based on EPA mileage ratings. Use for comparison purposes only. Actual mileage will vary depending on driving conditions, driving habits, vehicle maintenance, and other factors.', 'Fuel type': 'Gasoline ', 'Transmission': '5-Speed Automatic', 'Engine': '4.0L V8 32V MPFI DOHC', 'VIN': ' SAJJA41CXYNA04688 ', 'Stock #': ' IA1389-NM ', 'Mileage': ' 62,022 mi. '} | F19: {'Accidents or damage': 'None reported', '1-owner vehicle': 'No', 'Personal use only': 'Yes'} | G19: {'Comfort': '4.0', 'Interior': '5.0', 'Performance': '3.0', 'Value': '3.0', 'Exterior': '5.0', 'Reliability': '3.0'} | J19: 594 W Lake St Elmhurst, IL 60126
A20: 2013 Subaru XV Crosstrek 2.0i Premium | B20: Used | C20: 84,358 mi. | D20: $13,900$1,000 price drop | E20: {'Exterior color': ' Venetian Red Pearl ', 'Interior color': 'Ivory ', 'Drivetrain': 'All-wheel Drive ', 'MPG': ' 25â€“33Based on EPA mileage ratings. Use for comparison purposes only. Actual mileage will vary depending on driving conditions, driving habits, vehicle maintenance, and other factors.', 'Fuel type': 'Gasoline ', 'Transmission': 'Automatic', 'Engine': '2L H-4 DOHC, variable valve control, regular unleaded, engine wi', 'VIN': ' JF2GPAVCXD2864679 ', 'Stock #': ' P5259 ', 'Mileage': ' 84,358 mi. '} | F20: {'Accidents or damage': 'At least 1 accident or damage reported', '1-owner vehicle': 'No', 'Personal use only': 'Yes', 'Open recall': 'At least 1 open recall reported'} | G20: {'Comfort': '4.0', 'Interior': '3.0', 'Performance': '1.0', 'Value': '1.0', 'Exterior': '4.0', 'Reliability': '1.0'} | H20: 4.8 | I20: (185 reviews) | J20: 12717 Cal Sag Rd Crestwood, IL 60445
A21: 2011 Ford E250 Cargo | B21: Used | C21: 181,000 mi. | D21: 9995 | E21: {'Exterior color': ' Red ', 'Interior color': 'Black ', 'Drivetrain': 'Rear-wheel Drive ', 'MPG': ' 13â€“17Based on EPA mileage ratings. Use for comparison purposes only. Actual mileage will vary depending on driving conditions, driving habits, vehicle maintenance, and other factors.', 'Fuel type': 'E85 Flex Fuel ', 'Transmission': '4-Speed Automatic', 'Engine': '5.4L V8 16V MPFI SOHC Flexible Fuel', 'VIN': ' 1FTNE2EL0BDA58661 ', 'Stock #': ' IA1399 ', 'Mileage': ' 181,000 mi. '} | F21: {'Accidents or damage': 'At least 1 accident or damage reported', '1-owner vehicle': 'No', 'Personal use only': 'No'} | G21: {} | J21: 594 W Lake St Elmhurst, IL 60126
A22: 2013 BMW 128 128i Coupe | B22: Used | C22: 77,783 mi. | D22: 8995 | E22: {'Exterior color': ' Pearl White ', 'Interior color': 'Black ', 'Drivetrain': 'Rear-wheel Drive ', 'MPG': ' 18â€“28Based on EPA mileage ratings. Use for comparison purposes only. Actual mileage will vary depending on driving conditions, driving habits, vehicle maintenance, and other factors.', 'Fuel type': 'Gasoline ', 'Transmission': 'Automatic', 'Engine': '3L I-6 DOHC, Double VANOS variable valve control, premium unlead', 'VIN': ' WBAUP9C59DVS95159 ', 'Stock #': ' TS-0538 ', 'Mileage': ' 77,783 mi. '} | F22: {'Accidents or damage': 'At least 1 accident or damage reported', '1-owner vehicle': 'No', 'Personal use only': 'Yes', 'Open recall': 'At least 1 open recall reported'} | G22: {} | J22: 13840 South Pulaski Road Crestwood, IL 60445
A23: 2019 Audi TTS 2.0T quattro | B23: Used | C23: 33,832 mi. | D23: $39,990$455 price drop | E23: {'Exterior color': ' Daytona Gray Pearl Effect ', 'Interior color': 'Black / Rock Gray ', 'Drivetrain': 'All-wheel Drive ', 'MPG': ' 23â€“29Based on EPA mileage ratings. Use for comparison purposes only. Actual mileage will vary depending on driving conditions, driving habits, vehicle maintenance, and other factors.', 'Fuel type': 'Gasoline ', 'Transmission': '7-Speed Automatic with Auto-Shift', 'Engine': '2.0L I4 16V GDI DOHC Turbo', 'VIN': ' TRUA1AFV2K1008212 ', 'Stock #': ' C1905A ', 'Mileage': ' 33,832 mi. '} | F23: {'Accidents or damage': 'None reported', '1-owner vehicle': 'Yes', 'Personal use only': 'Yes'} | G23: {'Comfort': '4.0', 'Interior': '5.0', 'Performance': '5.0', 'Value': '5.0', 'Exterior': '5.0', 'Reliability': '5.0'} | H23: 4.9 | I23: (2,168 reviews) | J23: 500 E. Ogden Ave. Westmont, IL 60559
A24: 1988 Chevrolet C10/K10 Base | B24: Used | C24: 48,934 mi. | D24: 19888 | E24: {'Exterior color': ' Barcelona Red ', 'Interior color': 'Barcelona Red ', 'Drivetrain': 'Rear-wheel Drive ', 'MPG': ' 0â€“0Based on EPA mileage ratings. Use for comparison purposes only. Actual mileage will vary depending on driving conditions, driving habits, vehicle maintenance, and other factors.', 'Fuel type': 'Gasoline ', 'Transmission': 'Automatic', 'Engine': '5.7 TBI V8', 'VIN': ' 1GCDC14K2JZ156418 ', 'Stock #': ' 156418 ', 'Mileage': ' 48,934 mi. '} | F24: {'Accidents or damage': 'None reported', '1-owner vehicle': 'No', 'Personal use only': 'No'} | G24: {} | H24: 5 | I24: (5 reviews) | J24: 1326 West Irving Park Road Bensenville, IL 60106
A25: 2016 Mercedes-Benz AMG G AMG G 63 4MATIC | B25: Used | C25: 59,386 mi. | D25: 71995 | E25: {'Exterior color': ' Palladium Silver Metallic ', 'Interior color': 'Designo Black ', 'Drivetrain': 'All-wheel Drive ', 'MPG': ' 12â€“14Based on EPA mileage ratings. Use for comparison purposes only. Actual mileage will vary depending on driving conditions, driving habits, vehicle maintenance, and other factors.', 'Fuel type': 'Gasoline ', 'Transmission': '7-Speed Automatic', 'Engine': '5.5L V8 32V GDI DOHC Twin Turbo', 'VIN': ' WDCYC7DF7GX258917 ', 'Stock #': ' HL7535 ', 'Mileage': ' 59,386 mi. '} | F25: {'Accidents or damage': 'At least 1 accident or damage reported', '1-owner vehicle': 'No', 'Personal use only': 'Yes'} | G25: {'Comfort': '5.0', 'Interior': '5.0', 'Performance': '5.0', 'Value': '5.0', 'Exterior': '5.0', 'Reliability': 'â€”'} | H25: 4.6 | I25: (358 reviews) | J25: 555 Executive Dr Willowbrook, IL 60527
A26: 2002 Lexus SC 430 Base | B26: Used | C26: 98,373 mi. | D26: $8,999$300 price drop | E26: {'Exterior color': ' Burgundy ', 'Interior color': 'Tan ', 'Drivetrain': 'Rear-wheel Drive ', 'MPG': ' 18â€“23Based on EPA mileage ratings. Use for comparison purposes only. Actual mileage will vary depending on driving conditions, driving habits, vehicle maintenance, and other factors.', 'Fuel type': 'Gasoline ', 'Transmission': 'Automatic', 'Engine': '4.3L (262) DOHC EFI 32-valve V8 aluminum engine-inc: continuousl', 'VIN': ' JTHFN48YX20002417 ', 'Stock #': ' YC-002417 ', 'Mileage': ' 98,373 mi. '} | F26: {'Accidents or damage': 'None reported', '1-owner vehicle': 'No', 'Personal use only': 'Yes'} | G26: {'Comfort': '5.0', 'Interior': '5.0', 'Performance': '4.0', 'Value': '5.0', 'Exterior': '5.0', 'Reliability': '5.0'} | H26: 4.3 | I26: (110 reviews) | J26: 3128 W 147th St Posen, IL 60469
A27: 2023 Lexus LC 500 Base | B27: New | C27: 0 mi. | D27: $106,615MSRP $114,420 | E27: {'Exterior color': ' Caviar ', 'Interior color': 'Red ', 'Drivetrain': 'Rear-wheel Drive ', 'MPG': ' 15â€“25Based on EPA mileage ratings. Use for comparison purposes only. Actual mileage will vary depending on driving conditions, driving habits, vehicle maintenance, and other factors.', 'Fuel type': 'Gasoline ', 'Transmission': '10-Speed Automatic', 'Engine': '5.0L V8 32V PDI DOHC', 'VIN': ' JTHMPAAY6PA107242 ', 'Stock #': ' B1781 ', 'Mileage': ' 0 mi. '} | F27: {} | G27: {} | H27: 4.9 | I27: (2,168 reviews) | J27: 500 E. Ogden Ave. Westmont, IL 60559
E28: {} | F28: {} | G28: {}
A29: 2006 Pontiac GTO | B29: Used | C29: 55,915 mi. | D29: $20,691$1,300 price drop | E29: {'Exterior color': ' Phantom Black Metallic ', 'Interior color': 'Red ', 'Drivetrain': 'Rear-wheel Drive ', 'MPG': ' â€“', 'Fuel type': 'Gasoline ', 'Transmission': '4-Speed Automatic', 'Engine': '6.0L V8 16V MPFI OHV', 'VIN': ' 6G2VX12U86L521103 ', 'Stock #': ' 6L521103 ', 'Mileage': ' 55,915 mi. '} | F29: {'Accidents or damage': 'At least 1 accident or damage reported', '1-owner vehicle': 'Yes', 'Personal use only': 'Yes'} | G29: {} | H29: 4.7 | I29: (1,955 reviews) | J29: 430 E. Ogden Ave. Westmont, IL 60559
A30: 1988 BMW M6 | B30: Used | C30: 46,344 mi. | D30: 63910 | E30: {'Exterior color': ' Cinnabar Red ', 'Interior color': 'Tan ', 'Drivetrain': 'Rear-wheel Drive ', 'MPG': ' â€“', 'Fuel type': 'Gasoline ', 'Transmission': '5-Speed Manual', 'Engine': '3.5L I6 24V DOHC', 'VIN': ' WBAEE1410J2561382 ', 'Stock #': ' C071421 ', 'Mileage': ' 46,344 mi. '} | F30: {'Accidents or damage': 'None reported', 'Clean title': 'Yes', '1-owner vehicle': 'No', 'Personal use only': 'Yes'} | G30: {} | H30: 3.9 | I30: (160 reviews) | J30: 100 W Ogden Ave Westmont, IL 60559
A31: 1975 Triumph TR6 | B31: Used | C31: 27,667 mi. | D31: 26507 | E31: {'Exterior color': ' Yellow ', 'Interior color': 'Black ', 'Drivetrain': 'â€“ ', 'MPG': ' â€“', 'Fuel type': 'â€“ ', 'Transmission': 'Manual', 'Engine': 'â€“', 'VIN': ' 000000000CF39098U ', 'Stock #': ' C040623-1 ', 'Mileage': ' 27,667 mi. '} | F31: {} | G31: {} | H31: 3.9 | I31: (160 reviews) | J31: 100 W Ogden Ave Westmont, IL 60559
A32: 2018 BMW M6 Base | B32: Used | C32: 46,698 mi. | D32: 45373 | E32: {'Exterior color': ' San Marino Blue Metallic ', 'Interior color': 'Black ', 'Drivetrain': 'Rear-wheel Drive ', 'MPG': ' 14â€“20Based on EPA mileage ratings. Use for comparison purposes only. Actual mileage will vary depending on driving conditions, driving habits, vehicle maintenance, and other factors.', 'Fuel type': 'Gasoline ', 'Transmission': '7-Speed Automatic', 'Engine': '4.4L V8 32V DOHC TwinPower Turbo', 'VIN': ' WBS6G9C59JBM23806 ', 'Stock #': ' UN4073 ', 'Mileage': ' 46,698 mi. '} | F32: {'Accidents or damage': 'None reported', '1-owner vehicle': 'No', 'Personal use only': 'Yes'} | G32: {'Comfort': '5.0', 'Interior': '5.0', 'Performance': '5.0', 'Value': '5.0', 'Exterior': '5.0', 'Reliability': '5.0'} | H32: 2.8 | I32: (83 reviews) | J32: 1850 Holste Rd Northbrook, IL 60062
A33: 2009 INFINITI G37 Journey | B33: Used | C33: 96,658 mi. | D33: 10980 | E33: {'Exterior color': ' Blue Slate Pearl ', 'Interior color': 'Beige ', 'Drivetrain': 'Rear-wheel Drive ', 'MPG': ' 18â€“26Based on EPA mileage ratings. Use for comparison purposes only. Actual mileage will vary depending on driving conditions, driving habits, vehicle maintenance, and other factors.', 'Fuel type': 'Gasoline ', 'Transmission': 'Automatic', 'Engine': 'VQ 3.7L V-6 DOHC, variable valve control, premium unleaded, engi', 'VIN': ' JNKCV64E49M606171 ', 'Stock #': ' 5963 ', 'Mileage': ' 96,658 mi. '} | F33: {'Accidents or damage': 'At least 1 accident or damage reported', 'Clean title': 'Yes', '1-owner vehicle': 'No', 'Personal use only': 'Yes'} | G33: {} | H33: 4.6 | I33: (189 reviews) | J33: 1886 S Elmhurst Rd Mt Prospect, IL 60056
A34: 2016 Volkswagen Golf SportWagen TSI SE | B34: Used | C34: 145,302 mi. | D34: 9495 | E34: {'Exterior color': ' Silver ', 'Interior color': 'Black ', 'Drivetrain': 'Front-wheel Drive ', 'MPG': ' 25â€“35Based on EPA mileage ratings. Use for comparison purposes only. Actual mileage will vary depending on driving conditions, driving habits, vehicle maintenance, and other factors.', 'Fuel type': 'Gasoline ', 'Transmission': '6-Speed Automatic', 'Engine': '1.8L I4 16V GDI DOHC Turbo', 'VIN': ' 3VWC17AU4GM509453 ', 'Stock #': ' XM651 ', 'Mileage': ' 145,302 mi. '} | F34: {'Accidents or damage': 'At least 1 accident or damage reported', '1-owner vehicle': 'No', 'Personal use only': 'Yes'} | G34: {'Comfort': '4.0', 'Interior': '5.0', 'Performance': '5.0', 'Value': '5.0', 'Exterior': '5.0', 'Reliability': '5.0'} | J34: 870 S Fiene Dr. Addison, IL 60101
A35: 2005 Scion xA Base (A4) | B35: Used | C35: 102,243 mi. | D35: 5795 | E35: {'Exterior color': ' Gray ', 'Interior color': 'Black ', 'Drivetrain': 'Front-wheel Drive ', 'MPG': ' 31â€“38Based on EPA mileage ratings. Use for comparison purposes only. Actual mileage will vary depending on driving conditions, driving habits, vehicle maintenance, and other factors.', 'Fuel type': 'Gasoline ', 'Transmission': '4-Speed Automatic', 'Engine': '1.5L I4 16V MPFI DOHC', 'VIN': ' JTKKT624450118605 ', 'Stock #': ' 2807 ', 'Mileage': ' 102,243 mi. '} | F35: {'Accidents or damage': 'At least 1 accident or damage reported', '1-owner vehicle': 'No', 'Personal use only': 'Yes'} | G35: {} | H35: 4.6 | I35: (50 reviews) | J35: 555 S IL Route 83 Elmhurst, IL 60126
A36: 2015 Toyota Prius v Three | B36: Used | C36: 91,655 mi. | D36: 13980 | E36: {'Exterior color': ' Attitude Black ', 'Interior color': 'Gray ', 'Drivetrain': 'Front-wheel Drive ', 'MPG': ' 44â€“40Based on EPA mileage ratings. Use for comparison purposes only. Actual mileage will vary depending on driving conditions, driving habits, vehicle maintenance, and other factors.', 'Fuel type': 'Gasoline ', 'Transmission': 'Automatic', 'Engine': '1.8L I-4 DOHC, VVT-i variable valve control, regular unleaded, e', 'VIN': ' JTDZN3EUXFJ016005 ', 'Stock #': ' 6069 ', 'Mileage': ' 91,655 mi. '} | F36: {'Accidents or damage': 'None reported', 'Clean title': 'Yes', '1-owner vehicle': 'No', 'Personal use only': 'Yes', 'Open recall': 'At least 1 open recall reported'} | G36: {'Comfort': '5.0', 'Interior': '5.0', 'Performance': '5.0', 'Value': '5.0', 'Exterior': '5.0', 'Reliability': '5.0'} | H36: 4.6 | I36: (189 reviews) | J36: 1886 S Elmhurst Rd Mt Prospect, IL 60056
A37: 2024 Mercedes-Benz AMG EQS Base | B37: New | C37: 6 mi. | D37: $152,800MSRP $152,800 | E37: {'Exterior color': ' Moonlight White ', 'Interior color': 'Black ', 'Drivetrain': 'All-wheel Drive ', 'Transmission': '1-Speed Automatic', 'Engine': 'Electric', 'VIN': ' W1KCG5FB6RA047125 ', 'Stock #': ' 64-592 ', 'Mileage': ' 6 mi. '} | F37: {} | G37: {} | H37: 4.7 | I37: (2,850 reviews) | J37: 1600 Frontage Rd Northbrook, IL 60062
A38: 2012 Toyota Prius v Two | B38: Used | C38: 168,725 mi. | D38: 9945 | E38: {'Exterior color': ' Magnetic Gray Metallic ', 'Interior color': 'GRAY ', 'Drivetrain': 'Front-wheel Drive ', 'MPG': ' 0â€“0Based on EPA mileage ratings. Use for comparison purposes only. Actual mileage will vary depending on driving conditions, driving habits, vehicle maintenance, and other factors.', 'Fuel type': 'Hybrid ', 'Transmission': 'Automatic', 'Engine': '1.8L 4 CYLINDER', 'VIN': ' JTDZN3EU5C3136231 ', 'Stock #': ' 36231 ', 'Mileage': ' 168,725 mi. '} | F38: {'Accidents or damage': 'None reported', '1-owner vehicle': 'Yes', 'Personal use only': 'Yes'} | G38: {'Comfort': '5.0', 'Interior': '5.0', 'Performance': '5.0', 'Value': '5.0', 'Exterior': '5.0', 'Reliability': 'â€”'} | H38: 4.2 | I38: (20 reviews) | J38: 350 S Lalonde Ave ADDISON, IL 60101
A39: 2008 Chrysler Sebring Touring | B39: Used | C39: 70,974 mi. | D39: 11950 | E39: {'Exterior color': ' Silver Steel Metallic Clearcoat ', 'Interior color': 'Dark Slate Gray/Light Slate Gray ', 'Drivetrain': 'Front-wheel Drive ', 'MPG': ' 18â€“26Based on EPA mileage ratings. Use for comparison purposes only. Actual mileage will vary depending on driving conditions, driving habits, vehicle maintenance, and other factors.', 'Fuel type': 'E85 Flex Fuel ', 'Transmission': 'Automatic', 'Engine': '2.7L V-6 DOHC, engine with 189HP', 'VIN': ' 1C3LC55R88N615598 ', 'Stock #': ' N615598 ', 'Mileage': ' 70,974 mi. '} | F39: {'Accidents or damage': 'None reported', '1-owner vehicle': 'No', 'Personal use only': 'Yes'} | G39: {} | H39: 4.6 | I39: (127 reviews) | J39: 1030 Republic Dr Addison, IL 60101
A40: 2007 Jeep Commander Sport | B40: Used | C40: 173,694 mi. | D40: $4,550$400 price drop | E40: {'Exterior color': ' Light Graystone Pearlcoat ', 'Interior color': 'Khaki ', 'Drivetrain': 'Four-wheel Drive ', 'MPG': ' 16â€“19Based on EPA mileage ratings. Use for comparison purposes only. Actual mileage will vary depending on driving conditions, driving habits, vehicle maintenance, and other factors.', 'Fuel type': 'Gasoline ', 'Transmission': 'Automatic', 'Engine': 'Power Tech 3.7L V-6 regular unleaded, engine with 210HP', 'VIN': ' 1J8HG48K37C510145 ', 'Stock #': ' B-329 ', 'Mileage': ' 173,694 mi. '} | F40: {'Accidents or damage': 'At least 1 accident or damage reported', 'Clean title': 'Yes', '1-owner vehicle': 'No', 'Personal use only': 'Yes'} | G40: {} | J40: 11S344 Jeans Road Lemont, IL 60439
A41: 2017 INFINITI Q60 3.0T Premium | B41: Used | C41: 111,586 mi. | D41: 17995 | E41: {'Exterior color': ' Gray ', 'Interior color': 'Gray ', 'Drivetrain': 'All-wheel Drive ', 'MPG': ' 19â€“27Based on EPA mileage ratings. Use for comparison purposes only. Actual mileage will vary depending on driving conditions, driving habits, vehicle maintenance, and other factors.', 'Fuel type': 'Gasoline ', 'Transmission': '7-Speed Automatic', 'Engine': '3.0L V6 24V GDI DOHC Twin Turbo', 'VIN': ' JN1EV7ELXHM554222 ', 'Stock #': ' 554222 ', 'Mileage': ' 111,586 mi. '} | F41: {'Accidents or damage': 'At least 1 accident or damage reported', '1-owner vehicle': 'No', 'Personal use only': 'No'} | G41: {} | J41: 454 East North Avenue Lombard, IL 60148
A42: 2010 Lexus HS 250h Premium | B42: Used | C42: 128,900 mi. | D42: 9995 | E42: {'Exterior color': ' Black Opal Mica ', 'Interior color': 'Black ', 'Drivetrain': 'Front-wheel Drive ', 'MPG': ' 35â€“34Based on EPA mileage ratings. Use for comparison purposes only. Actual mileage will vary depending on driving conditions, driving habits, vehicle maintenance, and other factors.', 'Fuel type': 'Hybrid ', 'Transmission': 'Automatic', 'Engine': '2.4L DOHC SFI 16-valve Atkinson cycle I4 engine -inc: variable v', 'VIN': ' JTHBB1BA9A2007709 ', 'Stock #': ' 102100 ', 'Mileage': ' 128,900 mi. '} | F42: {'Accidents or damage': 'None reported', 'Clean title': 'Yes', '1-owner vehicle': 'No', 'Personal use only': 'Yes'} | G42: {'Comfort': '5.0', 'Interior': '5.0', 'Performance': '5.0', 'Value': '5.0', 'Exterior': '5.0', 'Reliability': '5.0'} | H42: 4.1 | I42: (49 reviews) | J42: 367 S Rohlwing Rd Addison, IL 60101
A43: 2015 Porsche Cayman S | B43: Used | C43: 48,163 mi. | D43: 52985 | E43: {'Exterior color': ' Black ', 'Interior color': 'Beige ', 'Drivetrain': 'Rear-wheel Drive ', 'MPG': ' 21â€“30Based on EPA mileage ratings. Use for comparison purposes only. Actual mileage will vary depending on driving conditions, driving habits, vehicle maintenance, and other factors.', 'Fuel type': 'Gasoline ', 'Transmission': 'Manual', 'Engine': '3.4L H-6 gasoline direct injection, DOHC, VarioCam variable valv', 'VIN': ' WP0AB2A82FK184482 ', 'Stock #': ' B15482801 ', 'Mileage': ' 48,163 mi. '} | F43: {'Accidents or damage': 'None reported', 'Clean title': 'Yes', '1-owner vehicle': 'No', 'Personal use only': 'Yes'} | G43: {} | H43: 4.2 | I43: (14 reviews) | J43: 1644 Ogden Ave Downers Grove, IL 60515
A44: 2013 INFINITI EX37 Journey | B44: Used | C44: 162,296 mi. | D44: 8888 | E44: {'Exterior color': ' Black Obsidian ', 'Interior color': 'Black ', 'Drivetrain': 'All-wheel Drive ', 'MPG': ' 17â€“24Based on EPA mileage ratings. Use for comparison purposes only. Actual mileage will vary depending on driving conditions, driving habits, vehicle maintenance, and other factors.', 'Fuel type': 'Gasoline ', 'Transmission': '7-Speed Automatic', 'Engine': '3.7L V6 24V MPFI DOHC', 'VIN': ' JN1BJ0HR4DM482367 ', 'Stock #': ' D-1778 ', 'Mileage': ' 162,296 mi. '} | F44: {'Accidents or damage': 'None reported', '1-owner vehicle': 'Yes', 'Personal use only': 'Yes'} | G44: {} | H44: 1.3 | I44: (32 reviews) | J44: 1543 Ogden Ave Downers Grove, IL 60515
A45: 2008 Lexus RX 400h | B45: Used | C45: 167,082 mi. | D45: 7777 | E45: {'Exterior color': ' Red ', 'Interior color': 'Beige ', 'Drivetrain': 'All-wheel Drive ', 'MPG': ' 26â€“24Based on EPA mileage ratings. Use for comparison purposes only. Actual mileage will vary depending on driving conditions, driving habits, vehicle maintenance, and other factors.', 'Fuel type': 'Hybrid ', 'Transmission': 'Automatic CVT', 'Engine': '3.3L V6 24V MPFI DOHC Hybrid', 'VIN': ' JTJHW31UX82050311 ', 'Stock #': ' D-1808 ', 'Mileage': ' 167,082 mi. '} | F45: {'Accidents or damage': 'At least 1 accident or damage reported', '1-owner vehicle': 'Yes', 'Personal use only': 'Yes'} | G45: {'Comfort': '4.0', 'Interior': '5.0', 'Performance': '4.0', 'Value': '5.0', 'Exterior': '5.0', 'Reliability': '5.0'} | H45: 1.3 | I45: (32 reviews) | J45: 1543 Ogden Ave Downers Grove, IL 60515
A46: 2012 Toyota Prius v Two | B46: Used | C46: 67,422 mi. | D46: 14999 | E46: {'Exterior color': ' Classic Silver Metallic ', 'Interior color': 'Black ', 'Drivetrain': 'Front-wheel Drive ', 'MPG': ' 44â€“40Based on EPA mileage ratings. Use for comparison purposes only. Actual mileage will vary depending on driving conditions, driving habits, vehicle maintenance, and other factors.', 'Fuel type': 'Gasoline ', 'Transmission': 'Automatic', 'Engine': '1.8L I-4 DOHC, VVT-i variable valve control, regular unleaded, e', 'VIN': ' JTDZN3EU5C3052524 ', 'Stock #': ' 052524 ', 'Mileage': ' 67,422 mi. '} | F46: {'Accidents or damage': 'At least 1 accident or damage reported', 'Clean title': 'Yes', '1-owner vehicle': 'Yes', 'Personal use only': 'Yes'} | G46: {'Comfort': '5.0', 'Interior': '5.0', 'Performance': '5.0', 'Value': '5.0', 'Exterior': '5.0', 'Reliability': 'â€”'} | J46: 3201 167th St Hazel Crest, IL 60429
A47: 2007 Toyota Yaris Base | B47: Used | C47: 67,300 mi. | D47: 9975 | E47: {'Exterior color': ' Pacific Blue Metallic ', 'Interior color': 'Dark Charcoal ', 'Drivetrain': 'Front-wheel Drive ', 'MPG': ' 34â€“40Based on EPA mileage ratings. Use for comparison purposes only. Actual mileage will vary depending on driving conditions, driving habits, vehicle maintenance, and other factors.', 'Fuel type': 'Gasoline ', 'Transmission': 'â€“', 'Engine': '1.5L DOHC SFI 16-valve VVT-i 4-cyl engine w/Toyota direct inject', 'VIN': ' JTDBT923071063907 ', 'Stock #': ' 96521400 ', 'Mileage': ' 67,300 mi. '} | F47: {'Accidents or damage': 'None reported', 'Clean title': 'Yes', '1-owner vehicle': 'Yes', 'Personal use only': 'No'} | G47: {} | H47: 4.1 | I47: (49 reviews) | J47: 367 S Rohlwing Rd Addison, IL 60101
A48: 2017 Mercedes-Benz AMG S 63 Base 4MATIC | B48: Used | C48: 5,350 mi. | D48: 69800 | E48: {'Exterior color': ' Magnetite Black Metallic ', 'Interior color': 'Black ', 'Drivetrain': 'All-wheel Drive ', 'MPG': ' 15â€“23Based on EPA mileage ratings. Use for comparison purposes only. Actual mileage will vary depending on driving conditions, driving habits, vehicle maintenance, and other factors.', 'Fuel type': 'Gasoline ', 'Transmission': '7-Speed Automatic', 'Engine': '5.5L V8 32V GDI DOHC Twin Turbo', 'VIN': ' WDDUG7JB8HA294832 ', 'Stock #': ' PGD0082 ', 'Mileage': ' 5,350 mi. '} | F48: {'Accidents or damage': 'At least 1 accident or damage reported', '1-owner vehicle': 'Yes', 'Personal use only': 'No'} | G48: {'Comfort': '5.0', 'Interior': '5.0', 'Performance': '5.0', 'Value': '5.0', 'Exterior': '5.0', 'Reliability': '5.0'} | J48: 1866 Ogden Avenue Downers Grove, IL 60515
A49: 2016 BMW M235 i | B49: Used | C49: 111,166 mi. | D49: 18888 | E49: {'Exterior color': ' White ', 'Interior color': 'Coral Red / Black ', 'Drivetrain': 'Rear-wheel Drive ', 'MPG': ' 20â€“31Based on EPA mileage ratings. Use for comparison purposes only. Actual mileage will vary depending on driving conditions, driving habits, vehicle maintenance, and other factors.', 'Fuel type': 'Gasoline ', 'Transmission': '8-Speed Automatic', 'Engine': '3.0L I6 24V GDI DOHC Turbo', 'VIN': ' WBA1J7C55GV359209 ', 'Stock #': ' D-1793 ', 'Mileage': ' 111,166 mi. '} | F49: {'Accidents or damage': 'None reported', '1-owner vehicle': 'No', 'Personal use only': 'Yes'} | G49: {} | H49: 1.3 | I49: (32 reviews) | J49: 1543 Ogden Ave Downers Grove, IL 60515
A50: 2011 Ford E250 Cargo | B50: Used | C50: 133,990 mi. | D50: 10990 | E50: {'Exterior color': ' White ', 'Interior color': 'Gray ', 'Drivetrain': 'Rear-wheel Drive ', 'MPG': ' 16â€“16Based on EPA mileage ratings. Use for comparison purposes only. Actual mileage will vary depending on driving conditions, driving habits, vehicle maintenance, and other factors.', 'Fuel type': 'E85 Flex Fuel ', 'Transmission': 'Automatic 4-Speed', 'Engine': '5.4L V8', 'VIN': ' 1FTNE2EL3BDA30854 ', 'Stock #': ' A10381 ', 'Mileage': ' 133,990 mi. '} | F50: {'Accidents or damage': 'At least 1 accident or damage reported', '1-owner vehicle': 'Yes', 'Personal use only': 'No'} | G50: {} | H50: 3.7 | I50: (84 reviews) | J50: 1233 Ogden Ave Downers Grove, IL 60515
A51: 2012 Aston Martin DB9 Volante | B51: Used | C51: 20,038 mi. | D51: 67455 | E51: {'Exterior color': ' Hammerhead Silver ', 'Interior color': 'Gray ', 'Drivetrain': 'Rear-wheel Drive ', 'MPG': ' 13â€“20Based on EPA mileage ratings. Use for comparison purposes only. Actual mileage will vary depending on driving conditions, driving habits, vehicle maintenance, and other factors.', 'Fuel type': 'Gasoline ', 'Transmission': '6-Speed Automatic', 'Engine': '6.0L V12 48V MPFI DOHC', 'VIN': ' SCFFDABE8CGB14387 ', 'Stock #': ' 2611 ', 'Mileage': ' 20,038 mi. '} | F51: {'Accidents or damage': 'None reported', '1-owner vehicle': 'Yes', 'Personal use only': 'Yes'} | G51: {'Comfort': '5.0', 'Interior': '5.0', 'Performance': '5.0', 'Value': '5.0', 'Exterior': '5.0', 'Reliability': '5.0'} | H51: 4.3 | I51: (71 reviews) | J51: 2401 Warrenville Rd Downers Grove, IL 60515
A52: 2022 Volkswagen Golf R 2.0T | B52: Used | C52: 12,959 mi. | D52: 43949 | E52: {'Exterior color': ' Pure White ', 'Interior color': 'Blue ', 'Drivetrain': 'All-wheel Drive ', 'MPG': ' 23â€“30Based on EPA mileage ratings. Use for comparison purposes only. Actual mileage will vary depending on driving conditions, driving habits, vehicle maintenance, and other factors.', 'Fuel type': 'Gasoline ', 'Transmission': '7-Speed Automatic', 'Engine': '2.0L I4 16V GDI DOHC Turbo', 'VIN': ' WVWEB7CD2NW170050 ', 'Stock #': ' 3056 ', 'Mileage': ' 12,959 mi. '} | F52: {'Accidents or damage': 'None reported', '1-owner vehicle': 'No', 'Personal use only': 'No'} | G52: {'Comfort': '5.0', 'Interior': '5.0', 'Performance': '5.0', 'Value': '5.0', 'Exterior': '4.0', 'Reliability': '5.0'} | H52: 4.3 | I52: (71 reviews) | J52: 2401 Warrenville Rd Downers Grove, IL 60515
A53: 2014 Cadillac XTS Luxury | B53: Used | C53: 44,500 mi. | D53: 16000 | E53: {'Exterior color': ' Graphite Metallic ', 'Interior color': 'Medium Titanium / Jet Black ', 'Drivetrain': 'Front-wheel Drive ', 'MPG': ' 18â€“28Based on EPA mileage ratings. Use for comparison purposes only. Actual mileage will vary depending on driving conditions, driving habits, vehicle maintenance, and other factors.', 'Fuel type': 'Gasoline ', 'Transmission': '6-Speed Automatic', 'Engine': '3.6L V6 24V GDI DOHC', 'VIN': ' 2G61M5S39E9237180 ', 'Stock #': ' J240122B ', 'Mileage': ' 44,500 mi. '} | F53: {'Accidents or damage': 'At least 1 accident or damage reported', '1-owner vehicle': 'No', 'Personal use only': 'Yes'} | G53: {} | H53: 4.7 | I53: (1,303 reviews) | J53: 17225 Torrence Ave Lansing, IL 60438
A54: 2008 Lexus RX 400h Base | B54: Used | C54: 186,000 mi. | D54: 6500 | E54: {'Exterior color': ' Silver ', 'Interior color': 'Beige ', 'Drivetrain': 'All-wheel Drive ', 'Fuel type': 'Hybrid ', 'Transmission': 'A/T', 'Engine': '208.0HP 3.3L V6 Cylinder Engine Gas/Electric Hybrid', 'VIN': ' JTJHW31U082047045 ', 'Mileage': ' 186,000 mi. '} | F54: {'Accidents or damage': 'None reported', 'Clean title': 'Yes', '1-owner vehicle': 'No', 'Personal use only': 'Yes'} | G54: {'Comfort': '4.0', 'Interior': '5.0', 'Performance': '4.0', 'Value': '5.0', 'Exterior': '5.0', 'Reliability': '5.0'}
A55: 2013 Toyota Prius v Five | B55: Used | C55: 92,754 mi. | D55: $11,700$800 price drop | E55: {'Exterior color': ' Blue ', 'Interior color': 'Bisque ', 'Drivetrain': 'Front-wheel Drive ', 'MPG': ' 44â€“40Based on EPA mileage ratings. Use for comparison purposes only. Actual mileage will vary depending on driving conditions, driving habits, vehicle maintenance, and other factors.', 'Fuel type': 'Gasoline ', 'Transmission': 'CVT', 'Engine': '1.8L 4-Cylinder DOHC 16V VVT-i Aluminum', 'VIN': ' JTDZN3EUXD3266975 ', 'Stock #': ' KBB1801 ', 'Mileage': ' 92,754 mi. '} | F55: {'Accidents or damage': 'At least 1 accident or damage reported', '1-owner vehicle': 'No', 'Personal use only': 'Yes'} | G55: {'Comfort': '5.0', 'Interior': '4.0', 'Performance': '4.0', 'Value': '5.0', 'Exterior': '4.0', 'Reliability': '5.0'} | H55: 4.8 | I55: (1,926 reviews) | J55: 17220 Torrence Ave Lansing, IL 60438
A56: 2014 Chevrolet Corvette Stingray Z51 | B56: Used | C56: 60,261 mi. | D56: 38595 | E56: {'Exterior color': ' Cyber Gray Metallic ', 'Interior color': 'Jet Black ', 'Drivetrain': 'Rear-wheel Drive ', 'MPG': ' 17â€“29Based on EPA mileage ratings. Use for comparison purposes only. Actual mileage will vary depending on driving conditions, driving habits, vehicle maintenance, and other factors.', 'Fuel type': 'Gasoline ', 'Transmission': '6-Speed Automatic', 'Engine': '6.2L V8 16V GDI OHV', 'VIN': ' 1G1YH2D72E5125406 ', 'Stock #': ' 2928 ', 'Mileage': ' 60,261 mi. '} | F56: {'Accidents or damage': 'None reported', '1-owner vehicle': 'No', 'Personal use only': 'Yes'} | G56: {'Comfort': '5.0', 'Interior': '5.0', 'Performance': '5.0', 'Value': '5.0', 'Exterior': '5.0', 'Reliability': '5.0'} | H56: 4.3 | I56: (71 reviews) | J56: 2401 Warrenville Rd Downers Grove, IL 60515
A57: 2005 Ford Excursion Eddie Bauer | B57: Used | C57: 304,425 mi. | D57: 5997 | E57: {'Exterior color': ' Oxford White ', 'Interior color': 'Medium Pebble ', 'Drivetrain': 'Four-wheel Drive ', 'MPG': ' 0â€“0Based on EPA mileage ratings. Use for comparison purposes only. Actual mileage will vary depending on driving conditions, driving habits, vehicle maintenance, and other factors.', 'Fuel type': 'Gasoline ', 'Transmission': 'Automatic', 'Engine': 'Triton 6.8L V-10 regular unleaded, engine with 310HP', 'VIN': ' 1FMNU45S05EA84354 ', 'Stock #': ' C-EXCURSION ', 'Mileage': ' 304,425 mi. '} | F57: {'Accidents or damage': 'None reported', 'Clean title': 'Yes', '1-owner vehicle': 'Yes', 'Personal use only': 'Yes'} | G57: {} | H57: 4.8 | I57: (313 reviews) | J57: 17651 Oak Park Ave Tinley Park, IL 60477
E58: {} | F58: {} | G58: {}
A59: 2021 Ford Escape SE | B59: Used | C59: 32,395 mi. | D59: 21987 | E59: {'Exterior color': ' Bronze Fire Metallic ', 'Interior color': 'Dark Earth Gray ', 'Drivetrain': 'All-wheel Drive ', 'MPG': ' 26â€“31Based on EPA mileage ratings. Use for comparison purposes only. Actual mileage will vary depending on driving conditions, driving habits, vehicle maintenance, and other factors.', 'Fuel type': 'Gasoline ', 'Transmission': '8-Speed Automatic', 'Engine': '1.5L I3 12V PDI DOHC Turbo', 'VIN': ' 1FMCU9G67MUA25830 ', 'Stock #': ' 21359P ', 'Mileage': ' 32,395 mi. '} | F59: {'Accidents or damage': 'At least 1 accident or damage reported', '1-owner vehicle': 'Yes', 'Personal use only': 'Yes'} | G59: {} | H59: 4.6 | I59: (427 reviews) | J59: 18033 S Halsted St Homewood, IL 60430
A60: 2007 Mazda Mazda6 i Sport | B60: Used | C60: 151,531 mi. | D60: 3777 | E60: {'Exterior color': ' MAROON ', 'Interior color': 'â€“ ', 'Drivetrain': 'Front-wheel Drive ', 'MPG': ' 24â€“0Based on EPA mileage ratings. Use for comparison purposes only. Actual mileage will vary depending on driving conditions, driving habits, vehicle maintenance, and other factors.', 'Fuel type': 'Gasoline ', 'Transmission': 'Automatic', 'Engine': '2.3L I-4 DOHC, variable valve control, regular unleaded, engine', 'VIN': ' 1YVHP80C875M52664 ', 'Stock #': ' B991 ', 'Mileage': ' 151,531 mi. '} | F60: {'Accidents or damage': 'None reported', 'Clean title': 'Yes', '1-owner vehicle': 'No', 'Personal use only': 'Yes'} | G60: {} | H60: 4.8 | I60: (313 reviews) | J60: 17651 Oak Park Ave Tinley Park, IL 60477
A61: 2018 Honda Clarity Plug-In Hybrid Touring | B61: Used | C61: 93,204 mi. | D61: 17999 | E61: {'Exterior color': ' Black ', 'Interior color': 'Black ', 'Drivetrain': 'Front-wheel Drive ', 'MPG': ' â€“', 'Fuel type': 'Hybrid ', 'Transmission': 'Automatic CVT', 'Engine': '1.5L I4 16V MPFI DOHC Hybrid', 'VIN': ' JHMZC5F30JC018879 ', 'Stock #': ' HP3255 ', 'Mileage': ' 93,204 mi. '} | F61: {'Accidents or damage': 'None reported', '1-owner vehicle': 'Yes', 'Personal use only': 'Yes', 'Open recall': 'At least 1 open recall reported'} | G61: {'Comfort': '1.0', 'Interior': '1.0', 'Performance': '1.0', 'Value': '1.0', 'Exterior': '1.0', 'Reliability': '1.0'} | H61: 4.8 | I61: (4,938 reviews) | J61: 4475 Lincoln Ave Lisle, IL 60532
A62: 2007 Lincoln Town Car Signature | B62: Used | C62: 40,145 mi. | D62: 16995 | E62: {'Exterior color': ' Vibrant White ', 'Interior color': 'Black ', 'Drivetrain': 'Rear-wheel Drive ', 'MPG': ' 17â€“25Based on EPA mileage ratings. Use for comparison purposes only. Actual mileage will vary depending on driving conditions, driving habits, vehicle maintenance, and other factors.', 'Fuel type': 'â€“ ', 'Transmission': '4-Speed Automatic', 'Engine': '4.6L V8 16V MPFI SOHC', 'VIN': ' 1LNHM81V57Y608829 ', 'Stock #': ' AS17338 ', 'Mileage': ' 40,145 mi. '} | F62: {'Accidents or damage': 'At least 1 accident or damage reported', '1-owner vehicle': 'No', 'Personal use only': 'Yes'} | G62: {'Comfort': '5.0', 'Interior': '5.0', 'Performance': '5.0', 'Value': '5.0', 'Exterior': '5.0', 'Reliability': '5.0'} | H62: 4.4 | I62: (66 reviews) | J62: 545 E. North Ave. Carol Stream, IL 60188
A63: 2007 Lincoln Town Car Signature Limited | B63: Used | C63: 104,736 mi. | D63: 9995 | E63: {'Exterior color': ' Cashmere Tri-Coat ', 'Interior color': 'Light Camel ', 'Drivetrain': 'Rear-wheel Drive ', 'MPG': ' 17â€“25Based on EPA mileage ratings. Use for comparison purposes only. Actual mileage will vary depending on driving conditions, driving habits, vehicle maintenance, and other factors.', 'Fuel type': 'â€“ ', 'Transmission': '4-Speed Automatic', 'Engine': '4.6L V8 16V MPFI SOHC', 'VIN': ' 1LNHM82V87Y608757 ', 'Stock #': ' AS08757 ', 'Mileage': ' 104,736 mi. '} | F63: {'Accidents or damage': 'None reported', '1-owner vehicle': 'No', 'Personal use only': 'No'} | G63: {'Comfort': '5.0', 'Interior': '5.0', 'Performance': '5.0', 'Value': '5.0', 'Exterior': '5.0', 'Reliability': '5.0'} | H63: 4.4 | I63: (66 reviews) | J63: 545 E. North Ave. Carol Stream, IL 60188
A64: 2007 Saturn Sky Red Line | B64: Used | C64: 35,052 mi. | D64: 18995 | E64: {'Exterior color': ' Midnight Blue ', 'Interior color': 'Tan ', 'Drivetrain': 'Rear-wheel Drive ', 'MPG': ' â€“', 'Fuel type': 'Gasoline ', 'Transmission': '5-Speed Manual', 'Engine': '2.0L I4 16V GDI DOHC Turbo', 'VIN': ' 1G8MG35X47Y110785 ', 'Stock #': ' AS17784 ', 'Mileage': ' 35,052 mi. '} | F64: {'Accidents or damage': 'None reported', '1-owner vehicle': 'No', 'Personal use only': 'Yes', 'Open recall': 'At least 1 open recall reported'} | G64: {} | H64: 4.4 | I64: (66 reviews) | J64: 545 E. North Ave. Carol Stream, IL 60188
A65: 2009 Saturn Sky Base | B65: Used | C65: 26,514 mi. | D65: 15995 | E65: {'Exterior color': ' Silver Pearl ', 'Interior color': 'Red ', 'Drivetrain': 'Rear-wheel Drive ', 'MPG': ' â€“', 'Fuel type': 'Gasoline ', 'Transmission': '5-Speed Automatic', 'Engine': '2.4L I4 16V MPFI DOHC', 'VIN': ' 1G8MN35B09Y105967 ', 'Stock #': ' AS16784 ', 'Mileage': ' 26,514 mi. '} | F65: {'Accidents or damage': 'At least 1 accident or damage reported', '1-owner vehicle': 'No', 'Personal use only': 'Yes'} | G65: {} | H65: 4.4 | I65: (66 reviews) | J65: 545 E. North Ave. Carol Stream, IL 60188
A66: 2020 Subaru WRX STI Base | B66: Used | C66: 27,861 mi. | D66: 35995 | E66: {'Exterior color': ' WR Blue Pearl ', 'Interior color': 'Black ', 'Drivetrain': 'All-wheel Drive ', 'MPG': ' 16â€“22Based on EPA mileage ratings. Use for comparison purposes only. Actual mileage will vary depending on driving conditions, driving habits, vehicle maintenance, and other factors.', 'Fuel type': 'Gasoline ', 'Transmission': '6-Speed Manual', 'Engine': '2.5L H4 16V MPFI DOHC Turbo', 'VIN': ' JF1VA2E66L9808936 ', 'Stock #': ' AS17519 ', 'Mileage': ' 27,861 mi. '} | F66: {'Accidents or damage': 'None reported', '1-owner vehicle': 'No', 'Personal use only': 'Yes', 'Open recall': 'At least 1 open recall reported'} | G66: {'Comfort': '5.0', 'Interior': '5.0', 'Performance': '5.0', 'Value': '5.0', 'Exterior': '5.0', 'Reliability': '5.0'} | H66: 4.4 | I66: (66 reviews) | J66: 545 E. North Ave. Carol Stream, IL 60188
A67: 2018 Porsche 718 Cayman Base | B67: Used | C67: 12,679 mi. | D67: 53995 | E67: {'Exterior color': ' Night Blue Metallic ', 'Interior color': 'Black ', 'Drivetrain': 'Rear-wheel Drive ', 'MPG': ' 21â€“28Based on EPA mileage ratings. Use for comparison purposes only. Actual mileage will vary depending on driving conditions, driving habits, vehicle maintenance, and other factors.', 'Fuel type': 'Gasoline ', 'Transmission': '6-Speed Manual', 'Engine': '2.0L H4 16V GDI DOHC Turbo', 'VIN': ' WP0AA2A89JK262252 ', 'Stock #': ' AS17691 ', 'Mileage': ' 12,679 mi. '} | F67: {'Accidents or damage': 'None reported', '1-owner vehicle': 'No', 'Personal use only': 'Yes'} | G67: {'Comfort': '5.0', 'Interior': '5.0', 'Performance': '5.0', 'Value': '4.0', 'Exterior': '5.0', 'Reliability': '5.0'} | H67: 4.4 | I67: (66 reviews) | J67: 545 E. North Ave. Carol Stream, IL 60188
A68: 2013 INFINITI G37x Base | B68: Used | C68: 87,150 mi. | D68: 16961 | E68: {'Exterior color': ' Lapis Blue ', 'Interior color': 'Stone ', 'Drivetrain': 'All-wheel Drive ', 'MPG': ' 18â€“25Based on EPA mileage ratings. Use for comparison purposes only. Actual mileage will vary depending on driving conditions, driving habits, vehicle maintenance, and other factors.', 'Fuel type': 'Gasoline ', 'Transmission': '7-Speed Automatic with Manual Shift', 'Engine': 'VQ 3.7L V-6 DOHC, variable valve control, premium unleaded, engi', 'VIN': ' JN1CV6EL9DM981001 ', 'Stock #': ' W174467A ', 'Mileage': ' 87,150 mi. '} | F68: {'Accidents or damage': 'At least 1 accident or damage reported', '1-owner vehicle': 'No', 'Personal use only': 'No'} | G68: {} | H68: 4.7 | I68: (3,096 reviews) | J68: 700 W Dundee Rd Wheeling, IL 60090
A69: 2004 Ford Excursion Eddie Bauer | B69: Used | C69: 204,560 mi. | D69: $15,800$1,000 price drop | E69: {'Exterior color': ' Oxford White ', 'Interior color': 'Medium Parchment ', 'Drivetrain': 'Four-wheel Drive ', 'MPG': ' 0â€“0Based on EPA mileage ratings. Use for comparison purposes only. Actual mileage will vary depending on driving conditions, driving habits, vehicle maintenance, and other factors.', 'Fuel type': 'Diesel ', 'Transmission': 'Automatic', 'Engine': 'Powerstroke 6L V-8 diesel direct injection, intercooled turbo, d', 'VIN': ' 1FMSU45P14EA87843 ', 'Stock #': ' A87843 ', 'Mileage': ' 204,560 mi. '} | F69: {'Accidents or damage': 'None reported', 'Clean title': 'Yes', '1-owner vehicle': 'No', 'Personal use only': 'Yes'} | G69: {} | J69: 1989 University Lane Unit J Lisle, IL 60532
A70: 2017 BMW X5 M Base | B70: Used | C70: 71,099 mi. | D70: 38995 | E70: {'Exterior color': ' Gray ', 'Interior color': 'Black ', 'Drivetrain': 'All-wheel Drive ', 'MPG': ' 14â€“19Based on EPA mileage ratings. Use for comparison purposes only. Actual mileage will vary depending on driving conditions, driving habits, vehicle maintenance, and other factors.', 'Fuel type': 'Gasoline ', 'Transmission': '8-Speed Automatic', 'Engine': '4.4L V8 32V GDI DOHC Twin Turbo', 'VIN': ' 5YMKT6C39H0U39337 ', 'Stock #': ' A2716 ', 'Mileage': ' 71,099 mi. '} | F70: {'Accidents or damage': 'At least 1 accident or damage reported', '1-owner vehicle': 'Yes', 'Personal use only': 'Yes'} | G70: {'Comfort': '4.0', 'Interior': '5.0', 'Performance': '5.0', 'Value': '4.0', 'Exterior': '5.0', 'Reliability': '5.0'} | H70: 4.1 | I70: (46 reviews) | J70: 27W333 North Ave IL West Chicago, IL 60185
A71: 2018 BMW 340 Gran Turismo i xDrive | B71: Used | C71: 91,475 mi. | D71: 22440 | E71: {'Exterior color': ' Black Sapphire Metallic ', 'Interior color': 'Oyster ', 'Drivetrain': 'All-wheel Drive ', 'MPG': ' 20â€“29Based on EPA mileage ratings. Use for comparison purposes only. Actual mileage will vary depending on driving conditions, driving habits, vehicle maintenance, and other factors.', 'Fuel type': 'Gasoline ', 'Transmission': '8-Speed Automatic', 'Engine': '3.0L I6 24V GDI DOHC Turbo', 'VIN': ' WBA8Y3C52JG451439 ', 'Stock #': ' 451439 ', 'Mileage': ' 91,475 mi. '} | F71: {'Accidents or damage': 'At least 1 accident or damage reported', 'Clean title': 'Yes', '1-owner vehicle': 'No', 'Personal use only': 'No'} | G71: {} | H71: 4.1 | I71: (60 reviews) | J71: 10926 southwest highway palos hills, IL 60465
A72: 2017 BMW M6 Base | B72: Used | C72: 14,826 mi. | D72: 78800 | E72: {'Exterior color': ' Space Gray Metallic ', 'Interior color': 'Black ', 'Drivetrain': 'Rear-wheel Drive ', 'MPG': ' 14â€“20Based on EPA mileage ratings. Use for comparison purposes only. Actual mileage will vary depending on driving conditions, driving habits, vehicle maintenance, and other factors.', 'Fuel type': 'Gasoline ', 'Transmission': '6-Speed Manual', 'Engine': '4.4L V8 32V GDI DOHC Twin Turbo', 'VIN': ' WBS6J9C5XHD934733 ', 'Stock #': ' 934733 ', 'Mileage': ' 14,826 mi. '} | F72: {'Accidents or damage': 'None reported', '1-owner vehicle': 'No', 'Personal use only': 'Yes'} | G72: {'Comfort': '5.0', 'Interior': '5.0', 'Performance': '5.0', 'Value': '4.0', 'Exterior': '5.0', 'Reliability': '5.0'} | H72: 4.7 | I72: (318 reviews) | J72: 2895 Ogden Ave Lisle, IL 60532
A73: 2019 Mercedes-Benz AMG CLS 53 S 4MATIC | B73: Used | C73: 38,545 mi. | D73: 48999 | E73: {'Exterior color': ' Gray ', 'Interior color': 'Black ', 'Drivetrain': 'All-wheel Drive ', 'MPG': ' 21â€“27Based on EPA mileage ratings. Use for comparison purposes only. Actual mileage will vary depending on driving conditions, driving habits, vehicle maintenance, and other factors.', 'Fuel type': 'Gasoline ', 'Transmission': '9-Speed Automatic', 'Engine': 'AMG 3L I-6 gasoline direct injection, DOHC, variable valve contr', 'VIN': ' WDD2J6BB9KA031693 ', 'Stock #': ' 25185G ', 'Mileage': ' 38,545 mi. '} | F73: {'Accidents or damage': 'None reported', '1-owner vehicle': 'Yes', 'Personal use only': 'Yes'} | G73: {} | H73: 4.5 | I73: (16 reviews) | J73: 2772 Skokie Valley Road Highland Park, IL 60035
A74: 2019 BMW M6 Gran Coupe Gran Coupe | B74: Used | C74: 31,010 mi. | D74: 53895 | E74: {'Exterior color': ' San Marino Blue Metallic ', 'Interior color': 'Black ', 'Drivetrain': 'Rear-wheel Drive ', 'MPG': ' 14â€“20Based on EPA mileage ratings. Use for comparison purposes only. Actual mileage will vary depending on driving conditions, driving habits, vehicle maintenance, and other factors.', 'Fuel type': 'Gasoline ', 'Transmission': '7-Speed Automatic with Auto-Shift', 'Engine': '4.4L V8 32V GDI DOHC Twin Turbo', 'VIN': ' WBS6E9C5XKG808463 ', 'Stock #': ' 808463 ', 'Mileage': ' 31,010 mi. '} | F74: {'Accidents or damage': 'None reported', '1-owner vehicle': 'No', 'Personal use only': 'Yes'} | G74: {'Comfort': '5.0', 'Interior': '5.0', 'Performance': '5.0', 'Value': '5.0', 'Exterior': '5.0', 'Reliability': 'â€”'} | J74: 641 Estes Ave Schaumburg, IL 60193
A75: 2003 Ford Excursion Limited | B75: Used | C75: 199,574 mi. | D75: $25,975$7,000 price drop | E75: {'Exterior color': ' Black Clearcoat ', 'Interior color': 'Medium Pebble ', 'Drivetrain': 'Four-wheel Drive ', 'MPG': ' 0â€“0Based on EPA mileage ratings. Use for comparison purposes only. Actual mileage will vary depending on driving conditions, driving habits, vehicle maintenance, and other factors.', 'Fuel type': 'Diesel ', 'Transmission': 'Automatic', 'Engine': 'Powerstroke 6L V-8 diesel direct injection, intercooled turbo, d', 'VIN': ' 1FMSU43P43EC31757 ', 'Stock #': ' B9213B ', 'Mileage': ' 199,574 mi. '} | F75: {'Accidents or damage': 'None reported', '1-owner vehicle': 'No', 'Personal use only': 'Yes'} | G75: {} | H75: 4.9 | I75: (5,683 reviews) | J75: 777 west dundee rd Arlington heights, IL 60004
A76: 2014 BMW M6 Base | B76: Used | C76: 78,188 mi. | D76: 28990 | E76: {'Exterior color': ' Blue ', 'Interior color': 'Black ', 'Drivetrain': 'Rear-wheel Drive ', 'MPG': ' 16â€“24Based on EPA mileage ratings. Use for comparison purposes only. Actual mileage will vary depending on driving conditions, driving habits, vehicle maintenance, and other factors.', 'Fuel type': 'Gasoline ', 'Transmission': 'Auto 7Spd DblCltch DrvLgc', 'Engine': 'V8, Twin Turbo, 4.4 Liter', 'VIN': ' WBSLZ9C50ED651197 ', 'Stock #': ' 651197A ', 'Mileage': ' 78,188 mi. '} | F76: {'Accidents or damage': 'At least 1 accident or damage reported', '1-owner vehicle': 'No', 'Personal use only': 'Yes'} | G76: {} | H76: 2.7 | I76: (613 reviews) | J76: 1600 Hicks Rd Rolling Meadows, IL 60008
A77: 2024 Lexus LC 500 Base | B77: New | C77: 0 mi. | D77: $115,425MSRP $115,425 | E77: {'Exterior color': ' Infrared ', 'Interior color': 'Black W/ Satin Metallic Trim ', 'Drivetrain': 'Rear-wheel Drive ', 'MPG': ' 15â€“0Based on EPA mileage ratings. Use for comparison purposes only. Actual mileage will vary depending on driving conditions, driving habits, vehicle maintenance, and other factors.', 'Fuel type': 'Gasoline ', 'Transmission': 'Automatic', 'Engine': '5L V-8 port/direct injection, DOHC, VVT-i variable valve control', 'VIN': ' JTHMPAAY4RA109302 ', 'Stock #': ' 240509 ', 'Mileage': ' 0 mi. '} | F77: {} | G77: {} | H77: 4.9 | I77: (2,276 reviews) | J77: 350 E Golf Rd Schaumburg, IL 60173
A78: 2021 Audi SQ7 4.0T Premium Plus | B78: Used | C78: 60,120 mi. | D78: 49980 | E78: {'Exterior color': ' Florett Silver Metallic ', 'Interior color': 'Black ', 'Drivetrain': 'All-wheel Drive ', 'MPG': ' 15â€“21Based on EPA mileage ratings. Use for comparison purposes only. Actual mileage will vary depending on driving conditions, driving habits, vehicle maintenance, and other factors.', 'Fuel type': 'Gasoline ', 'Transmission': '8-Speed Automatic', 'Engine': '4.0L V8 32V GDI DOHC Twin Turbo', 'VIN': ' WA1AWBF75MD010857 ', 'Stock #': ' PA478A ', 'Mileage': ' 60,120 mi. '} | F78: {'Accidents or damage': 'At least 1 accident or damage reported', '1-owner vehicle': 'Yes', 'Personal use only': 'Yes'} | G78: {'Comfort': '5.0', 'Interior': '5.0', 'Performance': '5.0', 'Value': '5.0', 'Exterior': '5.0', 'Reliability': '5.0'} | H78: 4.7 | I78: (5,251 reviews) | J78: 1200 W Golf Rd Hoffman Estates, IL 60169
A79: 2016 McLaren 675LT Base | B79: Used | C79: 852 mi. | D79: $339,800$10,000 price drop | E79: {'Exterior color': ' Storm Grey ', 'Interior color': 'Carbon Black with McLaren Orange ', 'Drivetrain': 'Rear-wheel Drive ', 'MPG': ' 16â€“22Based on EPA mileage ratings. Use for comparison purposes only. Actual mileage will vary depending on driving conditions, driving habits, vehicle maintenance, and other factors.', 'Fuel type': 'Gasoline ', 'Transmission': '7-Speed Double Clutch', 'Engine': '3.8L Twin Turbo V8 666hp 516ft. lbs.', 'VIN': ' SBM11RAA3GW675109 ', 'Stock #': ' 20638 ', 'Mileage': ' 852 mi. '} | F79: {'Accidents or damage': 'None reported', '1-owner vehicle': 'No', 'Personal use only': 'No', 'Open recall': 'At least 1 open recall reported'} | G79: {'Comfort': '5.0', 'Interior': '5.0', 'Performance': '5.0', 'Value': '5.0', 'Exterior': '5.0', 'Reliability': '5.0'} | H79: 4.7 | I79: (715 reviews) | J79: 27w110 North Ave West Chicago, IL 60185
A80: 2017 Porsche 718 Cayman Base | B80: Used | C80: 41,311 mi. | D80: 45911 | E80: {'Exterior color': ' Black ', 'Interior color': 'Black ', 'Drivetrain': 'Rear-wheel Drive ', 'MPG': ' 21â€“28Based on EPA mileage ratings. Use for comparison purposes only. Actual mileage will vary depending on driving conditions, driving habits, vehicle maintenance, and other factors.', 'Fuel type': 'Gasoline ', 'Transmission': '7-Speed Automatic with Auto-Shift', 'Engine': '2.0L H4 16V GDI DOHC Turbo', 'VIN': ' WP0AA2A84HS270253 ', 'Stock #': ' 902552B ', 'Mileage': ' 41,311 mi. '} | F80: {'Accidents or damage': 'None reported', 'Clean title': 'Yes', '1-owner vehicle': 'No', 'Personal use only': 'Yes'} | G80: {'Comfort': '5.0', 'Interior': '5.0', 'Performance': '5.0', 'Value': '5.0', 'Exterior': '5.0', 'Reliability': '5.0'} | J80: 1951 N. Rand Road Palatine, IL 60074
A81: 2005 Nissan 350Z Touring | B81: Used | C81: 46,347 mi. | D81: 16500 | E81: {'Exterior color': ' Daytona Blue ', 'Interior color': 'Beige ', 'Drivetrain': 'Rear-wheel Drive ', 'MPG': ' 18â€“25Based on EPA mileage ratings. Use for comparison purposes only. Actual mileage will vary depending on driving conditions, driving habits, vehicle maintenance, and other factors.', 'Fuel type': 'Gasoline ', 'Transmission': '5-Speed Automatic', 'Engine': '3.5L V6 24V MPFI DOHC', 'VIN': ' JN1AZ36A45M759054 ', 'Stock #': ' 0070 ', 'Mileage': ' 46,347 mi. '} | F81: {'Accidents or damage': 'None reported', '1-owner vehicle': 'No', 'Personal use only': 'Yes'} | G81: {} | H81: 4.7 | I81: (34 reviews) | J81: 1823 Centrepoint Circle Naperville, IL 60563
A82: 2008 Audi TT 3.2 quattro | B82: Used | C82: 86,447 mi. | D82: 15500 | E82: {'Exterior color': ' Blue ', 'Interior color': 'Black ', 'Drivetrain': 'All-wheel Drive ', 'MPG': ' 24Based on EPA mileage ratings. Use for comparison purposes only. Actual mileage will vary depending on driving conditions, driving habits, vehicle maintenance, and other factors.', 'Fuel type': 'Gasoline ', 'Transmission': 'Automatic', 'Engine': '3.2L V6 24V MPFI DOHC', 'VIN': ' TRUDD38J581017067 ', 'Stock #': ' 5453 ', 'Mileage': ' 86,447 mi. '} | F82: {'Accidents or damage': 'None reported', '1-owner vehicle': 'No', 'Personal use only': 'Yes'} | G82: {} | H82: 4.4 | I82: (47 reviews) | J82: 2232 N Rand Rd Palatine, IL 60074
A83: 2009 INFINITI G37 Sport | B83: Used | C83: 94,164 mi. | D83: 15800 | E83: {'Exterior color': ' Moonlight White ', 'Interior color': 'Black ', 'Drivetrain': 'Rear-wheel Drive ', 'MPG': ' 17â€“25Based on EPA mileage ratings. Use for comparison purposes only. Actual mileage will vary depending on driving conditions, driving habits, vehicle maintenance, and other factors.', 'Fuel type': 'Gasoline ', 'Transmission': '6-Speed Manual', 'Engine': '3.7L V6 24V MPFI DOHC', 'VIN': ' JNKCV64E29M600868 ', 'Stock #': ' 00134 ', 'Mileage': ' 94,164 mi. '} | F83: {'Accidents or damage': 'None reported', '1-owner vehicle': 'No', 'Personal use only': 'Yes'} | G83: {} | H83: 4.7 | I83: (34 reviews) | J83: 1823 Centrepoint Circle Naperville, IL 60563
A84: 2005 Lotus Elise BASE | B84: Used | C84: 19,127 mi. | D84: 59800 | E84: {'Exterior color': ' GREY ', 'Interior color': 'â€“ ', 'Drivetrain': 'Rear-wheel Drive ', 'MPG': ' 23â€“25Based on EPA mileage ratings. Use for comparison purposes only. Actual mileage will vary depending on driving conditions, driving habits, vehicle maintenance, and other factors.', 'Fuel type': 'Gasoline ', 'Transmission': 'Manual', 'Engine': '1.8L I-4 DOHC, variable valve control, premium unleaded, engine', 'VIN': ' SCCPC11135HL34579 ', 'Stock #': ' 10181 ', 'Mileage': ' 19,127 mi. '} | F84: {'Accidents or damage': 'None reported', '1-owner vehicle': 'Yes', 'Personal use only': 'Yes'} | G84: {} | J84: 562 W 5th Ave Naperville, IL 60563
A85: 1988 Lincoln Town Car Signature | B85: Used | C85: 72,980 mi. | D85: 16950 | E85: {'Exterior color': ' ROSE ', 'Interior color': 'Rose ', 'Drivetrain': 'Rear-wheel Drive ', 'MPG': ' 17â€“24Based on EPA mileage ratings. Use for comparison purposes only. Actual mileage will vary depending on driving conditions, driving habits, vehicle maintenance, and other factors.', 'Fuel type': 'Gasoline ', 'Transmission': 'Automatic', 'Engine': '5.0L', 'VIN': ' 1LNBM82FXJY616316 ', 'Stock #': ' 0113 ', 'Mileage': ' 72,980 mi. '} | F85: {'Accidents or damage': 'None reported', 'Clean title': 'Yes', '1-owner vehicle': 'No', 'Personal use only': 'Yes'} | G85: {} | H85: 4.3 | I85: (12 reviews) | J85: 503 South Weber Road Bolingbrook, IL 60490
A86: 2010 BMW M6 Base (M7) | B86: Used | C86: 28,006 mi. | D86: 31995 | E86: {'Exterior color': ' Blue ', 'Interior color': 'Black ', 'Drivetrain': 'Rear-wheel Drive ', 'MPG': ' 11â€“17Based on EPA mileage ratings. Use for comparison purposes only. Actual mileage will vary depending on driving conditions, driving habits, vehicle maintenance, and other factors.', 'Fuel type': 'Gasoline ', 'Transmission': '7-Speed Automatic with Auto-Shift', 'Engine': '5.0L V10 40V MPFI DOHC', 'VIN': ' WBSEK9C50ACY80301 ', 'Stock #': ' 4211 ', 'Mileage': ' 28,006 mi. '} | F86: {'Accidents or damage': 'None reported', '1-owner vehicle': 'No', 'Personal use only': 'Yes'} | G86: {} | H86: 2.3 | I86: (54 reviews) | J86: 601 W. Roosevelt West Chicago, IL 60185
A87: 2022 Cadillac CT5-V V-Series Blackwing | B87: Used | C87: 58,099 mi. | D87: 73995 | E87: {'Exterior color': ' Black Raven ', 'Interior color': 'Jet Black With Jet Black Accents ', 'Drivetrain': 'Rear-wheel Drive ', 'MPG': ' 13â€“22Based on EPA mileage ratings. Use for comparison purposes only. Actual mileage will vary depending on driving conditions, driving habits, vehicle maintenance, and other factors.', 'Fuel type': 'Gasoline ', 'Transmission': 'Automatic', 'Engine': '6.2L V-8 gasoline direct injection, VVT variable valve control,', 'VIN': ' 1G6D35R6XN0810386 ', 'Stock #': ' 24197A ', 'Mileage': ' 58,099 mi. '} | F87: {'Accidents or damage': 'None reported', '1-owner vehicle': 'Yes', 'Personal use only': 'No'} | G87: {'Comfort': '5.0', 'Interior': '5.0', 'Performance': '5.0', 'Value': '5.0', 'Exterior': '5.0', 'Reliability': '5.0'} | H87: 4.6 | I87: (258 reviews) | J87: 1507 W. Ogden Ave. Naperville, IL 60540
A88: 2011 Audi TTS 2.0T Prestige quattro | B88: Used | C88: 90,001 mi. | D88: 15495 | E88: {'Exterior color': ' Black ', 'Interior color': 'Madras Brown ', 'Drivetrain': 'All-wheel Drive ', 'MPG': ' 21â€“29Based on EPA mileage ratings. Use for comparison purposes only. Actual mileage will vary depending on driving conditions, driving habits, vehicle maintenance, and other factors.', 'Fuel type': 'Gasoline ', 'Transmission': '6-Speed Automatic with Auto-Shift', 'Engine': '2.0L I4 16V GDI DOHC Turbo', 'VIN': ' TRU41AFKXB1004444 ', 'Stock #': ' 3981A ', 'Mileage': ' 90,001 mi. '} | F88: {'Accidents or damage': 'At least 1 accident or damage reported', '1-owner vehicle': 'No', 'Personal use only': 'Yes'} | G88: {} | H88: 2.3 | I88: (54 reviews) | J88: 601 W. Roosevelt West Chicago, IL 60185
A89: 1983 Ferrari 512 BERLINETTA | B89: Used | C89: 32,252 mi. | D89: $299,900$10,000 price drop | E89: {'Exterior color': ' Red ', 'Interior color': 'Beige ', 'Drivetrain': 'â€“ ', 'MPG': ' â€“', 'Fuel type': 'Gasoline ', 'Transmission': 'Manual', 'Engine': '12 Cylinder', 'VIN': ' ZFFJA09B000045131 ', 'Stock #': ' 45131 ', 'Mileage': ' 32,252 mi. '} | F89: {'Accidents or damage': 'None reported', '1-owner vehicle': 'No', 'Personal use only': 'No'} | G89: {} | J89: 990 N Shore Dr Lake Bluff, IL 60044
A90: 2019 Volkswagen Golf SportWagen 1.8T S | B90: Used | C90: 98,185 mi. | D90: $12,200$300 price drop | E90: {'Exterior color': ' Platinum Gray Metallic ', 'Interior color': 'Titan Black ', 'Drivetrain': 'All-wheel Drive ', 'MPG': ' 22â€“29Based on EPA mileage ratings. Use for comparison purposes only. Actual mileage will vary depending on driving conditions, driving habits, vehicle maintenance, and other factors.', 'Fuel type': 'Gasoline ', 'Transmission': '6-Speed Automatic with Auto-Shift', 'Engine': '1.8L I4 16V GDI DOHC Turbo', 'VIN': ' 3VW117AU3KM508875 ', 'Stock #': ' V048142A ', 'Mileage': ' 98,185 mi. '} | F90: {'Accidents or damage': 'None reported', '1-owner vehicle': 'No', 'Personal use only': 'No', 'Open recall': 'At least 1 open recall reported'} | G90: {'Comfort': '5.0', 'Interior': '5.0', 'Performance': '5.0', 'Value': '5.0', 'Exterior': '5.0', 'Reliability': '5.0'} | H90: 4.6 | I90: (2,401 reviews) | J90: 1111 N Clark St Chicago, IL 60610
A91: 2009 Rolls-Royce Phantom Coupe | B91: Used | C91: 52,756 mi. | D91: 139800 | E91: {'Exterior color': ' Diamond Black ', 'Interior color': 'Moccasin ', 'Drivetrain': 'Rear-wheel Drive ', 'MPG': ' 11â€“18Based on EPA mileage ratings. Use for comparison purposes only. Actual mileage will vary depending on driving conditions, driving habits, vehicle maintenance, and other factors.', 'Fuel type': 'Gasoline ', 'Transmission': '6-Speed Automatic', 'Engine': '6.8L V12 48V GDI DOHC', 'VIN': ' SCA3C67599UX32035 ', 'Stock #': ' GC4004A ', 'Mileage': ' 52,756 mi. '} | F91: {'Accidents or damage': 'None reported', '1-owner vehicle': 'No', 'Personal use only': 'Yes'} | G91: {'Comfort': '5.0', 'Interior': '5.0', 'Performance': '5.0', 'Value': '4.0', 'Exterior': '5.0', 'Reliability': '5.0'} | J91: 834 N Rush St Chicago, IL 60611
A92: 2023 Genesis G90 3.5T e-SC AWD | B92: New | C92: 5 mi. | D92: $89,485MSRP $101,485 | E92: {'Exterior color': ' Makalu Gray Matte ', 'Interior color': 'Urban Brown/Glacier White ', 'Drivetrain': 'All-wheel Drive ', 'MPG': ' 17â€“24Based on EPA mileage ratings. Use for comparison purposes only. Actual mileage will vary depending on driving conditions, driving habits, vehicle maintenance, and other factors.', 'Fuel type': 'Gasoline ', 'Transmission': '8-Speed Automatic', 'Engine': '3.5L V-6 port/direct injection, DOHC, variable valve control, tw', 'VIN': ' KMTFC4SD0PU029849 ', 'Stock #': ' G23095 ', 'Mileage': ' 5 mi. '} | F92: {} | G92: {} | H92: 4.1 | I92: (986 reviews) | J92: 2720 South Michigan Avenue Chicago, IL 60616
A93: 2015 Chevrolet Impala LS | B93: Used | C93: 105,307 mi. | D93: 14995 | E93: {'Exterior color': ' Silver Ice Metallic ', 'Interior color': 'Dark Titanium/Jet Black ', 'Drivetrain': 'Front-wheel Drive ', 'MPG': ' 22â€“31Based on EPA mileage ratings. Use for comparison purposes only. Actual mileage will vary depending on driving conditions, driving habits, vehicle maintenance, and other factors.', 'Fuel type': 'Gasoline ', 'Transmission': 'Automatic', 'Engine': 'ECOTEC 2.5L I-4 gasoline direct injection, DOHC, variable valve', 'VIN': ' 1G11Z5SL7FU110407 ', 'Stock #': ' 10720 ', 'Mileage': ' 105,307 mi. '} | F93: {'Accidents or damage': 'None reported', '1-owner vehicle': 'No', 'Personal use only': 'No'} | G93: {} | J93: 4400 South Archer Avenue Chicago, IL 60632
A94: 2018 Chevrolet Impala 1LT | B94: Used | C94: 112,099 mi. | D94: 15995 | E94: {'Exterior color': ' Mosaic Black Metallic ', 'Interior color': 'Jet Black ', 'Drivetrain': 'Front-wheel Drive ', 'MPG': ' 22â€“30Based on EPA mileage ratings. Use for comparison purposes only. Actual mileage will vary depending on driving conditions, driving habits, vehicle maintenance, and other factors.', 'Fuel type': 'Gasoline ', 'Transmission': 'Automatic', 'Engine': 'Ecotec 2.5L I-4 gasoline direct injection, DOHC, variable valve', 'VIN': ' 1G1105SA5JU139132 ', 'Stock #': ' 11106 ', 'Mileage': ' 112,099 mi. '} | F94: {'Accidents or damage': 'None reported', '1-owner vehicle': 'Yes', 'Personal use only': 'No'} | G94: {} | J94: 4400 South Archer Avenue Chicago, IL 60632
A95: 2015 Dodge Durango SXT | B95: Used | C95: 132,502 mi. | D95: $14,995$2,000 price drop | E95: {'Exterior color': ' Deep Cherry Red Crystal Pearlcoat ', 'Interior color': 'Black ', 'Drivetrain': 'Rear-wheel Drive ', 'MPG': ' 18â€“25Based on EPA mileage ratings. Use for comparison purposes only. Actual mileage will vary depending on driving conditions, driving habits, vehicle maintenance, and other factors.', 'Fuel type': 'Gasoline ', 'Transmission': 'Automatic', 'Engine': '3.6L V-6 DOHC, variable valve control, regular unleaded, engine', 'VIN': ' 1C4RDHAG7FC127843 ', 'Stock #': ' 10755 ', 'Mileage': ' 132,502 mi. '} | F95: {'Accidents or damage': 'At least 1 accident or damage reported', '1-owner vehicle': 'No', 'Personal use only': 'Yes'} | G95: {} | J95: 4400 South Archer Avenue Chicago, IL 60632
A96: 2012 INFINITI G37x Sport Appearance Edition | B96: Used | C96: 84,766 mi. | D96: 11949 | E96: {'Exterior color': ' Graphite Shadow ', 'Interior color': 'Graphite ', 'Drivetrain': 'All-wheel Drive ', 'MPG': ' 18â€“25Based on EPA mileage ratings. Use for comparison purposes only. Actual mileage will vary depending on driving conditions, driving habits, vehicle maintenance, and other factors.', 'Fuel type': 'Gasoline ', 'Transmission': 'Automatic', 'Engine': 'VQ 3.7L V-6 DOHC, variable valve control, premium unleaded, engi', 'VIN': ' JN1CV6AR7CM682020 ', 'Stock #': ' C15106 ', 'Mileage': ' 84,766 mi. '} | F96: {'Accidents or damage': 'At least 1 accident or damage reported', '1-owner vehicle': 'No', 'Personal use only': 'Yes'} | G96: {} | H96: 4.6 | I96: (1,035 reviews) | J96: 4747 S Pulaski Rd Chicago, IL 60632
A97: 2019 Ford Escape SEL | B97: Used | C97: 66,533 mi. | D97: $15,903$912 price drop | E97: {'Exterior color': ' Ingot Silver ', 'Interior color': 'Charcoal Black ', 'Drivetrain': 'Four-wheel Drive ', 'MPG': ' 22â€“28Based on EPA mileage ratings. Use for comparison purposes only. Actual mileage will vary depending on driving conditions, driving habits, vehicle maintenance, and other factors.', 'Fuel type': 'Gasoline ', 'Transmission': 'Automatic', 'Engine': 'EcoBoost 1.5L I-4 gasoline direct injection, DOHC, iVCT variable', 'VIN': ' 1FMCU9HD0KUA10323 ', 'Stock #': ' PA6195 ', 'Mileage': ' 66,533 mi. '} | F97: {'Accidents or damage': 'None reported', 'Clean title': 'Yes', '1-owner vehicle': 'No', 'Personal use only': 'No'} | G97: {} | H97: 4.5 | I97: (1,513 reviews) | J97: 6900 McCormick Blvd Lincolnwood, IL 60712
A98: 2019 Subaru WRX STI Base | B98: Used | C98: 53,038 mi. | D98: $30,990$1,000 price drop | E98: {'Exterior color': ' Dark Gray Metallic ', 'Interior color': 'Black ', 'Drivetrain': 'All-wheel Drive ', 'MPG': ' 17â€“22Based on EPA mileage ratings. Use for comparison purposes only. Actual mileage will vary depending on driving conditions, driving habits, vehicle maintenance, and other factors.', 'Fuel type': 'Gasoline ', 'Transmission': '6-Speed Manual', 'Engine': '2.5L H4 16V MPFI DOHC Turbo', 'VIN': ' JF1VA2S65K9831126 ', 'Stock #': ' VK1260A ', 'Mileage': ' 53,038 mi. '} | F98: {'Accidents or damage': 'At least 1 accident or damage reported', '1-owner vehicle': 'No', 'Personal use only': 'Yes', 'Open recall': 'At least 1 open recall reported'} | G98: {'Comfort': '5.0', 'Interior': '5.0', 'Performance': '5.0', 'Value': '4.0', 'Exterior': '5.0', 'Reliability': 'â€”'} | H98: 4.9 | I98: (2,290 reviews) | J98: 1033 Chicago Ave Evanston, IL 60202
A99: 2018 Volkswagen Golf R 2.0T w/DCC & Navigation | B99: Volkswagen Certified | C99: 41,540 mi. | D99: $32,490$500 price drop | E99: {'Exterior color': ' Indium Gray Metallic ', 'Interior color': 'Titan Black ', 'Drivetrain': 'All-wheel Drive ', 'MPG': ' 21â€“29Based on EPA mileage ratings. Use for comparison purposes only. Actual mileage will vary depending on driving conditions, driving habits, vehicle maintenance, and other factors.', 'Fuel type': 'Gasoline ', 'Transmission': '6-Speed Manual', 'Engine': '2.0L I4 16V GDI DOHC Turbo', 'VIN': ' WVWWF7AU7JW249946 ', 'Stock #': ' V3620A ', 'Mileage': ' 41,540 mi. '} | F99: {'Accidents or damage': 'None reported', '1-owner vehicle': 'No', 'Personal use only': 'Yes'} | G99: {'Comfort': '5.0', 'Interior': '5.0', 'Performance': '5.0', 'Value': '4.0', 'Exterior': '4.0', 'Reliability': '5.0'} | H99: 4.9 | I99: (2,290 reviews) | J99: 1033 Chicago Ave Evanston, IL 60202
A100: 2012 Ford E250 Cargo | B100: Used | C100: 115,225 mi. | D100: $14,980$810 price drop | E100: {'Exterior color': ' White ', 'Interior color': 'Gray ', 'Drivetrain': 'Rear-wheel Drive ', 'MPG': ' 16â€“16Based on EPA mileage ratings. Use for comparison purposes only. Actual mileage will vary depending on driving conditions, driving habits, vehicle maintenance, and other factors.', 'Fuel type': 'E85 Flex Fuel ', 'Transmission': 'Automatic 4-Speed', 'Engine': '5.4L V8', 'VIN': ' 1FTNE2EL9CDB20236 ', 'Stock #': ' A060 ', 'Mileage': ' 115,225 mi. '} | F100: {'Accidents or damage': 'None reported', 'Clean title': 'Yes', '1-owner vehicle': 'Yes', 'Personal use only': 'Yes'} | G100: {'Comfort': '4.0', 'Interior': '4.0', 'Performance': '4.0', 'Value': '5.0', 'Exterior': '4.0', 'Reliability': '5.0'} | J100: 6400 Harlem Ave Summit, IL 60501
...

Sheet Working Sheet
A1: Make | B1: Year | C1: Model | D1: Condition | E1: Mileage | F1: Final Cost | G1: Final | H1: Price Drop | I1: MSRP | J1: Basics Info | K1: Vehicle History Info | L1: Vehicle Reviews Info | M1: Seller Rating | N1: Seller Rating Count | O1: Seller Address
A2: Lexus | B2: 2024 | C2: LC 500 Base | D2: New | E2: 0 | F2: $112,865 | G2: $112,865 | H2: No | I2: MSRP $118,865 | J2: {'Exterior color': ' Caviar ', 'Interior color': 'Black ', 'Drivetrain': 'Rear-wheel Drive ', 'MPG': ' 15â€“25Based on EPA mileage ratings. Use for comparison purposes only. Actual mileage will vary depending on driving conditions, driving habits, vehicle maintenance, and other factors.', 'Fuel type': 'Gasoline ', 'Transmission': '10-Speed Automatic', 'Engine': '5.0L V8 32V PDI DOHC', 'VIN': ' JTHNPAAY2RA108024 ', 'Stock #': ' R087 ', 'Mileage': ' 0 mi. '} | K2: {} | L2: {} | M2: 4.7 | N2: (1,261 reviews) | O2: 1250 W Division St Chicago, IL 60642
A3: Acura | B3: 2007 | C3: TSX Base | D3: Used | E3: 61110 | F3: 11295 | G3: 11295 | H3: No | J3: {'Exterior color': ' Alabaster Silver Metallic ', 'Interior color': 'â€“ ', 'Drivetrain': 'Front-wheel Drive ', 'MPG': ' 22â€“31Based on EPA mileage ratings. Use for comparison purposes only. Actual mileage will vary depending on driving conditions, driving habits, vehicle maintenance, and other factors.', 'Fuel type': 'Gasoline ', 'Transmission': 'Automatic', 'Engine': '2.4L I-4 DOHC, i-VTEC variable valve control, premium unleaded,', 'VIN': ' JH4CL96827C013765 ', 'Stock #': ' A40896A ', 'Mileage': ' 61,110 mi. '} | K3: {'Accidents or damage': 'At least 1 accident or damage reported', '1-owner vehicle': 'Yes', 'Personal use only': 'Yes'} | L3: {} | M3: 4.2 | N3: (440 reviews) | O3: 1301 N Elston Ave Chicago, IL 60642
A4: McLaren | B4: 2016 | C4: 675LT Base | D4: Used | E4: 6305 | F4: $219,997$5,464 | G4: $219,997 | H4: Yes | J4: {'Exterior color': ' McLaren Orange ', 'Interior color': 'Carbon Black ', 'Drivetrain': 'Rear-wheel Drive ', 'MPG': ' â€“', 'Fuel type': 'Gasoline ', 'Transmission': '7-Speed Automatic with Auto-Shift', 'Engine': '3.8L V8 32V MPFI DOHC Twin Turbo', 'VIN': ' SBM11RAA7GW675095 ', 'Stock #': ' K2338 ', 'Mileage': ' 6,305 mi. '} | K4: {'Accidents or damage': 'At least 1 accident or damage reported', '1-owner vehicle': 'No', 'Personal use only': 'No'} | L4: {'Comfort': '5.0', 'Interior': '5.0', 'Performance': '5.0', 'Value': '5.0', 'Exterior': '5.0', 'Reliability': '5.0'} | M4: 3.1 | N4: (421 reviews) | O4: 1561 N Fremont St Chicago, IL 60642
A5: Audi | B5: 2016 | C5: TTS 2.0T quattro | D5: Used | E5: 65715 | F5: 23999 | G5: 23999 | H5: No | J5: {'Exterior color': ' Black ', 'Interior color': 'Black ', 'Drivetrain': 'All-wheel Drive ', 'MPG': ' 23â€“27Based on EPA mileage ratings. Use for comparison purposes only. Actual mileage will vary depending on driving conditions, driving habits, vehicle maintenance, and other factors.', 'Fuel type': 'Gasoline ', 'Transmission': '6-Speed Automatic with Auto-Shift', 'Engine': '2.0L I4 16V GDI DOHC Turbo', 'VIN': ' TRUC1AFV1G1019119 ', 'Stock #': ' 3949 ', 'Mileage': ' 65,715 mi. '} | K5: {'Accidents or damage': 'At least 1 accident or damage reported', 'Clean title': 'Yes', '1-owner vehicle': 'No', 'Personal use only': 'Yes'} | L5: {'Comfort': '3.0', 'Interior': '5.0', 'Performance': '5.0', 'Value': '5.0', 'Exterior': '5.0', 'Reliability': '5.0'} | M5: 3.6 | N5: (123 reviews) | O5: 560 E North Ave West Chicago, IL 60185
A6: BMW | B6: 2018 | C6: 740e xDrive iPerformance | D6: Used | E6: 19830 | F6: $39,799$100 | G6: $39,799 | H6: Yes | J6: {'Exterior color': ' Imperial Blue Metallic ', 'Interior color': 'Black ', 'Drivetrain': 'All-wheel Drive ', 'MPG': ' 0â€“0Based on EPA mileage ratings. Use for comparison purposes only. Actual mileage will vary depending on driving conditions, driving habits, vehicle maintenance, and other factors.', 'Fuel type': 'Gasoline ', 'Transmission': '8-Speed Automatic', 'Engine': '2L I-4 gasoline direct injection, DOHC, Double VANOS variable va', 'VIN': ' WBA7J2C57JG938534 ', 'Stock #': ' A6006 ', 'Mileage': ' 19,830 mi. '} | K6: {'Accidents or damage': 'None reported', 'Clean title': 'Yes', '1-owner vehicle': 'Yes', 'Personal use only': 'No'} | L6: {'Comfort': '5.0', 'Interior': '5.0', 'Performance': '5.0', 'Value': '5.0', 'Exterior': '5.0', 'Reliability': '5.0'} | M6: 4.4 | N6: (91 reviews) | O6: 6539 Ogden Ave Berwyn, IL 60402
A7: Jeep | B7: 2019 | C7: Cherokee Limited | D7: Used | E7: 52245 | F7: $22,966$173 | G7: $22,966 | H7: Yes | J7: {'Exterior color': ' Diamond Black ', 'Interior color': 'Black ', 'Drivetrain': 'Four-wheel Drive ', 'MPG': ' 19â€“27Based on EPA mileage ratings. Use for comparison purposes only. Actual mileage will vary depending on driving conditions, driving habits, vehicle maintenance, and other factors.', 'Fuel type': 'Gasoline ', 'Transmission': '9-Speed Automatic', 'Engine': '3.2L V6 24V MPFI DOHC', 'VIN': ' 1C4PJMDX4KD139201 ', 'Stock #': ' Y17217A ', 'Mileage': ' 52,245 mi. '} | K7: {'Accidents or damage': 'At least 1 accident or damage reported', '1-owner vehicle': 'No', 'Personal use only': 'No'} | L7: {} | M7: 4.2 | N7: (3,030 reviews) | O7: 6750 W Grand Ave Chicago, IL 60707
A8: Cadillac | B8: 2019 | C8: CT6 3.6L Luxury | D8: Used | E8: 94008 | F8: $26,995$183 | G8: $26,995 | H8: Yes | J8: {'Exterior color': ' Black ', 'Interior color': 'Black ', 'Drivetrain': 'All-wheel Drive ', 'MPG': ' 18â€“27Based on EPA mileage ratings. Use for comparison purposes only. Actual mileage will vary depending on driving conditions, driving habits, vehicle maintenance, and other factors.', 'Fuel type': 'Gasoline ', 'Transmission': 'Automatic', 'Engine': '3.6L V-6 gasoline direct injection, DOHC, VVT variable valve con', 'VIN': ' 1G6KB5RS1KU131814 ', 'Stock #': ' 8378 ', 'Mileage': ' 94,008 mi. '} | K8: {'Accidents or damage': 'At least 1 accident or damage reported', '1-owner vehicle': 'No', 'Personal use only': 'No'} | L8: {} | M8: 4.1 | N8: (50 reviews) | O8: 7158 Harlem Ave Bridgeview, IL 60455
A9: Nissan | B9: 2012 | C9: NV Cargo S | D9: Used | E9: 110202 | F9: 14985 | G9: 14985 | H9: No | J9: {'Exterior color': ' Blizzard ', 'Interior color': 'Gray ', 'Drivetrain': 'Rear-wheel Drive ', 'MPG': ' â€“', 'Fuel type': 'Gasoline ', 'Transmission': 'Automatic', 'Engine': '5.6L V8 32V MPFI DOHC', 'VIN': ' 1N6AF0KX9CN103838 ', 'Stock #': ' 8418 ', 'Mileage': ' 110,202 mi. '} | K9: {'Accidents or damage': 'At least 1 accident or damage reported', 'Clean title': 'Yes', '1-owner vehicle': 'No', 'Personal use only': 'No'} | L9: {'Comfort': '5.0', 'Interior': '5.0', 'Performance': '5.0', 'Value': '4.0', 'Exterior': '4.0', 'Reliability': '3.0'} | M9: 3.6 | N9: (64 reviews) | O9: 6007 S Archer Rd Summit, IL 60501
A10: Chrysler | B10: 2008 | C10: Sebring Touring | D10: Used | E10: 77893 | F10: 7995 | G10: 7995 | H10: No | J10: {'Exterior color': ' Silver ', 'Interior color': 'Gray ', 'Drivetrain': 'Front-wheel Drive ', 'MPG': ' 26â€“26Based on EPA mileage ratings. Use for comparison purposes only. Actual mileage will vary depending on driving conditions, driving habits, vehicle maintenance, and other factors.', 'Fuel type': 'E85 Flex Fuel ', 'Transmission': 'Automatic 4-Speed', 'Engine': '2.7L V6', 'VIN': ' 1C3LC55R58N689769 ', 'Stock #': ' 8N689769STK ', 'Mileage': ' 77,893 mi. '} | K10: {'Accidents or damage': 'None reported', '1-owner vehicle': 'No', 'Personal use only': 'Yes'} | L10: {} | M10: 3.5 | N10: (43 reviews) | O10: 1210 25th Ave Melrose Park, IL 60160
A11: Ford | B11: 2012 | C11: E250 Cargo | D11: Used | E11: 106430 | F11: $15,750$540 | G11: $15,750 | H11: Yes | J11: {'Exterior color': ' White ', 'Interior color': 'Gray ', 'Drivetrain': 'Rear-wheel Drive ', 'MPG': ' 17â€“17Based on EPA mileage ratings. Use for comparison purposes only. Actual mileage will vary depending on driving conditions, driving habits, vehicle maintenance, and other factors.', 'Fuel type': 'E85 Flex Fuel ', 'Transmission': 'Automatic 4-Speed', 'Engine': '4.6L V8', 'VIN': ' 1FTNE2EW9CDA52319 ', 'Stock #': ' T0137 ', 'Mileage': ' 106,430 mi. '} | K11: {'Accidents or damage': 'None reported', 'Clean title': 'No', '1-owner vehicle': 'No', 'Personal use only': 'No'} | L11: {'Comfort': '4.0', 'Interior': '4.0', 'Performance': '4.0', 'Value': '5.0', 'Exterior': '4.0', 'Reliability': '5.0'} | O11: 6400 Harlem Ave Summit, IL 60501
A12: Toyota | B12: 2013 | C12: Prius v Five | D12: Used | E12: 155600 | F12: 12995 | G12: 12995 | H12: No | J12: {'Exterior color': ' Blue ', 'Interior color': 'Gray ', 'Drivetrain': 'Front-wheel Drive ', 'MPG': ' 44â€“40Based on EPA mileage ratings. Use for comparison purposes only. Actual mileage will vary depending on driving conditions, driving habits, vehicle maintenance, and other factors.', 'Fuel type': 'Gasoline ', 'Transmission': 'Automatic', 'Engine': '1.8L I-4 DOHC, VVT-i variable valve control, regular unleaded, e', 'VIN': ' JTDZN3EU9D3206492 ', 'Stock #': ' GA-206492 ', 'Mileage': ' 155,600 mi. '} | K12: {'Accidents or damage': 'At least 1 accident or damage reported', '1-owner vehicle': 'No', 'Personal use only': 'Yes'} | L12: {'Comfort': '5.0', 'Interior': '4.0', 'Performance': '4.0', 'Value': '5.0', 'Exterior': '4.0', 'Reliability': '5.0'} | O12: 5050 Dempster Street Skokie, IL 60077
A13: BMW | B13: 2002 | C13: 745 Li | D13: Used | E13: 146000 | F13: 4599 | G13: 4599 | H13: No | J13: {'Exterior color': ' White ', 'Interior color': 'Beige ', 'Drivetrain': 'Rear-wheel Drive ', 'Fuel type': 'Gasoline ', 'Transmission': 'A/T', 'Engine': '325.0HP 4.4L 8 Cylinder Engine Gasoline Fuel', 'VIN': ' WBAGN634X2DR03993 ', 'Mileage': ' 146,000 mi. '} | K13: {'Accidents or damage': 'None reported', 'Clean title': 'Yes', '1-owner vehicle': 'No', 'Personal use only': 'Yes'} | L13: {}
A14: INFINITI | B14: 2020 | C14: Q60 3.0t Red Sport 400 | D14: Used | E14: 22901 | F14: 38713 | G14: 38713 | H14: No | J14: {'Exterior color': ' Iridium Blue ', 'Interior color': 'Blue ', 'Drivetrain': 'Rear-wheel Drive ', 'MPG': ' 20â€“27Based on EPA mileage ratings. Use for comparison purposes only. Actual mileage will vary depending on driving conditions, driving habits, vehicle maintenance, and other factors.', 'Fuel type': 'Gasoline ', 'Transmission': '7-Speed Automatic', 'Engine': '3.0L V6 24V GDI DOHC Twin Turbo', 'VIN': ' JN1FV7EK1LM400180 ', 'Stock #': ' M91221 ', 'Mileage': ' 22,901 mi. '} | K14: {'Accidents or damage': 'None reported', '1-owner vehicle': 'Yes', 'Personal use only': 'Yes'} | L14: {} | M14: 4.1 | N14: (591 reviews) | O14: 6750 West 95th Street Oak Lawn, IL 60453
A15: Volkswagen | B15: 2014 | C15: Beetle 1.8T | D15: Used | E15: 48650 | F15: 16988 | G15: 16988 | H15: No | J15: {'Exterior color': ' Platinum Gray Metallic ', 'Interior color': 'Titan Black ', 'Drivetrain': 'Front-wheel Drive ', 'MPG': ' 25â€“33Based on EPA mileage ratings. Use for comparison purposes only. Actual mileage will vary depending on driving conditions, driving habits, vehicle maintenance, and other factors.', 'Fuel type': 'Gasoline ', 'Transmission': '6-Speed Automatic', 'Engine': '1.8L I4 16V GDI DOHC Turbo', 'VIN': ' 3VWJ17AT3EM659954 ', 'Stock #': ' P7459VW ', 'Mileage': ' 48,650 mi. '} | K15: {'Accidents or damage': 'None reported', '1-owner vehicle': 'Yes', 'Personal use only': 'Yes'} | L15: {} | M15: 4.5 | N15: (1,555 reviews) | O15: 241 Waukegan Rd Glenview, IL 60025
A16: BMW | B16: 2015 | C16: M235 i | D16: Used | E16: 73660 | F16: 22843 | G16: 22843 | H16: No | J16: {'Exterior color': ' Glacier Silver Metallic ', 'Interior color': 'â€“ ', 'Drivetrain': 'Rear-wheel Drive ', 'MPG': ' 21â€“32Based on EPA mileage ratings. Use for comparison purposes only. Actual mileage will vary depending on driving conditions, driving habits, vehicle maintenance, and other factors.', 'Fuel type': 'Gasoline ', 'Transmission': '8-Speed Automatic', 'Engine': '3.0L I6 24V GDI DOHC Turbo', 'VIN': ' WBA1J7C59FV358577 ', 'Stock #': ' R6301 ', 'Mileage': ' 73,660 mi. '} | K16: {'Accidents or damage': 'None reported', 'Clean title': 'Yes', '1-owner vehicle': 'No', 'Personal use only': 'Yes'} | L16: {} | M16: 4 | N16: (288 reviews) | O16: 11201 S Harlem Ave Worth, IL 60482
A17: BMW | B17: 2004 | C17: 745 745i | D17: Used | E17: 119263 | F17: 7999 | G17: 7999 | H17: No | J17: {'Exterior color': ' Gold ', 'Interior color': 'Tan ', 'Drivetrain': 'Rear-wheel Drive ', 'MPG': ' 18â€“26Based on EPA mileage ratings. Use for comparison purposes only. Actual mileage will vary depending on driving conditions, driving habits, vehicle maintenance, and other factors.', 'Fuel type': 'Gasoline ', 'Transmission': '6-speed Steptronic automatic transmission w/OD-inc', 'Engine': '4.4L (268) DOHC EFI 32-valve aluminum V8 engine w/variable valve', 'VIN': ' WBAGL63424DP69960 ', 'Stock #': ' EM-P69960 ', 'Mileage': ' 119,263 mi. '} | K17: {'Accidents or damage': 'None reported', '1-owner vehicle': 'No', 'Personal use only': 'Yes'} | L17: {} | M17: 4.3 | N17: (77 reviews) | O17: 530 W Grand Ave Elmhurst, IL 60126
A18: Chevrolet | B18: 2024 | C18: Blazer EV RS | D18: New | E18: 2210 | F18: $52,715 | G18: $52,715 | H18: No | I18: MSRP $60,215 | J18: {'Exterior color': ' Summit White ', 'Interior color': 'Black ', 'Drivetrain': 'All-wheel Drive ', 'Transmission': '1-Speed Automatic', 'Engine': 'Electric', 'VIN': ' 3GNKDCRJ4RS113831 ', 'Stock #': ' V23091 ', 'Mileage': ' 2,210 mi. '} | K18: {} | L18: {} | M18: 4.1 | N18: (1,154 reviews) | O18: 400 E Roosevelt Rd Villa Park, IL 60181
A19: Jaguar | B19: 2000 | C19: XK8 | D19: Used | E19: 62022 | F19: 13995 | G19: 13995 | H19: No | J19: {'Exterior color': ' Platinum Metallic ', 'Interior color': 'Ivory ', 'Drivetrain': 'Rear-wheel Drive ', 'MPG': ' 18â€“25Based on EPA mileage ratings. Use for comparison purposes only. Actual mileage will vary depending on driving conditions, driving habits, vehicle maintenance, and other factors.', 'Fuel type': 'Gasoline ', 'Transmission': '5-Speed Automatic', 'Engine': '4.0L V8 32V MPFI DOHC', 'VIN': ' SAJJA41CXYNA04688 ', 'Stock #': ' IA1389-NM ', 'Mileage': ' 62,022 mi. '} | K19: {'Accidents or damage': 'None reported', '1-owner vehicle': 'No', 'Personal use only': 'Yes'} | L19: {'Comfort': '4.0', 'Interior': '5.0', 'Performance': '3.0', 'Value': '3.0', 'Exterior': '5.0', 'Reliability': '3.0'} | O19: 594 W Lake St Elmhurst, IL 60126
A20: Subaru | B20: 2013 | C20: XV Crosstrek 2.0i Premium | D20: Used | E20: 84358 | F20: $13,900$1,000 | G20: $13,900 | H20: Yes | J20: {'Exterior color': ' Venetian Red Pearl ', 'Interior color': 'Ivory ', 'Drivetrain': 'All-wheel Drive ', 'MPG': ' 25â€“33Based on EPA mileage ratings. Use for comparison purposes only. Actual mileage will vary depending on driving conditions, driving habits, vehicle maintenance, and other factors.', 'Fuel type': 'Gasoline ', 'Transmission': 'Automatic', 'Engine': '2L H-4 DOHC, variable valve control, regular unleaded, engine wi', 'VIN': ' JF2GPAVCXD2864679 ', 'Stock #': ' P5259 ', 'Mileage': ' 84,358 mi. '} | K20: {'Accidents or damage': 'At least 1 accident or damage reported', '1-owner vehicle': 'No', 'Personal use only': 'Yes', 'Open recall': 'At least 1 open recall reported'} | L20: {'Comfort': '4.0', 'Interior': '3.0', 'Performance': '1.0', 'Value': '1.0', 'Exterior': '4.0', 'Reliability': '1.0'} | M20: 4.8 | N20: (185 reviews) | O20: 12717 Cal Sag Rd Crestwood, IL 60445
A21: Ford | B21: 2011 | C21: E250 Cargo | D21: Used | E21: 181000 | F21: 9995 | G21: 9995 | H21: No | J21: {'Exterior color': ' Red ', 'Interior color': 'Black ', 'Drivetrain': 'Rear-wheel Drive ', 'MPG': ' 13â€“17Based on EPA mileage ratings. Use for comparison purposes only. Actual mileage will vary depending on driving conditions, driving habits, vehicle maintenance, and other factors.', 'Fuel type': 'E85 Flex Fuel ', 'Transmission': '4-Speed Automatic', 'Engine': '5.4L V8 16V MPFI SOHC Flexible Fuel', 'VIN': ' 1FTNE2EL0BDA58661 ', 'Stock #': ' IA1399 ', 'Mileage': ' 181,000 mi. '} | K21: {'Accidents or damage': 'At least 1 accident or damage reported', '1-owner vehicle': 'No', 'Personal use only': 'No'} | L21: {} | O21: 594 W Lake St Elmhurst, IL 60126
A22: BMW | B22: 2013 | C22: 128 128i Coupe | D22: Used | E22: 77783 | F22: 8995 | G22: 8995 | H22: No | J22: {'Exterior color': ' Pearl White ', 'Interior color': 'Black ', 'Drivetrain': 'Rear-wheel Drive ', 'MPG': ' 18â€“28Based on EPA mileage ratings. Use for comparison purposes only. Actual mileage will vary depending on driving conditions, driving habits, vehicle maintenance, and other factors.', 'Fuel type': 'Gasoline ', 'Transmission': 'Automatic', 'Engine': '3L I-6 DOHC, Double VANOS variable valve control, premium unlead', 'VIN': ' WBAUP9C59DVS95159 ', 'Stock #': ' TS-0538 ', 'Mileage': ' 77,783 mi. '} | K22: {'Accidents or damage': 'At least 1 accident or damage reported', '1-owner vehicle': 'No', 'Personal use only': 'Yes', 'Open recall': 'At least 1 open recall reported'} | L22: {} | O22: 13840 South Pulaski Road Crestwood, IL 60445
A23: Audi | B23: 2019 | C23: TTS 2.0T quattro | D23: Used | E23: 33832 | F23: $39,990$455 | G23: $39,990 | H23: Yes | J23: {'Exterior color': ' Daytona Gray Pearl Effect ', 'Interior color': 'Black / Rock Gray ', 'Drivetrain': 'All-wheel Drive ', 'MPG': ' 23â€“29Based on EPA mileage ratings. Use for comparison purposes only. Actual mileage will vary depending on driving conditions, driving habits, vehicle maintenance, and other factors.', 'Fuel type': 'Gasoline ', 'Transmission': '7-Speed Automatic with Auto-Shift', 'Engine': '2.0L I4 16V GDI DOHC Turbo', 'VIN': ' TRUA1AFV2K1008212 ', 'Stock #': ' C1905A ', 'Mileage': ' 33,832 mi. '} | K23: {'Accidents or damage': 'None reported', '1-owner vehicle': 'Yes', 'Personal use only': 'Yes'} | L23: {'Comfort': '4.0', 'Interior': '5.0', 'Performance': '5.0', 'Value': '5.0', 'Exterior': '5.0', 'Reliability': '5.0'} | M23: 4.9 | N23: (2,168 reviews) | O23: 500 E. Ogden Ave. Westmont, IL 60559
A24: Chevrolet | B24: 1988 | C24: C10/K10 Base | D24: Used | E24: 48934 | F24: 19888 | G24: 19888 | H24: No | J24: {'Exterior color': ' Barcelona Red ', 'Interior color': 'Barcelona Red ', 'Drivetrain': 'Rear-wheel Drive ', 'MPG': ' 0â€“0Based on EPA mileage ratings. Use for comparison purposes only. Actual mileage will vary depending on driving conditions, driving habits, vehicle maintenance, and other factors.', 'Fuel type': 'Gasoline ', 'Transmission': 'Automatic', 'Engine': '5.7 TBI V8', 'VIN': ' 1GCDC14K2JZ156418 ', 'Stock #': ' 156418 ', 'Mileage': ' 48,934 mi. '} | K24: {'Accidents or damage': 'None reported', '1-owner vehicle': 'No', 'Personal use only': 'No'} | L24: {} | M24: 5 | N24: (5 reviews) | O24: 1326 West Irving Park Road Bensenville, IL 60106
A25: Mercedes-Benz | B25: 2016 | C25: AMG G AMG G 63 4MATIC | D25: Used | E25: 59386 | F25: 71995 | G25: 71995 | H25: No | J25: {'Exterior color': ' Palladium Silver Metallic ', 'Interior color': 'Designo Black ', 'Drivetrain': 'All-wheel Drive ', 'MPG': ' 12â€“14Based on EPA mileage ratings. Use for comparison purposes only. Actual mileage will vary depending on driving conditions, driving habits, vehicle maintenance, and other factors.', 'Fuel type': 'Gasoline ', 'Transmission': '7-Speed Automatic', 'Engine': '5.5L V8 32V GDI DOHC Twin Turbo', 'VIN': ' WDCYC7DF7GX258917 ', 'Stock #': ' HL7535 ', 'Mileage': ' 59,386 mi. '} | K25: {'Accidents or damage': 'At least 1 accident or damage reported', '1-owner vehicle': 'No', 'Personal use only': 'Yes'} | L25: {'Comfort': '5.0', 'Interior': '5.0', 'Performance': '5.0', 'Value': '5.0', 'Exterior': '5.0', 'Reliability': 'â€”'} | M25: 4.6 | N25: (358 reviews) | O25: 555 Executive Dr Willowbrook, IL 60527
A26: Lexus | B26: 2002 | C26: SC 430 Base | D26: Used | E26: 98373 | F26: $8,999$300 | G26: $8,999 | H26: Yes | J26: {'Exterior color': ' Burgundy ', 'Interior color': 'Tan ', 'Drivetrain': 'Rear-wheel Drive ', 'MPG': ' 18â€“23Based on EPA mileage ratings. Use for comparison purposes only. Actual mileage will vary depending on driving conditions, driving habits, vehicle maintenance, and other factors.', 'Fuel type': 'Gasoline ', 'Transmission': 'Automatic', 'Engine': '4.3L (262) DOHC EFI 32-valve V8 aluminum engine-inc: continuousl', 'VIN': ' JTHFN48YX20002417 ', 'Stock #': ' YC-002417 ', 'Mileage': ' 98,373 mi. '} | K26: {'Accidents or damage': 'None reported', '1-owner vehicle': 'No', 'Personal use only': 'Yes'} | L26: {'Comfort': '5.0', 'Interior': '5.0', 'Performance': '4.0', 'Value': '5.0', 'Exterior': '5.0', 'Reliability': '5.0'} | M26: 4.3 | N26: (110 reviews) | O26: 3128 W 147th St Posen, IL 60469
A27: Lexus | B27: 2023 | C27: LC 500 Base | D27: New | E27: 0 | F27: $106,615 | G27: $106,615 | H27: No | I27: MSRP $114,420 | J27: {'Exterior color': ' Caviar ', 'Interior color': 'Red ', 'Drivetrain': 'Rear-wheel Drive ', 'MPG': ' 15â€“25Based on EPA mileage ratings. Use for comparison purposes only. Actual mileage will vary depending on driving conditions, driving habits, vehicle maintenance, and other factors.', 'Fuel type': 'Gasoline ', 'Transmission': '10-Speed Automatic', 'Engine': '5.0L V8 32V PDI DOHC', 'VIN': ' JTHMPAAY6PA107242 ', 'Stock #': ' B1781 ', 'Mileage': ' 0 mi. '} | K27: {} | L27: {} | M27: 4.9 | N27: (2,168 reviews) | O27: 500 E. Ogden Ave. Westmont, IL 60559
C28: 0 | F28: 0 | G28: 0 | H28: No | J28: {} | K28: {} | L28: {}
A29: Pontiac | B29: 2006 | C29: GTO | D29: Used | E29: 55915 | F29: $20,691$1,300 | G29: $20,691 | H29: Yes | J29: {'Exterior color': ' Phantom Black Metallic ', 'Interior color': 'Red ', 'Drivetrain': 'Rear-wheel Drive ', 'MPG': ' â€“', 'Fuel type': 'Gasoline ', 'Transmission': '4-Speed Automatic', 'Engine': '6.0L V8 16V MPFI OHV', 'VIN': ' 6G2VX12U86L521103 ', 'Stock #': ' 6L521103 ', 'Mileage': ' 55,915 mi. '} | K29: {'Accidents or damage': 'At least 1 accident or damage reported', '1-owner vehicle': 'Yes', 'Personal use only': 'Yes'} | L29: {} | M29: 4.7 | N29: (1,955 reviews) | O29: 430 E. Ogden Ave. Westmont, IL 60559
A30: BMW | B30: 1988 | C30: M6 | D30: Used | E30: 46344 | F30: 63910 | G30: 63910 | H30: No | J30: {'Exterior color': ' Cinnabar Red ', 'Interior color': 'Tan ', 'Drivetrain': 'Rear-wheel Drive ', 'MPG': ' â€“', 'Fuel type': 'Gasoline ', 'Transmission': '5-Speed Manual', 'Engine': '3.5L I6 24V DOHC', 'VIN': ' WBAEE1410J2561382 ', 'Stock #': ' C071421 ', 'Mileage': ' 46,344 mi. '} | K30: {'Accidents or damage': 'None reported', 'Clean title': 'Yes', '1-owner vehicle': 'No', 'Personal use only': 'Yes'} | L30: {} | M30: 3.9 | N30: (160 reviews) | O30: 100 W Ogden Ave Westmont, IL 60559
A31: Triumph | B31: 1975 | C31: TR6 | D31: Used | E31: 27667 | F31: 26507 | G31: 26507 | H31: No | J31: {'Exterior color': ' Yellow ', 'Interior color': 'Black ', 'Drivetrain': 'â€“ ', 'MPG': ' â€“', 'Fuel type': 'â€“ ', 'Transmission': 'Manual', 'Engine': 'â€“', 'VIN': ' 000000000CF39098U ', 'Stock #': ' C040623-1 ', 'Mileage': ' 27,667 mi. '} | K31: {} | L31: {} | M31: 3.9 | N31: (160 reviews) | O31: 100 W Ogden Ave Westmont, IL 60559
A32: BMW | B32: 2018 | C32: M6 Base | D32: Used | E32: 46698 | F32: 45373 | G32: 45373 | H32: No | J32: {'Exterior color': ' San Marino Blue Metallic ', 'Interior color': 'Black ', 'Drivetrain': 'Rear-wheel Drive ', 'MPG': ' 14â€“20Based on EPA mileage ratings. Use for comparison purposes only. Actual mileage will vary depending on driving conditions, driving habits, vehicle maintenance, and other factors.', 'Fuel type': 'Gasoline ', 'Transmission': '7-Speed Automatic', 'Engine': '4.4L V8 32V DOHC TwinPower Turbo', 'VIN': ' WBS6G9C59JBM23806 ', 'Stock #': ' UN4073 ', 'Mileage': ' 46,698 mi. '} | K32: {'Accidents or damage': 'None reported', '1-owner vehicle': 'No', 'Personal use only': 'Yes'} | L32: {'Comfort': '5.0', 'Interior': '5.0', 'Performance': '5.0', 'Value': '5.0', 'Exterior': '5.0', 'Reliability': '5.0'} | M32: 2.8 | N32: (83 reviews) | O32: 1850 Holste Rd Northbrook, IL 60062
A33: INFINITI | B33: 2009 | C33: G37 Journey | D33: Used | E33: 96658 | F33: 10980 | G33: 10980 | H33: No | J33: {'Exterior color': ' Blue Slate Pearl ', 'Interior color': 'Beige ', 'Drivetrain': 'Rear-wheel Drive ', 'MPG': ' 18â€“26Based on EPA mileage ratings. Use for comparison purposes only. Actual mileage will vary depending on driving conditions, driving habits, vehicle maintenance, and other factors.', 'Fuel type': 'Gasoline ', 'Transmission': 'Automatic', 'Engine': 'VQ 3.7L V-6 DOHC, variable valve control, premium unleaded, engi', 'VIN': ' JNKCV64E49M606171 ', 'Stock #': ' 5963 ', 'Mileage': ' 96,658 mi. '} | K33: {'Accidents or damage': 'At least 1 accident or damage reported', 'Clean title': 'Yes', '1-owner vehicle': 'No', 'Personal use only': 'Yes'} | L33: {} | M33: 4.6 | N33: (189 reviews) | O33: 1886 S Elmhurst Rd Mt Prospect, IL 60056
A34: Volkswagen | B34: 2016 | C34: Golf SportWagen TSI SE | D34: Used | E34: 145302 | F34: 9495 | G34: 9495 | H34: No | J34: {'Exterior color': ' Silver ', 'Interior color': 'Black ', 'Drivetrain': 'Front-wheel Drive ', 'MPG': ' 25â€“35Based on EPA mileage ratings. Use for comparison purposes only. Actual mileage will vary depending on driving conditions, driving habits, vehicle maintenance, and other factors.', 'Fuel type': 'Gasoline ', 'Transmission': '6-Speed Automatic', 'Engine': '1.8L I4 16V GDI DOHC Turbo', 'VIN': ' 3VWC17AU4GM509453 ', 'Stock #': ' XM651 ', 'Mileage': ' 145,302 mi. '} | K34: {'Accidents or damage': 'At least 1 accident or damage reported', '1-owner vehicle': 'No', 'Personal use only': 'Yes'} | L34: {'Comfort': '4.0', 'Interior': '5.0', 'Performance': '5.0', 'Value': '5.0', 'Exterior': '5.0', 'Reliability': '5.0'} | O34: 870 S Fiene Dr. Addison, IL 60101
A35: Scion | B35: 2005 | C35: xA Base (A4) | D35: Used | E35: 102243 | F35: 5795 | G35: 5795 | H35: No | J35: {'Exterior color': ' Gray ', 'Interior color': 'Black ', 'Drivetrain': 'Front-wheel Drive ', 'MPG': ' 31â€“38Based on EPA mileage ratings. Use for comparison purposes only. Actual mileage will vary depending on driving conditions, driving habits, vehicle maintenance, and other factors.', 'Fuel type': 'Gasoline ', 'Transmission': '4-Speed Automatic', 'Engine': '1.5L I4 16V MPFI DOHC', 'VIN': ' JTKKT624450118605 ', 'Stock #': ' 2807 ', 'Mileage': ' 102,243 mi. '} | K35: {'Accidents or damage': 'At least 1 accident or damage reported', '1-owner vehicle': 'No', 'Personal use only': 'Yes'} | L35: {} | M35: 4.6 | N35: (50 reviews) | O35: 555 S IL Route 83 Elmhurst, IL 60126
A36: Toyota | B36: 2015 | C36: Prius v Three | D36: Used | E36: 91655 | F36: 13980 | G36: 13980 | H36: No | J36: {'Exterior color': ' Attitude Black ', 'Interior color': 'Gray ', 'Drivetrain': 'Front-wheel Drive ', 'MPG': ' 44â€“40Based on EPA mileage ratings. Use for comparison purposes only. Actual mileage will vary depending on driving conditions, driving habits, vehicle maintenance, and other factors.', 'Fuel type': 'Gasoline ', 'Transmission': 'Automatic', 'Engine': '1.8L I-4 DOHC, VVT-i variable valve control, regular unleaded, e', 'VIN': ' JTDZN3EUXFJ016005 ', 'Stock #': ' 6069 ', 'Mileage': ' 91,655 mi. '} | K36: {'Accidents or damage': 'None reported', 'Clean title': 'Yes', '1-owner vehicle': 'No', 'Personal use only': 'Yes', 'Open recall': 'At least 1 open recall reported'} | L36: {'Comfort': '5.0', 'Interior': '5.0', 'Performance': '5.0', 'Value': '5.0', 'Exterior': '5.0', 'Reliability': '5.0'} | M36: 4.6 | N36: (189 reviews) | O36: 1886 S Elmhurst Rd Mt Prospect, IL 60056
A37: Mercedes-Benz | B37: 2024 | C37: AMG EQS Base | D37: New | E37: 6 | F37: $152,800 | G37: $152,800 | H37: No | I37: MSRP $152,800 | J37: {'Exterior color': ' Moonlight White ', 'Interior color': 'Black ', 'Drivetrain': 'All-wheel Drive ', 'Transmission': '1-Speed Automatic', 'Engine': 'Electric', 'VIN': ' W1KCG5FB6RA047125 ', 'Stock #': ' 64-592 ', 'Mileage': ' 6 mi. '} | K37: {} | L37: {} | M37: 4.7 | N37: (2,850 reviews) | O37: 1600 Frontage Rd Northbrook, IL 60062
A38: Toyota | B38: 2012 | C38: Prius v Two | D38: Used | E38: 168725 | F38: 9945 | G38: 9945 | H38: No | J38: {'Exterior color': ' Magnetic Gray Metallic ', 'Interior color': 'GRAY ', 'Drivetrain': 'Front-wheel Drive ', 'MPG': ' 0â€“0Based on EPA mileage ratings. Use for comparison purposes only. Actual mileage will vary depending on driving conditions, driving habits, vehicle maintenance, and other factors.', 'Fuel type': 'Hybrid ', 'Transmission': 'Automatic', 'Engine': '1.8L 4 CYLINDER', 'VIN': ' JTDZN3EU5C3136231 ', 'Stock #': ' 36231 ', 'Mileage': ' 168,725 mi. '} | K38: {'Accidents or damage': 'None reported', '1-owner vehicle': 'Yes', 'Personal use only': 'Yes'} | L38: {'Comfort': '5.0', 'Interior': '5.0', 'Performance': '5.0', 'Value': '5.0', 'Exterior': '5.0', 'Reliability': 'â€”'} | M38: 4.2 | N38: (20 reviews) | O38: 350 S Lalonde Ave ADDISON, IL 60101
A39: Chrysler | B39: 2008 | C39: Sebring Touring | D39: Used | E39: 70974 | F39: 11950 | G39: 11950 | H39: No | J39: {'Exterior color': ' Silver Steel Metallic Clearcoat ', 'Interior color': 'Dark Slate Gray/Light Slate Gray ', 'Drivetrain': 'Front-wheel Drive ', 'MPG': ' 18â€“26Based on EPA mileage ratings. Use for comparison purposes only. Actual mileage will vary depending on driving conditions, driving habits, vehicle maintenance, and other factors.', 'Fuel type': 'E85 Flex Fuel ', 'Transmission': 'Automatic', 'Engine': '2.7L V-6 DOHC, engine with 189HP', 'VIN': ' 1C3LC55R88N615598 ', 'Stock #': ' N615598 ', 'Mileage': ' 70,974 mi. '} | K39: {'Accidents or damage': 'None reported', '1-owner vehicle': 'No', 'Personal use only': 'Yes'} | L39: {} | M39: 4.6 | N39: (127 reviews) | O39: 1030 Republic Dr Addison, IL 60101
A40: Jeep | B40: 2007 | C40: Commander Sport | D40: Used | E40: 173694 | F40: $4,550$400 | G40: $4,550 | H40: Yes | J40: {'Exterior color': ' Light Graystone Pearlcoat ', 'Interior color': 'Khaki ', 'Drivetrain': 'Four-wheel Drive ', 'MPG': ' 16â€“19Based on EPA mileage ratings. Use for comparison purposes only. Actual mileage will vary depending on driving conditions, driving habits, vehicle maintenance, and other factors.', 'Fuel type': 'Gasoline ', 'Transmission': 'Automatic', 'Engine': 'Power Tech 3.7L V-6 regular unleaded, engine with 210HP', 'VIN': ' 1J8HG48K37C510145 ', 'Stock #': ' B-329 ', 'Mileage': ' 173,694 mi. '} | K40: {'Accidents or damage': 'At least 1 accident or damage reported', 'Clean title': 'Yes', '1-owner vehicle': 'No', 'Personal use only': 'Yes'} | L40: {} | O40: 11S344 Jeans Road Lemont, IL 60439
A41: INFINITI | B41: 2017 | C41: Q60 3.0T Premium | D41: Used | E41: 111586 | F41: 17995 | G41: 17995 | H41: No | J41: {'Exterior color': ' Gray ', 'Interior color': 'Gray ', 'Drivetrain': 'All-wheel Drive ', 'MPG': ' 19â€“27Based on EPA mileage ratings. Use for comparison purposes only. Actual mileage will vary depending on driving conditions, driving habits, vehicle maintenance, and other factors.', 'Fuel type': 'Gasoline ', 'Transmission': '7-Speed Automatic', 'Engine': '3.0L V6 24V GDI DOHC Twin Turbo', 'VIN': ' JN1EV7ELXHM554222 ', 'Stock #': ' 554222 ', 'Mileage': ' 111,586 mi. '} | K41: {'Accidents or damage': 'At least 1 accident or damage reported', '1-owner vehicle': 'No', 'Personal use only': 'No'} | L41: {} | O41: 454 East North Avenue Lombard, IL 60148
A42: Lexus | B42: 2010 | C42: HS 250h Premium | D42: Used | E42: 128900 | F42: 9995 | G42: 9995 | H42: No | J42: {'Exterior color': ' Black Opal Mica ', 'Interior color': 'Black ', 'Drivetrain': 'Front-wheel Drive ', 'MPG': ' 35â€“34Based on EPA mileage ratings. Use for comparison purposes only. Actual mileage will vary depending on driving conditions, driving habits, vehicle maintenance, and other factors.', 'Fuel type': 'Hybrid ', 'Transmission': 'Automatic', 'Engine': '2.4L DOHC SFI 16-valve Atkinson cycle I4 engine -inc: variable v', 'VIN': ' JTHBB1BA9A2007709 ', 'Stock #': ' 102100 ', 'Mileage': ' 128,900 mi. '} | K42: {'Accidents or damage': 'None reported', 'Clean title': 'Yes', '1-owner vehicle': 'No', 'Personal use only': 'Yes'} | L42: {'Comfort': '5.0', 'Interior': '5.0', 'Performance': '5.0', 'Value': '5.0', 'Exterior': '5.0', 'Reliability': '5.0'} | M42: 4.1 | N42: (49 reviews) | O42: 367 S Rohlwing Rd Addison, IL 60101
A43: Porsche | B43: 2015 | C43: Cayman S | D43: Used | E43: 48163 | F43: 52985 | G43: 52985 | H43: No | J43: {'Exterior color': ' Black ', 'Interior color': 'Beige ', 'Drivetrain': 'Rear-wheel Drive ', 'MPG': ' 21â€“30Based on EPA mileage ratings. Use for comparison purposes only. Actual mileage will vary depending on driving conditions, driving habits, vehicle maintenance, and other factors.', 'Fuel type': 'Gasoline ', 'Transmission': 'Manual', 'Engine': '3.4L H-6 gasoline direct injection, DOHC, VarioCam variable valv', 'VIN': ' WP0AB2A82FK184482 ', 'Stock #': ' B15482801 ', 'Mileage': ' 48,163 mi. '} | K43: {'Accidents or damage': 'None reported', 'Clean title': 'Yes', '1-owner vehicle': 'No', 'Personal use only': 'Yes'} | L43: {} | M43: 4.2 | N43: (14 reviews) | O43: 1644 Ogden Ave Downers Grove, IL 60515
A44: INFINITI | B44: 2013 | C44: EX37 Journey | D44: Used | E44: 162296 | F44: 8888 | G44: 8888 | H44: No | J44: {'Exterior color': ' Black Obsidian ', 'Interior color': 'Black ', 'Drivetrain': 'All-wheel Drive ', 'MPG': ' 17â€“24Based on EPA mileage ratings. Use for comparison purposes only. Actual mileage will vary depending on driving conditions, driving habits, vehicle maintenance, and other factors.', 'Fuel type': 'Gasoline ', 'Transmission': '7-Speed Automatic', 'Engine': '3.7L V6 24V MPFI DOHC', 'VIN': ' JN1BJ0HR4DM482367 ', 'Stock #': ' D-1778 ', 'Mileage': ' 162,296 mi. '} | K44: {'Accidents or damage': 'None reported', '1-owner vehicle': 'Yes', 'Personal use only': 'Yes'} | L44: {} | M44: 1.3 | N44: (32 reviews) | O44: 1543 Ogden Ave Downers Grove, IL 60515
A45: Lexus | B45: 2008 | C45: RX 400h | D45: Used | E45: 167082 | F45: 7777 | G45: 7777 | H45: No | J45: {'Exterior color': ' Red ', 'Interior color': 'Beige ', 'Drivetrain': 'All-wheel Drive ', 'MPG': ' 26â€“24Based on EPA mileage ratings. Use for comparison purposes only. Actual mileage will vary depending on driving conditions, driving habits, vehicle maintenance, and other factors.', 'Fuel type': 'Hybrid ', 'Transmission': 'Automatic CVT', 'Engine': '3.3L V6 24V MPFI DOHC Hybrid', 'VIN': ' JTJHW31UX82050311 ', 'Stock #': ' D-1808 ', 'Mileage': ' 167,082 mi. '} | K45: {'Accidents or damage': 'At least 1 accident or damage reported', '1-owner vehicle': 'Yes', 'Personal use only': 'Yes'} | L45: {'Comfort': '4.0', 'Interior': '5.0', 'Performance': '4.0', 'Value': '5.0', 'Exterior': '5.0', 'Reliability': '5.0'} | M45: 1.3 | N45: (32 reviews) | O45: 1543 Ogden Ave Downers Grove, IL 60515
A46: Toyota | B46: 2012 | C46: Prius v Two | D46: Used | E46: 67422 | F46: 14999 | G46: 14999 | H46: No | J46: {'Exterior color': ' Classic Silver Metallic ', 'Interior color': 'Black ', 'Drivetrain': 'Front-wheel Drive ', 'MPG': ' 44â€“40Based on EPA mileage ratings. Use for comparison purposes only. Actual mileage will vary depending on driving conditions, driving habits, vehicle maintenance, and other factors.', 'Fuel type': 'Gasoline ', 'Transmission': 'Automatic', 'Engine': '1.8L I-4 DOHC, VVT-i variable valve control, regular unleaded, e', 'VIN': ' JTDZN3EU5C3052524 ', 'Stock #': ' 052524 ', 'Mileage': ' 67,422 mi. '} | K46: {'Accidents or damage': 'At least 1 accident or damage reported', 'Clean title': 'Yes', '1-owner vehicle': 'Yes', 'Personal use only': 'Yes'} | L46: {'Comfort': '5.0', 'Interior': '5.0', 'Performance': '5.0', 'Value': '5.0', 'Exterior': '5.0', 'Reliability': 'â€”'} | O46: 3201 167th St Hazel Crest, IL 60429
A47: Toyota | B47: 2007 | C47: Yaris Base | D47: Used | E47: 67300 | F47: 9975 | G47: 9975 | H47: No | J47: {'Exterior color': ' Pacific Blue Metallic ', 'Interior color': 'Dark Charcoal ', 'Drivetrain': 'Front-wheel Drive ', 'MPG': ' 34â€“40Based on EPA mileage ratings. Use for comparison purposes only. Actual mileage will vary depending on driving conditions, driving habits, vehicle maintenance, and other factors.', 'Fuel type': 'Gasoline ', 'Transmission': 'â€“', 'Engine': '1.5L DOHC SFI 16-valve VVT-i 4-cyl engine w/Toyota direct inject', 'VIN': ' JTDBT923071063907 ', 'Stock #': ' 96521400 ', 'Mileage': ' 67,300 mi. '} | K47: {'Accidents or damage': 'None reported', 'Clean title': 'Yes', '1-owner vehicle': 'Yes', 'Personal use only': 'No'} | L47: {} | M47: 4.1 | N47: (49 reviews) | O47: 367 S Rohlwing Rd Addison, IL 60101
A48: Mercedes-Benz | B48: 2017 | C48: AMG S 63 Base 4MATIC | D48: Used | E48: 5350 | F48: 69800 | G48: 69800 | H48: No | J48: {'Exterior color': ' Magnetite Black Metallic ', 'Interior color': 'Black ', 'Drivetrain': 'All-wheel Drive ', 'MPG': ' 15â€“23Based on EPA mileage ratings. Use for comparison purposes only. Actual mileage will vary depending on driving conditions, driving habits, vehicle maintenance, and other factors.', 'Fuel type': 'Gasoline ', 'Transmission': '7-Speed Automatic', 'Engine': '5.5L V8 32V GDI DOHC Twin Turbo', 'VIN': ' WDDUG7JB8HA294832 ', 'Stock #': ' PGD0082 ', 'Mileage': ' 5,350 mi. '} | K48: {'Accidents or damage': 'At least 1 accident or damage reported', '1-owner vehicle': 'Yes', 'Personal use only': 'No'} | L48: {'Comfort': '5.0', 'Interior': '5.0', 'Performance': '5.0', 'Value': '5.0', 'Exterior': '5.0', 'Reliability': '5.0'} | O48: 1866 Ogden Avenue Downers Grove, IL 60515
A49: BMW | B49: 2016 | C49: M235 i | D49: Used | E49: 111166 | F49: 18888 | G49: 18888 | H49: No | J49: {'Exterior color': ' White ', 'Interior color': 'Coral Red / Black ', 'Drivetrain': 'Rear-wheel Drive ', 'MPG': ' 20â€“31Based on EPA mileage ratings. Use for comparison purposes only. Actual mileage will vary depending on driving conditions, driving habits, vehicle maintenance, and other factors.', 'Fuel type': 'Gasoline ', 'Transmission': '8-Speed Automatic', 'Engine': '3.0L I6 24V GDI DOHC Turbo', 'VIN': ' WBA1J7C55GV359209 ', 'Stock #': ' D-1793 ', 'Mileage': ' 111,166 mi. '} | K49: {'Accidents or damage': 'None reported', '1-owner vehicle': 'No', 'Personal use only': 'Yes'} | L49: {} | M49: 1.3 | N49: (32 reviews) | O49: 1543 Ogden Ave Downers Grove, IL 60515
A50: Ford | B50: 2011 | C50: E250 Cargo | D50: Used | E50: 133990 | F50: 10990 | G50: 10990 | H50: No | J50: {'Exterior color': ' White ', 'Interior color': 'Gray ', 'Drivetrain': 'Rear-wheel Drive ', 'MPG': ' 16â€“16Based on EPA mileage ratings. Use for comparison purposes only. Actual mileage will vary depending on driving conditions, driving habits, vehicle maintenance, and other factors.', 'Fuel type': 'E85 Flex Fuel ', 'Transmission': 'Automatic 4-Speed', 'Engine': '5.4L V8', 'VIN': ' 1FTNE2EL3BDA30854 ', 'Stock #': ' A10381 ', 'Mileage': ' 133,990 mi. '} | K50: {'Accidents or damage': 'At least 1 accident or damage reported', '1-owner vehicle': 'Yes', 'Personal use only': 'No'} | L50: {} | M50: 3.7 | N50: (84 reviews) | O50: 1233 Ogden Ave Downers Grove, IL 60515
A51: Aston | B51: 2012 | C51: Martin DB9 Volante | D51: Used | E51: 20038 | F51: 67455 | G51: 67455 | H51: No | J51: {'Exterior color': ' Hammerhead Silver ', 'Interior color': 'Gray ', 'Drivetrain': 'Rear-wheel Drive ', 'MPG': ' 13â€“20Based on EPA mileage ratings. Use for comparison purposes only. Actual mileage will vary depending on driving conditions, driving habits, vehicle maintenance, and other factors.', 'Fuel type': 'Gasoline ', 'Transmission': '6-Speed Automatic', 'Engine': '6.0L V12 48V MPFI DOHC', 'VIN': ' SCFFDABE8CGB14387 ', 'Stock #': ' 2611 ', 'Mileage': ' 20,038 mi. '} | K51: {'Accidents or damage': 'None reported', '1-owner vehicle': 'Yes', 'Personal use only': 'Yes'} | L51: {'Comfort': '5.0', 'Interior': '5.0', 'Performance': '5.0', 'Value': '5.0', 'Exterior': '5.0', 'Reliability': '5.0'} | M51: 4.3 | N51: (71 reviews) | O51: 2401 Warrenville Rd Downers Grove, IL 60515
A52: Volkswagen | B52: 2022 | C52: Golf R 2.0T | D52: Used | E52: 12959 | F52: 43949 | G52: 43949 | H52: No | J52: {'Exterior color': ' Pure White ', 'Interior color': 'Blue ', 'Drivetrain': 'All-wheel Drive ', 'MPG': ' 23â€“30Based on EPA mileage ratings. Use for comparison purposes only. Actual mileage will vary depending on driving conditions, driving habits, vehicle maintenance, and other factors.', 'Fuel type': 'Gasoline ', 'Transmission': '7-Speed Automatic', 'Engine': '2.0L I4 16V GDI DOHC Turbo', 'VIN': ' WVWEB7CD2NW170050 ', 'Stock #': ' 3056 ', 'Mileage': ' 12,959 mi. '} | K52: {'Accidents or damage': 'None reported', '1-owner vehicle': 'No', 'Personal use only': 'No'} | L52: {'Comfort': '5.0', 'Interior': '5.0', 'Performance': '5.0', 'Value': '5.0', 'Exterior': '4.0', 'Reliability': '5.0'} | M52: 4.3 | N52: (71 reviews) | O52: 2401 Warrenville Rd Downers Grove, IL 60515
A53: Cadillac | B53: 2014 | C53: XTS Luxury | D53: Used | E53: 44500 | F53: 16000 | G53: 16000 | H53: No | J53: {'Exterior color': ' Graphite Metallic ', 'Interior color': 'Medium Titanium / Jet Black ', 'Drivetrain': 'Front-wheel Drive ', 'MPG': ' 18â€“28Based on EPA mileage ratings. Use for comparison purposes only. Actual mileage will vary depending on driving conditions, driving habits, vehicle maintenance, and other factors.', 'Fuel type': 'Gasoline ', 'Transmission': '6-Speed Automatic', 'Engine': '3.6L V6 24V GDI DOHC', 'VIN': ' 2G61M5S39E9237180 ', 'Stock #': ' J240122B ', 'Mileage': ' 44,500 mi. '} | K53: {'Accidents or damage': 'At least 1 accident or damage reported', '1-owner vehicle': 'No', 'Personal use only': 'Yes'} | L53: {} | M53: 4.7 | N53: (1,303 reviews) | O53: 17225 Torrence Ave Lansing, IL 60438
A54: Lexus | B54: 2008 | C54: RX 400h Base | D54: Used | E54: 186000 | F54: 6500 | G54: 6500 | H54: No | J54: {'Exterior color': ' Silver ', 'Interior color': 'Beige ', 'Drivetrain': 'All-wheel Drive ', 'Fuel type': 'Hybrid ', 'Transmission': 'A/T', 'Engine': '208.0HP 3.3L V6 Cylinder Engine Gas/Electric Hybrid', 'VIN': ' JTJHW31U082047045 ', 'Mileage': ' 186,000 mi. '} | K54: {'Accidents or damage': 'None reported', 'Clean title': 'Yes', '1-owner vehicle': 'No', 'Personal use only': 'Yes'} | L54: {'Comfort': '4.0', 'Interior': '5.0', 'Performance': '4.0', 'Value': '5.0', 'Exterior': '5.0', 'Reliability': '5.0'}
A55: Toyota | B55: 2013 | C55: Prius v Five | D55: Used | E55: 92754 | F55: $11,700$800 | G55: $11,700 | H55: Yes | J55: {'Exterior color': ' Blue ', 'Interior color': 'Bisque ', 'Drivetrain': 'Front-wheel Drive ', 'MPG': ' 44â€“40Based on EPA mileage ratings. Use for comparison purposes only. Actual mileage will vary depending on driving conditions, driving habits, vehicle maintenance, and other factors.', 'Fuel type': 'Gasoline ', 'Transmission': 'CVT', 'Engine': '1.8L 4-Cylinder DOHC 16V VVT-i Aluminum', 'VIN': ' JTDZN3EUXD3266975 ', 'Stock #': ' KBB1801 ', 'Mileage': ' 92,754 mi. '} | K55: {'Accidents or damage': 'At least 1 accident or damage reported', '1-owner vehicle': 'No', 'Personal use only': 'Yes'} | L55: {'Comfort': '5.0', 'Interior': '4.0', 'Performance': '4.0', 'Value': '5.0', 'Exterior': '4.0', 'Reliability': '5.0'} | M55: 4.8 | N55: (1,926 reviews) | O55: 17220 Torrence Ave Lansing, IL 60438
A56: Chevrolet | B56: 2014 | C56: Corvette Stingray Z51 | D56: Used | E56: 60261 | F56: 38595 | G56: 38595 | H56: No | J56: {'Exterior color': ' Cyber Gray Metallic ', 'Interior color': 'Jet Black ', 'Drivetrain': 'Rear-wheel Drive ', 'MPG': ' 17â€“29Based on EPA mileage ratings. Use for comparison purposes only. Actual mileage will vary depending on driving conditions, driving habits, vehicle maintenance, and other factors.', 'Fuel type': 'Gasoline ', 'Transmission': '6-Speed Automatic', 'Engine': '6.2L V8 16V GDI OHV', 'VIN': ' 1G1YH2D72E5125406 ', 'Stock #': ' 2928 ', 'Mileage': ' 60,261 mi. '} | K56: {'Accidents or damage': 'None reported', '1-owner vehicle': 'No', 'Personal use only': 'Yes'} | L56: {'Comfort': '5.0', 'Interior': '5.0', 'Performance': '5.0', 'Value': '5.0', 'Exterior': '5.0', 'Reliability': '5.0'} | M56: 4.3 | N56: (71 reviews) | O56: 2401 Warrenville Rd Downers Grove, IL 60515
A57: Ford | B57: 2005 | C57: Excursion Eddie Bauer | D57: Used | E57: 304425 | F57: 5997 | G57: 5997 | H57: No | J57: {'Exterior color': ' Oxford White ', 'Interior color': 'Medium Pebble ', 'Drivetrain': 'Four-wheel Drive ', 'MPG': ' 0â€“0Based on EPA mileage ratings. Use for comparison purposes only. Actual mileage will vary depending on driving conditions, driving habits, vehicle maintenance, and other factors.', 'Fuel type': 'Gasoline ', 'Transmission': 'Automatic', 'Engine': 'Triton 6.8L V-10 regular unleaded, engine with 310HP', 'VIN': ' 1FMNU45S05EA84354 ', 'Stock #': ' C-EXCURSION ', 'Mileage': ' 304,425 mi. '} | K57: {'Accidents or damage': 'None reported', 'Clean title': 'Yes', '1-owner vehicle': 'Yes', 'Personal use only': 'Yes'} | L57: {} | M57: 4.8 | N57: (313 reviews) | O57: 17651 Oak Park Ave Tinley Park, IL 60477
A58: Ford | B58: 2021 | C58: Escape SE | D58: Used | E58: 32395 | F58: 21987 | G58: 21987 | H58: No | J58: {'Exterior color': ' Bronze Fire Metallic ', 'Interior color': 'Dark Earth Gray ', 'Drivetrain': 'All-wheel Drive ', 'MPG': ' 26â€“31Based on EPA mileage ratings. Use for comparison purposes only. Actual mileage will vary depending on driving conditions, driving habits, vehicle maintenance, and other factors.', 'Fuel type': 'Gasoline ', 'Transmission': '8-Speed Automatic', 'Engine': '1.5L I3 12V PDI DOHC Turbo', 'VIN': ' 1FMCU9G67MUA25830 ', 'Stock #': ' 21359P ', 'Mileage': ' 32,395 mi. '} | K58: {'Accidents or damage': 'At least 1 accident or damage reported', '1-owner vehicle': 'Yes', 'Personal use only': 'Yes'} | L58: {} | M58: 4.6 | N58: (427 reviews) | O58: 18033 S Halsted St Homewood, IL 60430
A59: Mazda | B59: 2007 | C59: Mazda6 i Sport | D59: Used | E59: 151531 | F59: 3777 | G59: 3777 | H59: No | J59: {'Exterior color': ' MAROON ', 'Interior color': 'â€“ ', 'Drivetrain': 'Front-wheel Drive ', 'MPG': ' 24â€“0Based on EPA mileage ratings. Use for comparison purposes only. Actual mileage will vary depending on driving conditions, driving habits, vehicle maintenance, and other factors.', 'Fuel type': 'Gasoline ', 'Transmission': 'Automatic', 'Engine': '2.3L I-4 DOHC, variable valve control, regular unleaded, engine', 'VIN': ' 1YVHP80C875M52664 ', 'Stock #': ' B991 ', 'Mileage': ' 151,531 mi. '} | K59: {'Accidents or damage': 'None reported', 'Clean title': 'Yes', '1-owner vehicle': 'No', 'Personal use only': 'Yes'} | L59: {} | M59: 4.8 | N59: (313 reviews) | O59: 17651 Oak Park Ave Tinley Park, IL 60477
A60: Honda | B60: 2018 | C60: Clarity Plug-In Hybrid Touring | D60: Used | E60: 93204 | F60: 17999 | G60: 17999 | H60: No | J60: {'Exterior color': ' Black ', 'Interior color': 'Black ', 'Drivetrain': 'Front-wheel Drive ', 'MPG': ' â€“', 'Fuel type': 'Hybrid ', 'Transmission': 'Automatic CVT', 'Engine': '1.5L I4 16V MPFI DOHC Hybrid', 'VIN': ' JHMZC5F30JC018879 ', 'Stock #': ' HP3255 ', 'Mileage': ' 93,204 mi. '} | K60: {'Accidents or damage': 'None reported', '1-owner vehicle': 'Yes', 'Personal use only': 'Yes', 'Open recall': 'At least 1 open recall reported'} | L60: {'Comfort': '1.0', 'Interior': '1.0', 'Performance': '1.0', 'Value': '1.0', 'Exterior': '1.0', 'Reliability': '1.0'} | M60: 4.8 | N60: (4,938 reviews) | O60: 4475 Lincoln Ave Lisle, IL 60532
A61: Lincoln | B61: 2007 | C61: Town Car Signature | D61: Used | E61: 40145 | F61: 16995 | G61: 16995 | H61: No | J61: {'Exterior color': ' Vibrant White ', 'Interior color': 'Black ', 'Drivetrain': 'Rear-wheel Drive ', 'MPG': ' 17â€“25Based on EPA mileage ratings. Use for comparison purposes only. Actual mileage will vary depending on driving conditions, driving habits, vehicle maintenance, and other factors.', 'Fuel type': 'â€“ ', 'Transmission': '4-Speed Automatic', 'Engine': '4.6L V8 16V MPFI SOHC', 'VIN': ' 1LNHM81V57Y608829 ', 'Stock #': ' AS17338 ', 'Mileage': ' 40,145 mi. '} | K61: {'Accidents or damage': 'At least 1 accident or damage reported', '1-owner vehicle': 'No', 'Personal use only': 'Yes'} | L61: {'Comfort': '5.0', 'Interior': '5.0', 'Performance': '5.0', 'Value': '5.0', 'Exterior': '5.0', 'Reliability': '5.0'} | M61: 4.4 | N61: (66 reviews) | O61: 545 E. North Ave. Carol Stream, IL 60188
A62: Lincoln | B62: 2007 | C62: Town Car Signature Limited | D62: Used | E62: 104736 | F62: 9995 | G62: 9995 | H62: No | J62: {'Exterior color': ' Cashmere Tri-Coat ', 'Interior color': 'Light Camel ', 'Drivetrain': 'Rear-wheel Drive ', 'MPG': ' 17â€“25Based on EPA mileage ratings. Use for comparison purposes only. Actual mileage will vary depending on driving conditions, driving habits, vehicle maintenance, and other factors.', 'Fuel type': 'â€“ ', 'Transmission': '4-Speed Automatic', 'Engine': '4.6L V8 16V MPFI SOHC', 'VIN': ' 1LNHM82V87Y608757 ', 'Stock #': ' AS08757 ', 'Mileage': ' 104,736 mi. '} | K62: {'Accidents or damage': 'None reported', '1-owner vehicle': 'No', 'Personal use only': 'No'} | L62: {'Comfort': '5.0', 'Interior': '5.0', 'Performance': '5.0', 'Value': '5.0', 'Exterior': '5.0', 'Reliability': '5.0'} | M62: 4.4 | N62: (66 reviews) | O62: 545 E. North Ave. Carol Stream, IL 60188
A63: Saturn | B63: 2007 | C63: Sky Red Line | D63: Used | E63: 35052 | F63: 18995 | G63: 18995 | H63: No | J63: {'Exterior color': ' Midnight Blue ', 'Interior color': 'Tan ', 'Drivetrain': 'Rear-wheel Drive ', 'MPG': ' â€“', 'Fuel type': 'Gasoline ', 'Transmission': '5-Speed Manual', 'Engine': '2.0L I4 16V GDI DOHC Turbo', 'VIN': ' 1G8MG35X47Y110785 ', 'Stock #': ' AS17784 ', 'Mileage': ' 35,052 mi. '} | K63: {'Accidents or damage': 'None reported', '1-owner vehicle': 'No', 'Personal use only': 'Yes', 'Open recall': 'At least 1 open recall reported'} | L63: {} | M63: 4.4 | N63: (66 reviews) | O63: 545 E. North Ave. Carol Stream, IL 60188
A64: Saturn | B64: 2009 | C64: Sky Base | D64: Used | E64: 26514 | F64: 15995 | G64: 15995 | H64: No | J64: {'Exterior color': ' Silver Pearl ', 'Interior color': 'Red ', 'Drivetrain': 'Rear-wheel Drive ', 'MPG': ' â€“', 'Fuel type': 'Gasoline ', 'Transmission': '5-Speed Automatic', 'Engine': '2.4L I4 16V MPFI DOHC', 'VIN': ' 1G8MN35B09Y105967 ', 'Stock #': ' AS16784 ', 'Mileage': ' 26,514 mi. '} | K64: {'Accidents or damage': 'At least 1 accident or damage reported', '1-owner vehicle': 'No', 'Personal use only': 'Yes'} | L64: {} | M64: 4.4 | N64: (66 reviews) | O64: 545 E. North Ave. Carol Stream, IL 60188
A65: Subaru | B65: 2020 | C65: WRX STI Base | D65: Used | E65: 27861 | F65: 35995 | G65: 35995 | H65: No | J65: {'Exterior color': ' WR Blue Pearl ', 'Interior color': 'Black ', 'Drivetrain': 'All-wheel Drive ', 'MPG': ' 16â€“22Based on EPA mileage ratings. Use for comparison purposes only. Actual mileage will vary depending on driving conditions, driving habits, vehicle maintenance, and other factors.', 'Fuel type': 'Gasoline ', 'Transmission': '6-Speed Manual', 'Engine': '2.5L H4 16V MPFI DOHC Turbo', 'VIN': ' JF1VA2E66L9808936 ', 'Stock #': ' AS17519 ', 'Mileage': ' 27,861 mi. '} | K65: {'Accidents or damage': 'None reported', '1-owner vehicle': 'No', 'Personal use only': 'Yes', 'Open recall': 'At least 1 open recall reported'} | L65: {'Comfort': '5.0', 'Interior': '5.0', 'Performance': '5.0', 'Value': '5.0', 'Exterior': '5.0', 'Reliability': '5.0'} | M65: 4.4 | N65: (66 reviews) | O65: 545 E. North Ave. Carol Stream, IL 60188
A66: Porsche | B66: 2018 | C66: 718 Cayman Base | D66: Used | E66: 12679 | F66: 53995 | G66: 53995 | H66: No | J66: {'Exterior color': ' Night Blue Metallic ', 'Interior color': 'Black ', 'Drivetrain': 'Rear-wheel Drive ', 'MPG': ' 21â€“28Based on EPA mileage ratings. Use for comparison purposes only. Actual mileage will vary depending on driving conditions, driving habits, vehicle maintenance, and other factors.', 'Fuel type': 'Gasoline ', 'Transmission': '6-Speed Manual', 'Engine': '2.0L H4 16V GDI DOHC Turbo', 'VIN': ' WP0AA2A89JK262252 ', 'Stock #': ' AS17691 ', 'Mileage': ' 12,679 mi. '} | K66: {'Accidents or damage': 'None reported', '1-owner vehicle': 'No', 'Personal use only': 'Yes'} | L66: {'Comfort': '5.0', 'Interior': '5.0', 'Performance': '5.0', 'Value': '4.0', 'Exterior': '5.0', 'Reliability': '5.0'} | M66: 4.4 | N66: (66 reviews) | O66: 545 E. North Ave. Carol Stream, IL 60188
A67: INFINITI | B67: 2013 | C67: G37x Base | D67: Used | E67: 87150 | F67: 16961 | G67: 16961 | H67: No | J67: {'Exterior color': ' Lapis Blue ', 'Interior color': 'Stone ', 'Drivetrain': 'All-wheel Drive ', 'MPG': ' 18â€“25Based on EPA mileage ratings. Use for comparison purposes only. Actual mileage will vary depending on driving conditions, driving habits, vehicle maintenance, and other factors.', 'Fuel type': 'Gasoline ', 'Transmission': '7-Speed Automatic with Manual Shift', 'Engine': 'VQ 3.7L V-6 DOHC, variable valve control, premium unleaded, engi', 'VIN': ' JN1CV6EL9DM981001 ', 'Stock #': ' W174467A ', 'Mileage': ' 87,150 mi. '} | K67: {'Accidents or damage': 'At least 1 accident or damage reported', '1-owner vehicle': 'No', 'Personal use only': 'No'} | L67: {} | M67: 4.7 | N67: (3,096 reviews) | O67: 700 W Dundee Rd Wheeling, IL 60090
A68: Ford | B68: 2004 | C68: Excursion Eddie Bauer | D68: Used | E68: 204560 | F68: $15,800$1,000 | G68: $15,800 | H68: Yes | J68: {'Exterior color': ' Oxford White ', 'Interior color': 'Medium Parchment ', 'Drivetrain': 'Four-wheel Drive ', 'MPG': ' 0â€“0Based on EPA mileage ratings. Use for comparison purposes only. Actual mileage will vary depending on driving conditions, driving habits, vehicle maintenance, and other factors.', 'Fuel type': 'Diesel ', 'Transmission': 'Automatic', 'Engine': 'Powerstroke 6L V-8 diesel direct injection, intercooled turbo, d', 'VIN': ' 1FMSU45P14EA87843 ', 'Stock #': ' A87843 ', 'Mileage': ' 204,560 mi. '} | K68: {'Accidents or damage': 'None reported', 'Clean title': 'Yes', '1-owner vehicle': 'No', 'Personal use only': 'Yes'} | L68: {} | O68: 1989 University Lane Unit J Lisle, IL 60532
A69: BMW | B69: 2017 | C69: X5 M Base | D69: Used | E69: 71099 | F69: 38995 | G69: 38995 | H69: No | J69: {'Exterior color': ' Gray ', 'Interior color': 'Black ', 'Drivetrain': 'All-wheel Drive ', 'MPG': ' 14â€“19Based on EPA mileage ratings. Use for comparison purposes only. Actual mileage will vary depending on driving conditions, driving habits, vehicle maintenance, and other factors.', 'Fuel type': 'Gasoline ', 'Transmission': '8-Speed Automatic', 'Engine': '4.4L V8 32V GDI DOHC Twin Turbo', 'VIN': ' 5YMKT6C39H0U39337 ', 'Stock #': ' A2716 ', 'Mileage': ' 71,099 mi. '} | K69: {'Accidents or damage': 'At least 1 accident or damage reported', '1-owner vehicle': 'Yes', 'Personal use only': 'Yes'} | L69: {'Comfort': '4.0', 'Interior': '5.0', 'Performance': '5.0', 'Value': '4.0', 'Exterior': '5.0', 'Reliability': '5.0'} | M69: 4.1 | N69: (46 reviews) | O69: 27W333 North Ave IL West Chicago, IL 60185
A70: BMW | B70: 2018 | C70: 340 Gran Turismo i xDrive | D70: Used | E70: 91475 | F70: 22440 | G70: 22440 | H70: No | J70: {'Exterior color': ' Black Sapphire Metallic ', 'Interior color': 'Oyster ', 'Drivetrain': 'All-wheel Drive ', 'MPG': ' 20â€“29Based on EPA mileage ratings. Use for comparison purposes only. Actual mileage will vary depending on driving conditions, driving habits, vehicle maintenance, and other factors.', 'Fuel type': 'Gasoline ', 'Transmission': '8-Speed Automatic', 'Engine': '3.0L I6 24V GDI DOHC Turbo', 'VIN': ' WBA8Y3C52JG451439 ', 'Stock #': ' 451439 ', 'Mileage': ' 91,475 mi. '} | K70: {'Accidents or damage': 'At least 1 accident or damage reported', 'Clean title': 'Yes', '1-owner vehicle': 'No', 'Personal use only': 'No'} | L70: {} | M70: 4.1 | N70: (60 reviews) | O70: 10926 southwest highway palos hills, IL 60465
A71: BMW | B71: 2017 | C71: M6 Base | D71: Used | E71: 14826 | F71: 78800 | G71: 78800 | H71: No | J71: {'Exterior color': ' Space Gray Metallic ', 'Interior color': 'Black ', 'Drivetrain': 'Rear-wheel Drive ', 'MPG': ' 14â€“20Based on EPA mileage ratings. Use for comparison purposes only. Actual mileage will vary depending on driving conditions, driving habits, vehicle maintenance, and other factors.', 'Fuel type': 'Gasoline ', 'Transmission': '6-Speed Manual', 'Engine': '4.4L V8 32V GDI DOHC Twin Turbo', 'VIN': ' WBS6J9C5XHD934733 ', 'Stock #': ' 934733 ', 'Mileage': ' 14,826 mi. '} | K71: {'Accidents or damage': 'None reported', '1-owner vehicle': 'No', 'Personal use only': 'Yes'} | L71: {'Comfort': '5.0', 'Interior': '5.0', 'Performance': '5.0', 'Value': '4.0', 'Exterior': '5.0', 'Reliability': '5.0'} | M71: 4.7 | N71: (318 reviews) | O71: 2895 Ogden Ave Lisle, IL 60532
A72: Mercedes-Benz | B72: 2019 | C72: AMG CLS 53 S 4MATIC | D72: Used | E72: 38545 | F72: 48999 | G72: 48999 | H72: No | J72: {'Exterior color': ' Gray ', 'Interior color': 'Black ', 'Drivetrain': 'All-wheel Drive ', 'MPG': ' 21â€“27Based on EPA mileage ratings. Use for comparison purposes only. Actual mileage will vary depending on driving conditions, driving habits, vehicle maintenance, and other factors.', 'Fuel type': 'Gasoline ', 'Transmission': '9-Speed Automatic', 'Engine': 'AMG 3L I-6 gasoline direct injection, DOHC, variable valve contr', 'VIN': ' WDD2J6BB9KA031693 ', 'Stock #': ' 25185G ', 'Mileage': ' 38,545 mi. '} | K72: {'Accidents or damage': 'None reported', '1-owner vehicle': 'Yes', 'Personal use only': 'Yes'} | L72: {} | M72: 4.5 | N72: (16 reviews) | O72: 2772 Skokie Valley Road Highland Park, IL 60035
A73: BMW | B73: 2019 | C73: M6 Gran Coupe Gran Coupe | D73: Used | E73: 31010 | F73: 53895 | G73: 53895 | H73: No | J73: {'Exterior color': ' San Marino Blue Metallic ', 'Interior color': 'Black ', 'Drivetrain': 'Rear-wheel Drive ', 'MPG': ' 14â€“20Based on EPA mileage ratings. Use for comparison purposes only. Actual mileage will vary depending on driving conditions, driving habits, vehicle maintenance, and other factors.', 'Fuel type': 'Gasoline ', 'Transmission': '7-Speed Automatic with Auto-Shift', 'Engine': '4.4L V8 32V GDI DOHC Twin Turbo', 'VIN': ' WBS6E9C5XKG808463 ', 'Stock #': ' 808463 ', 'Mileage': ' 31,010 mi. '} | K73: {'Accidents or damage': 'None reported', '1-owner vehicle': 'No', 'Personal use only': 'Yes'} | L73: {'Comfort': '5.0', 'Interior': '5.0', 'Performance': '5.0', 'Value': '5.0', 'Exterior': '5.0', 'Reliability': 'â€”'} | O73: 641 Estes Ave Schaumburg, IL 60193
A74: Ford | B74: 2003 | C74: Excursion Limited | D74: Used | E74: 199574 | F74: $25,975$7,000 | G74: $25,975 | H74: Yes | J74: {'Exterior color': ' Black Clearcoat ', 'Interior color': 'Medium Pebble ', 'Drivetrain': 'Four-wheel Drive ', 'MPG': ' 0â€“0Based on EPA mileage ratings. Use for comparison purposes only. Actual mileage will vary depending on driving conditions, driving habits, vehicle maintenance, and other factors.', 'Fuel type': 'Diesel ', 'Transmission': 'Automatic', 'Engine': 'Powerstroke 6L V-8 diesel direct injection, intercooled turbo, d', 'VIN': ' 1FMSU43P43EC31757 ', 'Stock #': ' B9213B ', 'Mileage': ' 199,574 mi. '} | K74: {'Accidents or damage': 'None reported', '1-owner vehicle': 'No', 'Personal use only': 'Yes'} | L74: {} | M74: 4.9 | N74: (5,683 reviews) | O74: 777 west dundee rd Arlington heights, IL 60004
A75: BMW | B75: 2014 | C75: M6 Base | D75: Used | E75: 78188 | F75: 28990 | G75: 28990 | H75: No | J75: {'Exterior color': ' Blue ', 'Interior color': 'Black ', 'Drivetrain': 'Rear-wheel Drive ', 'MPG': ' 16â€“24Based on EPA mileage ratings. Use for comparison purposes only. Actual mileage will vary depending on driving conditions, driving habits, vehicle maintenance, and other factors.', 'Fuel type': 'Gasoline ', 'Transmission': 'Auto 7Spd DblCltch DrvLgc', 'Engine': 'V8, Twin Turbo, 4.4 Liter', 'VIN': ' WBSLZ9C50ED651197 ', 'Stock #': ' 651197A ', 'Mileage': ' 78,188 mi. '} | K75: {'Accidents or damage': 'At least 1 accident or damage reported', '1-owner vehicle': 'No', 'Personal use only': 'Yes'} | L75: {} | M75: 2.7 | N75: (613 reviews) | O75: 1600 Hicks Rd Rolling Meadows, IL 60008
A76: Lexus | B76: 2024 | C76: LC 500 Base | D76: New | E76: 0 | F76: $115,425 | G76: $115,425 | H76: No | I76: MSRP $115,425 | J76: {'Exterior color': ' Infrared ', 'Interior color': 'Black W/ Satin Metallic Trim ', 'Drivetrain': 'Rear-wheel Drive ', 'MPG': ' 15â€“0Based on EPA mileage ratings. Use for comparison purposes only. Actual mileage will vary depending on driving conditions, driving habits, vehicle maintenance, and other factors.', 'Fuel type': 'Gasoline ', 'Transmission': 'Automatic', 'Engine': '5L V-8 port/direct injection, DOHC, VVT-i variable valve control', 'VIN': ' JTHMPAAY4RA109302 ', 'Stock #': ' 240509 ', 'Mileage': ' 0 mi. '} | K76: {} | L76: {} | M76: 4.9 | N76: (2,276 reviews) | O76: 350 E Golf Rd Schaumburg, IL 60173
A77: Audi | B77: 2021 | C77: SQ7 4.0T Premium Plus | D77: Used | E77: 60120 | F77: 49980 | G77: 49980 | H77: No | J77: {'Exterior color': ' Florett Silver Metallic ', 'Interior color': 'Black ', 'Drivetrain': 'All-wheel Drive ', 'MPG': ' 15â€“21Based on EPA mileage ratings. Use for comparison purposes only. Actual mileage will vary depending on driving conditions, driving habits, vehicle maintenance, and other factors.', 'Fuel type': 'Gasoline ', 'Transmission': '8-Speed Automatic', 'Engine': '4.0L V8 32V GDI DOHC Twin Turbo', 'VIN': ' WA1AWBF75MD010857 ', 'Stock #': ' PA478A ', 'Mileage': ' 60,120 mi. '} | K77: {'Accidents or damage': 'At least 1 accident or damage reported', '1-owner vehicle': 'Yes', 'Personal use only': 'Yes'} | L77: {'Comfort': '5.0', 'Interior': '5.0', 'Performance': '5.0', 'Value': '5.0', 'Exterior': '5.0', 'Reliability': '5.0'} | M77: 4.7 | N77: (5,251 reviews) | O77: 1200 W Golf Rd Hoffman Estates, IL 60169
A78: McLaren | B78: 2016 | C78: 675LT Base | D78: Used | E78: 852 | F78: $339,800$10,000 | G78: $339,800 | H78: Yes | J78: {'Exterior color': ' Storm Grey ', 'Interior color': 'Carbon Black with McLaren Orange ', 'Drivetrain': 'Rear-wheel Drive ', 'MPG': ' 16â€“22Based on EPA mileage ratings. Use for comparison purposes only. Actual mileage will vary depending on driving conditions, driving habits, vehicle maintenance, and other factors.', 'Fuel type': 'Gasoline ', 'Transmission': '7-Speed Double Clutch', 'Engine': '3.8L Twin Turbo V8 666hp 516ft. lbs.', 'VIN': ' SBM11RAA3GW675109 ', 'Stock #': ' 20638 ', 'Mileage': ' 852 mi. '} | K78: {'Accidents or damage': 'None reported', '1-owner vehicle': 'No', 'Personal use only': 'No', 'Open recall': 'At least 1 open recall reported'} | L78: {'Comfort': '5.0', 'Interior': '5.0', 'Performance': '5.0', 'Value': '5.0', 'Exterior': '5.0', 'Reliability': '5.0'} | M78: 4.7 | N78: (715 reviews) | O78: 27w110 North Ave West Chicago, IL 60185
A79: Porsche | B79: 2017 | C79: 718 Cayman Base | D79: Used | E79: 41311 | F79: 45911 | G79: 45911 | H79: No | J79: {'Exterior color': ' Black ', 'Interior color': 'Black ', 'Drivetrain': 'Rear-wheel Drive ', 'MPG': ' 21â€“28Based on EPA mileage ratings. Use for comparison purposes only. Actual mileage will vary depending on driving conditions, driving habits, vehicle maintenance, and other factors.', 'Fuel type': 'Gasoline ', 'Transmission': '7-Speed Automatic with Auto-Shift', 'Engine': '2.0L H4 16V GDI DOHC Turbo', 'VIN': ' WP0AA2A84HS270253 ', 'Stock #': ' 902552B ', 'Mileage': ' 41,311 mi. '} | K79: {'Accidents or damage': 'None reported', 'Clean title': 'Yes', '1-owner vehicle': 'No', 'Personal use only': 'Yes'} | L79: {'Comfort': '5.0', 'Interior': '5.0', 'Performance': '5.0', 'Value': '5.0', 'Exterior': '5.0', 'Reliability': '5.0'} | O79: 1951 N. Rand Road Palatine, IL 60074
A80: Nissan | B80: 2005 | C80: 350Z Touring | D80: Used | E80: 46347 | F80: 16500 | G80: 16500 | H80: No | J80: {'Exterior color': ' Daytona Blue ', 'Interior color': 'Beige ', 'Drivetrain': 'Rear-wheel Drive ', 'MPG': ' 18â€“25Based on EPA mileage ratings. Use for comparison purposes only. Actual mileage will vary depending on driving conditions, driving habits, vehicle maintenance, and other factors.', 'Fuel type': 'Gasoline ', 'Transmission': '5-Speed Automatic', 'Engine': '3.5L V6 24V MPFI DOHC', 'VIN': ' JN1AZ36A45M759054 ', 'Stock #': ' 0070 ', 'Mileage': ' 46,347 mi. '} | K80: {'Accidents or damage': 'None reported', '1-owner vehicle': 'No', 'Personal use only': 'Yes'} | L80: {} | M80: 4.7 | N80: (34 reviews) | O80: 1823 Centrepoint Circle Naperville, IL 60563
A81: Audi | B81: 2008 | C81: TT 3.2 quattro | D81: Used | E81: 86447 | F81: 15500 | G81: 15500 | H81: No | J81: {'Exterior color': ' Blue ', 'Interior color': 'Black ', 'Drivetrain': 'All-wheel Drive ', 'MPG': ' 24Based on EPA mileage ratings. Use for comparison purposes only. Actual mileage will vary depending on driving conditions, driving habits, vehicle maintenance, and other factors.', 'Fuel type': 'Gasoline ', 'Transmission': 'Automatic', 'Engine': '3.2L V6 24V MPFI DOHC', 'VIN': ' TRUDD38J581017067 ', 'Stock #': ' 5453 ', 'Mileage': ' 86,447 mi. '} | K81: {'Accidents or damage': 'None reported', '1-owner vehicle': 'No', 'Personal use only': 'Yes'} | L81: {} | M81: 4.4 | N81: (47 reviews) | O81: 2232 N Rand Rd Palatine, IL 60074
A82: INFINITI | B82: 2009 | C82: G37 Sport | D82: Used | E82: 94164 | F82: 15800 | G82: 15800 | H82: No | J82: {'Exterior color': ' Moonlight White ', 'Interior color': 'Black ', 'Drivetrain': 'Rear-wheel Drive ', 'MPG': ' 17â€“25Based on EPA mileage ratings. Use for comparison purposes only. Actual mileage will vary depending on driving conditions, driving habits, vehicle maintenance, and other factors.', 'Fuel type': 'Gasoline ', 'Transmission': '6-Speed Manual', 'Engine': '3.7L V6 24V MPFI DOHC', 'VIN': ' JNKCV64E29M600868 ', 'Stock #': ' 00134 ', 'Mileage': ' 94,164 mi. '} | K82: {'Accidents or damage': 'None reported', '1-owner vehicle': 'No', 'Personal use only': 'Yes'} | L82: {} | M82: 4.7 | N82: (34 reviews) | O82: 1823 Centrepoint Circle Naperville, IL 60563
A83: Lotus | B83: 2005 | C83: Elise BASE | D83: Used | E83: 19127 | F83: 59800 | G83: 59800 | H83: No | J83: {'Exterior color': ' GREY ', 'Interior color': 'â€“ ', 'Drivetrain': 'Rear-wheel Drive ', 'MPG': ' 23â€“25Based on EPA mileage ratings. Use for comparison purposes only. Actual mileage will vary depending on driving conditions, driving habits, vehicle maintenance, and other factors.', 'Fuel type': 'Gasoline ', 'Transmission': 'Manual', 'Engine': '1.8L I-4 DOHC, variable valve control, premium unleaded, engine', 'VIN': ' SCCPC11135HL34579 ', 'Stock #': ' 10181 ', 'Mileage': ' 19,127 mi. '} | K83: {'Accidents or damage': 'None reported', '1-owner vehicle': 'Yes', 'Personal use only': 'Yes'} | L83: {} | O83: 562 W 5th Ave Naperville, IL 60563
A84: Lincoln | B84: 1988 | C84: Town Car Signature | D84: Used | E84: 72980 | F84: 16950 | G84: 16950 | H84: No | J84: {'Exterior color': ' ROSE ', 'Interior color': 'Rose ', 'Drivetrain': 'Rear-wheel Drive ', 'MPG': ' 17â€“24Based on EPA mileage ratings. Use for comparison purposes only. Actual mileage will vary depending on driving conditions, driving habits, vehicle maintenance, and other factors.', 'Fuel type': 'Gasoline ', 'Transmission': 'Automatic', 'Engine': '5.0L', 'VIN': ' 1LNBM82FXJY616316 ', 'Stock #': ' 0113 ', 'Mileage': ' 72,980 mi. '} | K84: {'Accidents or damage': 'None reported', 'Clean title': 'Yes', '1-owner vehicle': 'No', 'Personal use only': 'Yes'} | L84: {} | M84: 4.3 | N84: (12 reviews) | O84: 503 South Weber Road Bolingbrook, IL 60490
A85: BMW | B85: 2010 | C85: M6 Base (M7) | D85: Used | E85: 28006 | F85: 31995 | G85: 31995 | H85: No | J85: {'Exterior color': ' Blue ', 'Interior color': 'Black ', 'Drivetrain': 'Rear-wheel Drive ', 'MPG': ' 11â€“17Based on EPA mileage ratings. Use for comparison purposes only. Actual mileage will vary depending on driving conditions, driving habits, vehicle maintenance, and other factors.', 'Fuel type': 'Gasoline ', 'Transmission': '7-Speed Automatic with Auto-Shift', 'Engine': '5.0L V10 40V MPFI DOHC', 'VIN': ' WBSEK9C50ACY80301 ', 'Stock #': ' 4211 ', 'Mileage': ' 28,006 mi. '} | K85: {'Accidents or damage': 'None reported', '1-owner vehicle': 'No', 'Personal use only': 'Yes'} | L85: {} | M85: 2.3 | N85: (54 reviews) | O85: 601 W. Roosevelt West Chicago, IL 60185
A86: Cadillac | B86: 2022 | C86: CT5-V V-Series Blackwing | D86: Used | E86: 58099 | F86: 73995 | G86: 73995 | H86: No | J86: {'Exterior color': ' Black Raven ', 'Interior color': 'Jet Black With Jet Black Accents ', 'Drivetrain': 'Rear-wheel Drive ', 'MPG': ' 13â€“22Based on EPA mileage ratings. Use for comparison purposes only. Actual mileage will vary depending on driving conditions, driving habits, vehicle maintenance, and other factors.', 'Fuel type': 'Gasoline ', 'Transmission': 'Automatic', 'Engine': '6.2L V-8 gasoline direct injection, VVT variable valve control,', 'VIN': ' 1G6D35R6XN0810386 ', 'Stock #': ' 24197A ', 'Mileage': ' 58,099 mi. '} | K86: {'Accidents or damage': 'None reported', '1-owner vehicle': 'Yes', 'Personal use only': 'No'} | L86: {'Comfort': '5.0', 'Interior': '5.0', 'Performance': '5.0', 'Value': '5.0', 'Exterior': '5.0', 'Reliability': '5.0'} | M86: 4.6 | N86: (258 reviews) | O86: 1507 W. Ogden Ave. Naperville, IL 60540
A87: Audi | B87: 2011 | C87: TTS 2.0T Prestige quattro | D87: Used | E87: 90001 | F87: 15495 | G87: 15495 | H87: No | J87: {'Exterior color': ' Black ', 'Interior color': 'Madras Brown ', 'Drivetrain': 'All-wheel Drive ', 'MPG': ' 21â€“29Based on EPA mileage ratings. Use for comparison purposes only. Actual mileage will vary depending on driving conditions, driving habits, vehicle maintenance, and other factors.', 'Fuel type': 'Gasoline ', 'Transmission': '6-Speed Automatic with Auto-Shift', 'Engine': '2.0L I4 16V GDI DOHC Turbo', 'VIN': ' TRU41AFKXB1004444 ', 'Stock #': ' 3981A ', 'Mileage': ' 90,001 mi. '} | K87: {'Accidents or damage': 'At least 1 accident or damage reported', '1-owner vehicle': 'No', 'Personal use only': 'Yes'} | L87: {} | M87: 2.3 | N87: (54 reviews) | O87: 601 W. Roosevelt West Chicago, IL 60185
A88: Ferrari | B88: 1983 | C88: 512 BERLINETTA | D88: Used | E88: 32252 | F88: $299,900$10,000 | G88: $299,900 | H88: Yes | J88: {'Exterior color': ' Red ', 'Interior color': 'Beige ', 'Drivetrain': 'â€“ ', 'MPG': ' â€“', 'Fuel type': 'Gasoline ', 'Transmission': 'Manual', 'Engine': '12 Cylinder', 'VIN': ' ZFFJA09B000045131 ', 'Stock #': ' 45131 ', 'Mileage': ' 32,252 mi. '} | K88: {'Accidents or damage': 'None reported', '1-owner vehicle': 'No', 'Personal use only': 'No'} | L88: {} | O88: 990 N Shore Dr Lake Bluff, IL 60044
A89: Volkswagen | B89: 2019 | C89: Golf SportWagen 1.8T S | D89: Used | E89: 98185 | F89: $12,200$300 | G89: $12,200 | H89: Yes | J89: {'Exterior color': ' Platinum Gray Metallic ', 'Interior color': 'Titan Black ', 'Drivetrain': 'All-wheel Drive ', 'MPG': ' 22â€“29Based on EPA mileage ratings. Use for comparison purposes only. Actual mileage will vary depending on driving conditions, driving habits, vehicle maintenance, and other factors.', 'Fuel type': 'Gasoline ', 'Transmission': '6-Speed Automatic with Auto-Shift', 'Engine': '1.8L I4 16V GDI DOHC Turbo', 'VIN': ' 3VW117AU3KM508875 ', 'Stock #': ' V048142A ', 'Mileage': ' 98,185 mi. '} | K89: {'Accidents or damage': 'None reported', '1-owner vehicle': 'No', 'Personal use only': 'No', 'Open recall': 'At least 1 open recall reported'} | L89: {'Comfort': '5.0', 'Interior': '5.0', 'Performance': '5.0', 'Value': '5.0', 'Exterior': '5.0', 'Reliability': '5.0'} | M89: 4.6 | N89: (2,401 reviews) | O89: 1111 N Clark St Chicago, IL 60610
A90: Rolls | B90: 2009 | C90: Royce Phantom Coupe | D90: Used | E90: 52756 | F90: 139800 | G90: 139800 | H90: No | J90: {'Exterior color': ' Diamond Black ', 'Interior color': 'Moccasin ', 'Drivetrain': 'Rear-wheel Drive ', 'MPG': ' 11â€“18Based on EPA mileage ratings. Use for comparison purposes only. Actual mileage will vary depending on driving conditions, driving habits, vehicle maintenance, and other factors.', 'Fuel type': 'Gasoline ', 'Transmission': '6-Speed Automatic', 'Engine': '6.8L V12 48V GDI DOHC', 'VIN': ' SCA3C67599UX32035 ', 'Stock #': ' GC4004A ', 'Mileage': ' 52,756 mi. '} | K90: {'Accidents or damage': 'None reported', '1-owner vehicle': 'No', 'Personal use only': 'Yes'} | L90: {'Comfort': '5.0', 'Interior': '5.0', 'Performance': '5.0', 'Value': '4.0', 'Exterior': '5.0', 'Reliability': '5.0'} | O90: 834 N Rush St Chicago, IL 60611
A91: Genesis | B91: 2023 | C91: G90 3.5T e-SC AWD | D91: New | E91: 5 | F91: $89,485 | G91: $89,485 | H91: No | I91: MSRP $101,485 | J91: {'Exterior color': ' Makalu Gray Matte ', 'Interior color': 'Urban Brown/Glacier White ', 'Drivetrain': 'All-wheel Drive ', 'MPG': ' 17â€“24Based on EPA mileage ratings. Use for comparison purposes only. Actual mileage will vary depending on driving conditions, driving habits, vehicle maintenance, and other factors.', 'Fuel type': 'Gasoline ', 'Transmission': '8-Speed Automatic', 'Engine': '3.5L V-6 port/direct injection, DOHC, variable valve control, tw', 'VIN': ' KMTFC4SD0PU029849 ', 'Stock #': ' G23095 ', 'Mileage': ' 5 mi. '} | K91: {} | L91: {} | M91: 4.1 | N91: (986 reviews) | O91: 2720 South Michigan Avenue Chicago, IL 60616
A92: Chevrolet | B92: 2015 | C92: Impala LS | D92: Used | E92: 105307 | F92: 14995 | G92: 14995 | H92: No | J92: {'Exterior color': ' Silver Ice Metallic ', 'Interior color': 'Dark Titanium/Jet Black ', 'Drivetrain': 'Front-wheel Drive ', 'MPG': ' 22â€“31Based on EPA mileage ratings. Use for comparison purposes only. Actual mileage will vary depending on driving conditions, driving habits, vehicle maintenance, and other factors.', 'Fuel type': 'Gasoline ', 'Transmission': 'Automatic', 'Engine': 'ECOTEC 2.5L I-4 gasoline direct injection, DOHC, variable valve', 'VIN': ' 1G11Z5SL7FU110407 ', 'Stock #': ' 10720 ', 'Mileage': ' 105,307 mi. '} | K92: {'Accidents or damage': 'None reported', '1-owner vehicle': 'No', 'Personal use only': 'No'} | L92: {} | O92: 4400 South Archer Avenue Chicago, IL 60632
A93: Chevrolet | B93: 2018 | C93: Impala 1LT | D93: Used | E93: 112099 | F93: 15995 | G93: 15995 | H93: No | J93: {'Exterior color': ' Mosaic Black Metallic ', 'Interior color': 'Jet Black ', 'Drivetrain': 'Front-wheel Drive ', 'MPG': ' 22â€“30Based on EPA mileage ratings. Use for comparison purposes only. Actual mileage will vary depending on driving conditions, driving habits, vehicle maintenance, and other factors.', 'Fuel type': 'Gasoline ', 'Transmission': 'Automatic', 'Engine': 'Ecotec 2.5L I-4 gasoline direct injection, DOHC, variable valve', 'VIN': ' 1G1105SA5JU139132 ', 'Stock #': ' 11106 ', 'Mileage': ' 112,099 mi. '} | K93: {'Accidents or damage': 'None reported', '1-owner vehicle': 'Yes', 'Personal use only': 'No'} | L93: {} | O93: 4400 South Archer Avenue Chicago, IL 60632
A94: Dodge | B94: 2015 | C94: Durango SXT | D94: Used | E94: 132502 | F94: $14,995$2,000 | G94: $14,995 | H94: Yes | J94: {'Exterior color': ' Deep Cherry Red Crystal Pearlcoat ', 'Interior color': 'Black ', 'Drivetrain': 'Rear-wheel Drive ', 'MPG': ' 18â€“25Based on EPA mileage ratings. Use for comparison purposes only. Actual mileage will vary depending on driving conditions, driving habits, vehicle maintenance, and other factors.', 'Fuel type': 'Gasoline ', 'Transmission': 'Automatic', 'Engine': '3.6L V-6 DOHC, variable valve control, regular unleaded, engine', 'VIN': ' 1C4RDHAG7FC127843 ', 'Stock #': ' 10755 ', 'Mileage': ' 132,502 mi. '} | K94: {'Accidents or damage': 'At least 1 accident or damage reported', '1-owner vehicle': 'No', 'Personal use only': 'Yes'} | L94: {} | O94: 4400 South Archer Avenue Chicago, IL 60632
A95: INFINITI | B95: 2012 | C95: G37x Sport Appearance Edition | D95: Used | E95: 84766 | F95: 11949 | G95: 11949 | H95: No | J95: {'Exterior color': ' Graphite Shadow ', 'Interior color': 'Graphite ', 'Drivetrain': 'All-wheel Drive ', 'MPG': ' 18â€“25Based on EPA mileage ratings. Use for comparison purposes only. Actual mileage will vary depending on driving conditions, driving habits, vehicle maintenance, and other factors.', 'Fuel type': 'Gasoline ', 'Transmission': 'Automatic', 'Engine': 'VQ 3.7L V-6 DOHC, variable valve control, premium unleaded, engi', 'VIN': ' JN1CV6AR7CM682020 ', 'Stock #': ' C15106 ', 'Mileage': ' 84,766 mi. '} | K95: {'Accidents or damage': 'At least 1 accident or damage reported', '1-owner vehicle': 'No', 'Personal use only': 'Yes'} | L95: {} | M95: 4.6 | N95: (1,035 reviews) | O95: 4747 S Pulaski Rd Chicago, IL 60632
A96: Ford | B96: 2019 | C96: Escape SEL | D96: Used | E96: 66533 | F96: $15,903$912 | G96: $15,903 | H96: Yes | J96: {'Exterior color': ' Ingot Silver ', 'Interior color': 'Charcoal Black ', 'Drivetrain': 'Four-wheel Drive ', 'MPG': ' 22â€“28Based on EPA mileage ratings. Use for comparison purposes only. Actual mileage will vary depending on driving conditions, driving habits, vehicle maintenance, and other factors.', 'Fuel type': 'Gasoline ', 'Transmission': 'Automatic', 'Engine': 'EcoBoost 1.5L I-4 gasoline direct injection, DOHC, iVCT variable', 'VIN': ' 1FMCU9HD0KUA10323 ', 'Stock #': ' PA6195 ', 'Mileage': ' 66,533 mi. '} | K96: {'Accidents or damage': 'None reported', 'Clean title': 'Yes', '1-owner vehicle': 'No', 'Personal use only': 'No'} | L96: {} | M96: 4.5 | N96: (1,513 reviews) | O96: 6900 McCormick Blvd Lincolnwood, IL 60712
A97: Subaru | B97: 2019 | C97: WRX STI Base | D97: Used | E97: 53038 | F97: $30,990$1,000 | G97: $30,990 | H97: Yes | J97: {'Exterior color': ' Dark Gray Metallic ', 'Interior color': 'Black ', 'Drivetrain': 'All-wheel Drive ', 'MPG': ' 17â€“22Based on EPA mileage ratings. Use for comparison purposes only. Actual mileage will vary depending on driving conditions, driving habits, vehicle maintenance, and other factors.', 'Fuel type': 'Gasoline ', 'Transmission': '6-Speed Manual', 'Engine': '2.5L H4 16V MPFI DOHC Turbo', 'VIN': ' JF1VA2S65K9831126 ', 'Stock #': ' VK1260A ', 'Mileage': ' 53,038 mi. '} | K97: {'Accidents or damage': 'At least 1 accident or damage reported', '1-owner vehicle': 'No', 'Personal use only': 'Yes', 'Open recall': 'At least 1 open recall reported'} | L97: {'Comfort': '5.0', 'Interior': '5.0', 'Performance': '5.0', 'Value': '4.0', 'Exterior': '5.0', 'Reliability': 'â€”'} | M97: 4.9 | N97: (2,290 reviews) | O97: 1033 Chicago Ave Evanston, IL 60202
A98: Volkswagen | B98: 2018 | C98: Golf R 2.0T w/DCC & Navigation | D98: Certified | E98: 41540 | F98: $32,490$500 | G98: $32,490 | H98: Yes | J98: {'Exterior color': ' Indium Gray Metallic ', 'Interior color': 'Titan Black ', 'Drivetrain': 'All-wheel Drive ', 'MPG': ' 21â€“29Based on EPA mileage ratings. Use for comparison purposes only. Actual mileage will vary depending on driving conditions, driving habits, vehicle maintenance, and other factors.', 'Fuel type': 'Gasoline ', 'Transmission': '6-Speed Manual', 'Engine': '2.0L I4 16V GDI DOHC Turbo', 'VIN': ' WVWWF7AU7JW249946 ', 'Stock #': ' V3620A ', 'Mileage': ' 41,540 mi. '} | K98: {'Accidents or damage': 'None reported', '1-owner vehicle': 'No', 'Personal use only': 'Yes'} | L98: {'Comfort': '5.0', 'Interior': '5.0', 'Performance': '5.0', 'Value': '4.0', 'Exterior': '4.0', 'Reliability': '5.0'} | M98: 4.9 | N98: (2,290 reviews) | O98: 1033 Chicago Ave Evanston, IL 60202
A99: Ford | B99: 2012 | C99: E250 Cargo | D99: Used | E99: 115225 | F99: $14,980$810 | G99: $14,980 | H99: Yes | J99: {'Exterior color': ' White ', 'Interior color': 'Gray ', 'Drivetrain': 'Rear-wheel Drive ', 'MPG': ' 16â€“16Based on EPA mileage ratings. Use for comparison purposes only. Actual mileage will vary depending on driving conditions, driving habits, vehicle maintenance, and other factors.', 'Fuel type': 'E85 Flex Fuel ', 'Transmission': 'Automatic 4-Speed', 'Engine': '5.4L V8', 'VIN': ' 1FTNE2EL9CDB20236 ', 'Stock #': ' A060 ', 'Mileage': ' 115,225 mi. '} | K99: {'Accidents or damage': 'None reported', 'Clean title': 'Yes', '1-owner vehicle': 'Yes', 'Personal use only': 'Yes'} | L99: {'Comfort': '4.0', 'Interior': '4.0', 'Performance': '4.0', 'Value': '5.0', 'Exterior': '4.0', 'Reliability': '5.0'} | O99: 6400 Harlem Ave Summit, IL 60501
A100: Chevrolet | B100: 2021 | C100: Malibu 1LS | D100: Used | E100: 29804 | F100: 21000 | G100: 21000 | H100: No | J100: {'Exterior color': ' Silver Ice Metallic ', 'Interior color': 'Jet Black ', 'Drivetrain': 'Front-wheel Drive ', 'MPG': ' 29â€“36Based on EPA mileage ratings. Use for comparison purposes only. Actual mileage will vary depending on driving conditions, driving habits, vehicle maintenance, and other factors.', 'Fuel type': 'Gasoline ', 'Transmission': 'Automatic CVT', 'Engine': '1.5L I4 16V GDI DOHC Turbo', 'VIN': ' 1G1ZC5ST9MF042228 ', 'Stock #': ' B13723 ', 'Mileage': ' 29,804 mi. '} | K100: {'Accidents or damage': 'None reported', '1-owner vehicle': 'No', 'Personal use only': 'Yes'} | L100: {} | M100: 4.5 | N100: (3,514 reviews) | O100: 1600 W North Ave Melrose Park, IL 60160
...

Sheet Clean Sheet
A1: Car_ID | B1: Make | C1: Year | D1: Condition | E1: Mileage | F1: Milage_Group | G1: Price_Drop | H1: Price | I1: Exterior_Color | J1: Interior _Color | K1: Drivetrain | L1: MPG | M1: Accident | N1: Seller_Rating
A2: 1 | B2: Lexus | C2: 2024 | D2: New | E2: 0 | F2: =IF((Table5[[#This Row],[Mileage]])=0, "None", IF(Table5[[#This Row],[Mileage]]<10000, "Low", IF(Table5[[#This Row],[Mileage]]<55000, "Average", "High"))) -> None | G2: No | H2: 112865 | I2: Caviar | J2: Black | K2: Rear-wheel Drive | L2: 15 | M2: No | N2: 4.7
A3: 2 | B3: Acura | C3: 2007 | D3: Used | E3: 61110 | F3: =IF((Table5[[#This Row],[Mileage]])=0, "None", IF(Table5[[#This Row],[Mileage]]<10000, "Low", IF(Table5[[#This Row],[Mileage]]<55000, "Average", "High"))) -> High | G3: No | H3: 11295 | I3: Alabaster Silver Metallic | J3: - | K3: Rear-wheel Drive | L3: - | M3: Yes | N3: 4.2
A4: 3 | B4: McLaren | C4: 2016 | D4: Used | E4: 6305 | F4: =IF((Table5[[#This Row],[Mileage]])=0, "None", IF(Table5[[#This Row],[Mileage]]<10000, "Low", IF(Table5[[#This Row],[Mileage]]<55000, "Average", "High"))) -> Low | G4: Yes | H4: 219997 | I4: McLaren Orange | J4: Carbon Black | K4: Rear-wheel Drive | L4: - | M4: Yes | N4: 3.1
A5: 4 | B5: Audi | C5: 2016 | D5: Used | E5: 65715 | F5: =IF((Table5[[#This Row],[Mileage]])=0, "None", IF(Table5[[#This Row],[Mileage]]<10000, "Low", IF(Table5[[#This Row],[Mileage]]<55000, "Average", "High"))) -> High | G5: No | H5: 23999 | I5: Black | J5: Black | K5: All-wheel Drive | L5: 23 | M5: Yes | N5: 3.6
A6: 5 | B6: BMW | C6: 2018 | D6: Used | E6: 19830 | F6: =IF((Table5[[#This Row],[Mileage]])=0, "None", IF(Table5[[#This Row],[Mileage]]<10000, "Low", IF(Table5[[#This Row],[Mileage]]<55000, "Average", "High"))) -> Average | G6: Yes | H6: 39799 | I6: Imperial Blue Metallic | J6: Black | K6: All-wheel Drive | L6: 0 | M6: No | N6: 4.4
A7: 6 | B7: Jeep | C7: 2019 | D7: Used | E7: 52245 | F7: =IF((Table5[[#This Row],[Mileage]])=0, "None", IF(Table5[[#This Row],[Mileage]]<10000, "Low", IF(Table5[[#This Row],[Mileage]]<55000, "Average", "High"))) -> Average | G7: Yes | H7: 22966 | I7: Diamond Black | J7: Black | K7: Four-wheel Drive | L7: 19 | M7: Yes | N7: 4.2
A8: 7 | B8: Cadillac | C8: 2019 | D8: Used | E8: 94008 | F8: =IF((Table5[[#This Row],[Mileage]])=0, "None", IF(Table5[[#This Row],[Mileage]]<10000, "Low", IF(Table5[[#This Row],[Mileage]]<55000, "Average", "High"))) -> High | G8: Yes | H8: 26995 | I8: Black | J8: Black | K8: All-wheel Drive | L8: 18 | M8: Yes | N8: 4.1
A9: 8 | B9: Nissan | C9: 2012 | D9: Used | E9: 110202 | F9: =IF((Table5[[#This Row],[Mileage]])=0, "None", IF(Table5[[#This Row],[Mileage]]<10000, "Low", IF(Table5[[#This Row],[Mileage]]<55000, "Average", "High"))) -> High | G9: No | H9: 14985 | I9: Blizzard | J9: Gray | K9: Rear-wheel Drive | L9: - | M9: Yes | N9: 3.6
A10: 9 | B10: Chrysler | C10: 2008 | D10: Used | E10: 77893 | F10: =IF((Table5[[#This Row],[Mileage]])=0, "None", IF(Table5[[#This Row],[Mileage]]<10000, "Low", IF(Table5[[#This Row],[Mileage]]<55000, "Average", "High"))) -> High | G10: No | H10: 7995 | I10: Silver | J10: Gray | K10: Front-wheel Drive | L10: 26 | M10: No | N10: 3.5
A11: 10 | B11: Ford | C11: 2012 | D11: Used | E11: 106430 | F11: =IF((Table5[[#This Row],[Mileage]])=0, "None", IF(Table5[[#This Row],[Mileage]]<10000, "Low", IF(Table5[[#This Row],[Mileage]]<55000, "Average", "High"))) -> High | G11: Yes | H11: 15750 | I11: White | J11: Gray | K11: Rear-wheel Drive | L11: 17 | M11: No
A12: 11 | B12: Toyota | C12: 2013 | D12: Used | E12: 155600 | F12: =IF((Table5[[#This Row],[Mileage]])=0, "None", IF(Table5[[#This Row],[Mileage]]<10000, "Low", IF(Table5[[#This Row],[Mileage]]<55000, "Average", "High"))) -> High | G12: No | H12: 12995 | I12: Blue | J12: Gray | K12: Front-wheel Drive | L12: 44 | M12: Yes
A13: 12 | B13: BMW | C13: 2002 | D13: Used | E13: 146000 | F13: =IF((Table5[[#This Row],[Mileage]])=0, "None", IF(Table5[[#This Row],[Mileage]]<10000, "Low", IF(Table5[[#This Row],[Mileage]]<55000, "Average", "High"))) -> High | G13: No | H13: 4599 | I13: White | J13: Beige | K13: Rear-wheel Drive | L13: - | M13: No
A14: 13 | B14: INFINITI | C14: 2020 | D14: Used | E14: 22901 | F14: =IF((Table5[[#This Row],[Mileage]])=0, "None", IF(Table5[[#This Row],[Mileage]]<10000, "Low", IF(Table5[[#This Row],[Mileage]]<55000, "Average", "High"))) -> Average | G14: No | H14: 38713 | I14: Iridium Blue | J14: Blue | K14: Rear-wheel Drive | L14: 20 | M14: No | N14: 4.1
A15: 14 | B15: Volkswagen | C15: 2014 | D15: Used | E15: 48650 | F15: =IF((Table5[[#This Row],[Mileage]])=0, "None", IF(Table5[[#This Row],[Mileage]]<10000, "Low", IF(Table5[[#This Row],[Mileage]]<55000, "Average", "High"))) -> Average | G15: No | H15: 16988 | I15: Platinum Gray Metallic | J15: Titan Black | K15: Front-wheel Drive | L15: 25 | M15: No | N15: 4.5
A16: 15 | B16: BMW | C16: 2015 | D16: Used | E16: 73660 | F16: =IF((Table5[[#This Row],[Mileage]])=0, "None", IF(Table5[[#This Row],[Mileage]]<10000, "Low", IF(Table5[[#This Row],[Mileage]]<55000, "Average", "High"))) -> High | G16: No | H16: 22843 | I16: Glacier Silver Metallic | J16: - | K16: Front-wheel Drive | L16: - | M16: No | N16: 4
A17: 16 | B17: BMW | C17: 2004 | D17: Used | E17: 119263 | F17: =IF((Table5[[#This Row],[Mileage]])=0, "None", IF(Table5[[#This Row],[Mileage]]<10000, "Low", IF(Table5[[#This Row],[Mileage]]<55000, "Average", "High"))) -> High | G17: No | H17: 7999 | I17: Gold | J17: Tan | K17: Rear-wheel Drive | L17: 18 | M17: No | N17: 4.3
A18: 17 | B18: Chevrolet | C18: 2024 | D18: New | E18: 2210 | F18: =IF((Table5[[#This Row],[Mileage]])=0, "None", IF(Table5[[#This Row],[Mileage]]<10000, "Low", IF(Table5[[#This Row],[Mileage]]<55000, "Average", "High"))) -> Low | G18: No | H18: 52715 | I18: Summit White | J18: Black | K18: All-wheel Drive | L18: - | M18: No | N18: 4.1
A19: 18 | B19: Jaguar | C19: 2000 | D19: Used | E19: 62022 | F19: =IF((Table5[[#This Row],[Mileage]])=0, "None", IF(Table5[[#This Row],[Mileage]]<10000, "Low", IF(Table5[[#This Row],[Mileage]]<55000, "Average", "High"))) -> High | G19: No | H19: 13995 | I19: Platinum Metallic | J19: Ivory | K19: Rear-wheel Drive | L19: 18 | M19: No
A20: 19 | B20: Subaru | C20: 2013 | D20: Used | E20: 84358 | F20: =IF((Table5[[#This Row],[Mileage]])=0, "None", IF(Table5[[#This Row],[Mileage]]<10000, "Low", IF(Table5[[#This Row],[Mileage]]<55000, "Average", "High"))) -> High | G20: Yes | H20: 13900 | I20: Venetian Red Pearl | J20: Ivory | K20: All-wheel Drive | L20: 25 | M20: Yes | N20: 4.8
A21: 20 | B21: Ford | C21: 2011 | D21: Used | E21: 181000 | F21: =IF((Table5[[#This Row],[Mileage]])=0, "None", IF(Table5[[#This Row],[Mileage]]<10000, "Low", IF(Table5[[#This Row],[Mileage]]<55000, "Average", "High"))) -> High | G21: No | H21: 9995 | I21: Red | J21: Black | K21: Rear-wheel Drive | L21: 13 | M21: Yes
A22: 21 | B22: BMW | C22: 2013 | D22: Used | E22: 77783 | F22: =IF((Table5[[#This Row],[Mileage]])=0, "None", IF(Table5[[#This Row],[Mileage]]<10000, "Low", IF(Table5[[#This Row],[Mileage]]<55000, "Average", "High"))) -> High | G22: No | H22: 8995 | I22: Pearl White | J22: Black | K22: Rear-wheel Drive | L22: 18 | M22: Yes
A23: 22 | B23: Audi | C23: 2019 | D23: Used | E23: 33832 | F23: =IF((Table5[[#This Row],[Mileage]])=0, "None", IF(Table5[[#This Row],[Mileage]]<10000, "Low", IF(Table5[[#This Row],[Mileage]]<55000, "Average", "High"))) -> Average | G23: Yes | H23: 39990 | I23: Daytona Gray Pearl Effect | J23: Black / Rock Gray | K23: All-wheel Drive | L23: 23 | M23: No | N23: 4.9
A24: 23 | B24: Chevrolet | C24: 1988 | D24: Used | E24: 48934 | F24: =IF((Table5[[#This Row],[Mileage]])=0, "None", IF(Table5[[#This Row],[Mileage]]<10000, "Low", IF(Table5[[#This Row],[Mileage]]<55000, "Average", "High"))) -> Average | G24: No | H24: 19888 | I24: Barcelona Red | J24: Barcelona Red | K24: Rear-wheel Drive | L24: 0 | M24: No | N24: 5
A25: 24 | B25: Mercedes-Benz | C25: 2016 | D25: Used | E25: 59386 | F25: =IF((Table5[[#This Row],[Mileage]])=0, "None", IF(Table5[[#This Row],[Mileage]]<10000, "Low", IF(Table5[[#This Row],[Mileage]]<55000, "Average", "High"))) -> High | G25: No | H25: 71995 | I25: Palladium Silver Metallic | J25: Designo Black | K25: All-wheel Drive | L25: 12 | M25: Yes | N25: 4.6
A26: 25 | B26: Lexus | C26: 2002 | D26: Used | E26: 98373 | F26: =IF((Table5[[#This Row],[Mileage]])=0, "None", IF(Table5[[#This Row],[Mileage]]<10000, "Low", IF(Table5[[#This Row],[Mileage]]<55000, "Average", "High"))) -> High | G26: Yes | H26: 8999 | I26: Burgundy | J26: Tan | K26: Rear-wheel Drive | L26: 18 | M26: No | N26: 4.3
A27: 26 | B27: Lexus | C27: 2023 | D27: New | E27: 0 | F27: =IF((Table5[[#This Row],[Mileage]])=0, "None", IF(Table5[[#This Row],[Mileage]]<10000, "Low", IF(Table5[[#This Row],[Mileage]]<55000, "Average", "High"))) -> None | G27: No | H27: 106615 | I27: Caviar | J27: Red | K27: Rear-wheel Drive | L27: 15 | M27: No | N27: 4.9
A28: 27 | B28: Pontiac | C28: 2006 | D28: Used | E28: 55915 | F28: =IF((Table5[[#This Row],[Mileage]])=0, "None", IF(Table5[[#This Row],[Mileage]]<10000, "Low", IF(Table5[[#This Row],[Mileage]]<55000, "Average", "High"))) -> High | G28: Yes | H28: 20691 | I28: Phantom Black Metallic | J28: Red | K28: Rear-wheel Drive | L28: - | M28: Yes | N28: 4.7
A29: 28 | B29: BMW | C29: 1988 | D29: Used | E29: 46344 | F29: =IF((Table5[[#This Row],[Mileage]])=0, "None", IF(Table5[[#This Row],[Mileage]]<10000, "Low", IF(Table5[[#This Row],[Mileage]]<55000, "Average", "High"))) -> Average | G29: No | H29: 63910 | I29: Cinnabar Red | J29: Tan | K29: Rear-wheel Drive | L29: - | M29: No | N29: 3.9
A30: 29 | B30: Triumph | C30: 1975 | D30: Used | E30: 27667 | F30: =IF((Table5[[#This Row],[Mileage]])=0, "None", IF(Table5[[#This Row],[Mileage]]<10000, "Low", IF(Table5[[#This Row],[Mileage]]<55000, "Average", "High"))) -> Average | G30: No | H30: 26507 | I30: Yellow | J30: Black | K30: Unkown | L30: - | M30: No | N30: 3.9
A31: 30 | B31: BMW | C31: 2018 | D31: Used | E31: 46698 | F31: =IF((Table5[[#This Row],[Mileage]])=0, "None", IF(Table5[[#This Row],[Mileage]]<10000, "Low", IF(Table5[[#This Row],[Mileage]]<55000, "Average", "High"))) -> Average | G31: No | H31: 45373 | I31: San Marino Blue Metallic | J31: Black | K31: Rear-wheel Drive | L31: 14 | M31: No | N31: 2.8
A32: 31 | B32: INFINITI | C32: 2009 | D32: Used | E32: 96658 | F32: =IF((Table5[[#This Row],[Mileage]])=0, "None", IF(Table5[[#This Row],[Mileage]]<10000, "Low", IF(Table5[[#This Row],[Mileage]]<55000, "Average", "High"))) -> High | G32: No | H32: 10980 | I32: Blue Slate Pearl | J32: Beige | K32: Rear-wheel Drive | L32: 18 | M32: Yes | N32: 4.6
A33: 32 | B33: Volkswagen | C33: 2016 | D33: Used | E33: 145302 | F33: =IF((Table5[[#This Row],[Mileage]])=0, "None", IF(Table5[[#This Row],[Mileage]]<10000, "Low", IF(Table5[[#This Row],[Mileage]]<55000, "Average", "High"))) -> High | G33: No | H33: 9495 | I33: Silver | J33: Black | K33: Front-wheel Drive | L33: 25 | M33: Yes
A34: 33 | B34: Scion | C34: 2005 | D34: Used | E34: 102243 | F34: =IF((Table5[[#This Row],[Mileage]])=0, "None", IF(Table5[[#This Row],[Mileage]]<10000, "Low", IF(Table5[[#This Row],[Mileage]]<55000, "Average", "High"))) -> High | G34: No | H34: 5795 | I34: Gray | J34: Black | K34: Front-wheel Drive | L34: 31 | M34: Yes | N34: 4.6
A35: 34 | B35: Toyota | C35: 2015 | D35: Used | E35: 91655 | F35: =IF((Table5[[#This Row],[Mileage]])=0, "None", IF(Table5[[#This Row],[Mileage]]<10000, "Low", IF(Table5[[#This Row],[Mileage]]<55000, "Average", "High"))) -> High | G35: No | H35: 13980 | I35: Attitude Black | J35: Gray | K35: Front-wheel Drive | L35: 44 | M35: No | N35: 4.6
A36: 35 | B36: Mercedes-Benz | C36: 2024 | D36: New | E36: 6 | F36: =IF((Table5[[#This Row],[Mileage]])=0, "None", IF(Table5[[#This Row],[Mileage]]<10000, "Low", IF(Table5[[#This Row],[Mileage]]<55000, "Average", "High"))) -> Low | G36: No | H36: 152800 | I36: Moonlight White | J36: Black | K36: All-wheel Drive | L36: - | M36: No | N36: 4.7
A37: 36 | B37: Toyota | C37: 2012 | D37: Used | E37: 168725 | F37: =IF((Table5[[#This Row],[Mileage]])=0, "None", IF(Table5[[#This Row],[Mileage]]<10000, "Low", IF(Table5[[#This Row],[Mileage]]<55000, "Average", "High"))) -> High | G37: No | H37: 9945 | I37: Magnetic Gray Metallic | J37: GRAY | K37: Front-wheel Drive | L37: 0 | M37: No | N37: 4.2
A38: 37 | B38: Chrysler | C38: 2008 | D38: Used | E38: 70974 | F38: =IF((Table5[[#This Row],[Mileage]])=0, "None", IF(Table5[[#This Row],[Mileage]]<10000, "Low", IF(Table5[[#This Row],[Mileage]]<55000, "Average", "High"))) -> High | G38: No | H38: 11950 | I38: Silver Steel Metallic Clearcoat | J38: Dark Slate Gray/Light Slate Gray | K38: Front-wheel Drive | L38: 18 | M38: No | N38: 4.6
A39: 38 | B39: Jeep | C39: 2007 | D39: Used | E39: 173694 | F39: =IF((Table5[[#This Row],[Mileage]])=0, "None", IF(Table5[[#This Row],[Mileage]]<10000, "Low", IF(Table5[[#This Row],[Mileage]]<55000, "Average", "High"))) -> High | G39: Yes | H39: 4550 | I39: Light Graystone Pearlcoat | J39: Khaki | K39: Four-wheel Drive | L39: 16 | M39: Yes
A40: 39 | B40: INFINITI | C40: 2017 | D40: Used | E40: 111586 | F40: =IF((Table5[[#This Row],[Mileage]])=0, "None", IF(Table5[[#This Row],[Mileage]]<10000, "Low", IF(Table5[[#This Row],[Mileage]]<55000, "Average", "High"))) -> High | G40: No | H40: 17995 | I40: Gray | J40: Gray | K40: All-wheel Drive | L40: 19 | M40: Yes
A41: 40 | B41: Lexus | C41: 2010 | D41: Used | E41: 128900 | F41: =IF((Table5[[#This Row],[Mileage]])=0, "None", IF(Table5[[#This Row],[Mileage]]<10000, "Low", IF(Table5[[#This Row],[Mileage]]<55000, "Average", "High"))) -> High | G41: No | H41: 9995 | I41: Black Opal Mica | J41: Black | K41: Front-wheel Drive | L41: 35 | M41: No | N41: 4.1
A42: 41 | B42: Porsche | C42: 2015 | D42: Used | E42: 48163 | F42: =IF((Table5[[#This Row],[Mileage]])=0, "None", IF(Table5[[#This Row],[Mileage]]<10000, "Low", IF(Table5[[#This Row],[Mileage]]<55000, "Average", "High"))) -> Average | G42: No | H42: 52985 | I42: Black | J42: Beige | K42: Rear-wheel Drive | L42: 21 | M42: No | N42: 4.2
A43: 42 | B43: INFINITI | C43: 2013 | D43: Used | E43: 162296 | F43: =IF((Table5[[#This Row],[Mileage]])=0, "None", IF(Table5[[#This Row],[Mileage]]<10000, "Low", IF(Table5[[#This Row],[Mileage]]<55000, "Average", "High"))) -> High | G43: No | H43: 8888 | I43: Black Obsidian | J43: Black | K43: All-wheel Drive | L43: 17 | M43: No | N43: 1.3
A44: 43 | B44: Lexus | C44: 2008 | D44: Used | E44: 167082 | F44: =IF((Table5[[#This Row],[Mileage]])=0, "None", IF(Table5[[#This Row],[Mileage]]<10000, "Low", IF(Table5[[#This Row],[Mileage]]<55000, "Average", "High"))) -> High | G44: No | H44: 7777 | I44: Red | J44: Beige | K44: All-wheel Drive | L44: 26 | M44: Yes | N44: 1.3
A45: 44 | B45: Toyota | C45: 2012 | D45: Used | E45: 67422 | F45: =IF((Table5[[#This Row],[Mileage]])=0, "None", IF(Table5[[#This Row],[Mileage]]<10000, "Low", IF(Table5[[#This Row],[Mileage]]<55000, "Average", "High"))) -> High | G45: No | H45: 14999 | I45: Classic Silver Metallic | J45: Black | K45: Front-wheel Drive | L45: 44 | M45: Yes
A46: 45 | B46: Toyota | C46: 2007 | D46: Used | E46: 67300 | F46: =IF((Table5[[#This Row],[Mileage]])=0, "None", IF(Table5[[#This Row],[Mileage]]<10000, "Low", IF(Table5[[#This Row],[Mileage]]<55000, "Average", "High"))) -> High | G46: No | H46: 9975 | I46: Pacific Blue Metallic | J46: Dark Charcoal | K46: Front-wheel Drive | L46: 34 | M46: No | N46: 4.1
A47: 46 | B47: Mercedes-Benz | C47: 2017 | D47: Used | E47: 5350 | F47: =IF((Table5[[#This Row],[Mileage]])=0, "None", IF(Table5[[#This Row],[Mileage]]<10000, "Low", IF(Table5[[#This Row],[Mileage]]<55000, "Average", "High"))) -> Low | G47: No | H47: 69800 | I47: Magnetite Black Metallic | J47: Black | K47: All-wheel Drive | L47: 15 | M47: Yes
A48: 47 | B48: BMW | C48: 2016 | D48: Used | E48: 111166 | F48: =IF((Table5[[#This Row],[Mileage]])=0, "None", IF(Table5[[#This Row],[Mileage]]<10000, "Low", IF(Table5[[#This Row],[Mileage]]<55000, "Average", "High"))) -> High | G48: No | H48: 18888 | I48: White | J48: Coral Red / Black | K48: Rear-wheel Drive | L48: 20 | M48: No | N48: 1.3
A49: 48 | B49: Ford | C49: 2011 | D49: Used | E49: 133990 | F49: =IF((Table5[[#This Row],[Mileage]])=0, "None", IF(Table5[[#This Row],[Mileage]]<10000, "Low", IF(Table5[[#This Row],[Mileage]]<55000, "Average", "High"))) -> High | G49: No | H49: 10990 | I49: White | J49: Gray | K49: Rear-wheel Drive | L49: 16 | M49: Yes | N49: 3.7
A50: 49 | B50: Aston | C50: 2012 | D50: Used | E50: 20038 | F50: =IF((Table5[[#This Row],[Mileage]])=0, "None", IF(Table5[[#This Row],[Mileage]]<10000, "Low", IF(Table5[[#This Row],[Mileage]]<55000, "Average", "High"))) -> Average | G50: No | H50: 67455 | I50: Hammerhead Silver | J50: Gray | K50: Rear-wheel Drive | L50: 13 | M50: No | N50: 4.3
A51: 50 | B51: Volkswagen | C51: 2022 | D51: Used | E51: 12959 | F51: =IF((Table5[[#This Row],[Mileage]])=0, "None", IF(Table5[[#This Row],[Mileage]]<10000, "Low", IF(Table5[[#This Row],[Mileage]]<55000, "Average", "High"))) -> Average | G51: No | H51: 43949 | I51: Pure White | J51: Blue | K51: All-wheel Drive | L51: 23 | M51: No | N51: 4.3
A52: 51 | B52: Cadillac | C52: 2014 | D52: Used | E52: 44500 | F52: =IF((Table5[[#This Row],[Mileage]])=0, "None", IF(Table5[[#This Row],[Mileage]]<10000, "Low", IF(Table5[[#This Row],[Mileage]]<55000, "Average", "High"))) -> Average | G52: No | H52: 16000 | I52: Graphite Metallic | J52: Medium Titanium / Jet Black | K52: Front-wheel Drive | L52: 18 | M52: Yes | N52: 4.7
A53: 52 | B53: Lexus | C53: 2008 | D53: Used | E53: 186000 | F53: =IF((Table5[[#This Row],[Mileage]])=0, "None", IF(Table5[[#This Row],[Mileage]]<10000, "Low", IF(Table5[[#This Row],[Mileage]]<55000, "Average", "High"))) -> High | G53: No | H53: 6500 | I53: Silver | J53: Beige | K53: All-wheel Drive | L53: - | M53: No
A54: 53 | B54: Toyota | C54: 2013 | D54: Used | E54: 92754 | F54: =IF((Table5[[#This Row],[Mileage]])=0, "None", IF(Table5[[#This Row],[Mileage]]<10000, "Low", IF(Table5[[#This Row],[Mileage]]<55000, "Average", "High"))) -> High | G54: Yes | H54: 11700 | I54: Blue | J54: Bisque | K54: Front-wheel Drive | L54: 44 | M54: Yes | N54: 4.8
A55: 54 | B55: Chevrolet | C55: 2014 | D55: Used | E55: 60261 | F55: =IF((Table5[[#This Row],[Mileage]])=0, "None", IF(Table5[[#This Row],[Mileage]]<10000, "Low", IF(Table5[[#This Row],[Mileage]]<55000, "Average", "High"))) -> High | G55: No | H55: 38595 | I55: Cyber Gray Metallic | J55: Jet Black | K55: Rear-wheel Drive | L55: 17 | M55: No | N55: 4.3
A56: 55 | B56: Ford | C56: 2005 | D56: Used | E56: 304425 | F56: =IF((Table5[[#This Row],[Mileage]])=0, "None", IF(Table5[[#This Row],[Mileage]]<10000, "Low", IF(Table5[[#This Row],[Mileage]]<55000, "Average", "High"))) -> High | G56: No | H56: 5997 | I56: Oxford White | J56: Medium Pebble | K56: Four-wheel Drive | L56: 0 | M56: No | N56: 4.8
A57: 56 | B57: Ford | C57: 2021 | D57: Used | E57: 32395 | F57: =IF((Table5[[#This Row],[Mileage]])=0, "None", IF(Table5[[#This Row],[Mileage]]<10000, "Low", IF(Table5[[#This Row],[Mileage]]<55000, "Average", "High"))) -> Average | G57: No | H57: 21987 | I57: Bronze Fire Metallic | J57: Dark Earth Gray | K57: All-wheel Drive | L57: 26 | M57: Yes | N57: 4.6
A58: 57 | B58: Mazda | C58: 2007 | D58: Used | E58: 151531 | F58: =IF((Table5[[#This Row],[Mileage]])=0, "None", IF(Table5[[#This Row],[Mileage]]<10000, "Low", IF(Table5[[#This Row],[Mileage]]<55000, "Average", "High"))) -> High | G58: No | H58: 3777 | I58: MAROON | J58: - | K58: - | L58: - | M58: No | N58: 4.8
A59: 58 | B59: Honda | C59: 2018 | D59: Used | E59: 93204 | F59: =IF((Table5[[#This Row],[Mileage]])=0, "None", IF(Table5[[#This Row],[Mileage]]<10000, "Low", IF(Table5[[#This Row],[Mileage]]<55000, "Average", "High"))) -> High | G59: No | H59: 17999 | I59: Black | J59: Black | K59: Front-wheel Drive | L59: - | M59: No | N59: 4.8
A60: 59 | B60: Lincoln | C60: 2007 | D60: Used | E60: 40145 | F60: =IF((Table5[[#This Row],[Mileage]])=0, "None", IF(Table5[[#This Row],[Mileage]]<10000, "Low", IF(Table5[[#This Row],[Mileage]]<55000, "Average", "High"))) -> Average | G60: No | H60: 16995 | I60: Vibrant White | J60: Black | K60: Rear-wheel Drive | L60: 17 | M60: Yes | N60: 4.4
A61: 60 | B61: Lincoln | C61: 2007 | D61: Used | E61: 104736 | F61: =IF((Table5[[#This Row],[Mileage]])=0, "None", IF(Table5[[#This Row],[Mileage]]<10000, "Low", IF(Table5[[#This Row],[Mileage]]<55000, "Average", "High"))) -> High | G61: No | H61: 9995 | I61: Cashmere Tri-Coat | J61: Light Camel | K61: Rear-wheel Drive | L61: 17 | M61: No | N61: 4.4
A62: 61 | B62: Saturn | C62: 2007 | D62: Used | E62: 35052 | F62: =IF((Table5[[#This Row],[Mileage]])=0, "None", IF(Table5[[#This Row],[Mileage]]<10000, "Low", IF(Table5[[#This Row],[Mileage]]<55000, "Average", "High"))) -> Average | G62: No | H62: 18995 | I62: Midnight Blue | J62: Tan | K62: Rear-wheel Drive | L62: - | M62: No | N62: 4.4
A63: 62 | B63: Saturn | C63: 2009 | D63: Used | E63: 26514 | F63: =IF((Table5[[#This Row],[Mileage]])=0, "None", IF(Table5[[#This Row],[Mileage]]<10000, "Low", IF(Table5[[#This Row],[Mileage]]<55000, "Average", "High"))) -> Average | G63: No | H63: 15995 | I63: Silver Pearl | J63: Red | K63: Rear-wheel Drive | L63: - | M63: Yes | N63: 4.4
A64: 63 | B64: Subaru | C64: 2020 | D64: Used | E64: 27861 | F64: =IF((Table5[[#This Row],[Mileage]])=0, "None", IF(Table5[[#This Row],[Mileage]]<10000, "Low", IF(Table5[[#This Row],[Mileage]]<55000, "Average", "High"))) -> Average | G64: No | H64: 35995 | I64: WR Blue Pearl | J64: Black | K64: All-wheel Drive | L64: 16 | M64: No | N64: 4.4
A65: 64 | B65: Porsche | C65: 2018 | D65: Used | E65: 12679 | F65: =IF((Table5[[#This Row],[Mileage]])=0, "None", IF(Table5[[#This Row],[Mileage]]<10000, "Low", IF(Table5[[#This Row],[Mileage]]<55000, "Average", "High"))) -> Average | G65: No | H65: 53995 | I65: Night Blue Metallic | J65: Black | K65: Rear-wheel Drive | L65: 21 | M65: No | N65: 4.4
A66: 65 | B66: INFINITI | C66: 2013 | D66: Used | E66: 87150 | F66: =IF((Table5[[#This Row],[Mileage]])=0, "None", IF(Table5[[#This Row],[Mileage]]<10000, "Low", IF(Table5[[#This Row],[Mileage]]<55000, "Average", "High"))) -> High | G66: No | H66: 16961 | I66: Lapis Blue | J66: Stone | K66: All-wheel Drive | L66: 18 | M66: Yes | N66: 4.7
A67: 66 | B67: Ford | C67: 2004 | D67: Used | E67: 204560 | F67: =IF((Table5[[#This Row],[Mileage]])=0, "None", IF(Table5[[#This Row],[Mileage]]<10000, "Low", IF(Table5[[#This Row],[Mileage]]<55000, "Average", "High"))) -> High | G67: Yes | H67: 15800 | I67: Oxford White | J67: Medium Parchment | K67: Four-wheel Drive | L67: 0 | M67: No
A68: 67 | B68: BMW | C68: 2017 | D68: Used | E68: 71099 | F68: =IF((Table5[[#This Row],[Mileage]])=0, "None", IF(Table5[[#This Row],[Mileage]]<10000, "Low", IF(Table5[[#This Row],[Mileage]]<55000, "Average", "High"))) -> High | G68: No | H68: 38995 | I68: Gray | J68: Black | K68: All-wheel Drive | L68: 14 | M68: Yes | N68: 4.1
A69: 68 | B69: BMW | C69: 2018 | D69: Used | E69: 91475 | F69: =IF((Table5[[#This Row],[Mileage]])=0, "None", IF(Table5[[#This Row],[Mileage]]<10000, "Low", IF(Table5[[#This Row],[Mileage]]<55000, "Average", "High"))) -> High | G69: No | H69: 22440 | I69: Black Sapphire Metallic | J69: Oyster | K69: All-wheel Drive | L69: 20 | M69: Yes | N69: 4.1
A70: 69 | B70: BMW | C70: 2017 | D70: Used | E70: 14826 | F70: =IF((Table5[[#This Row],[Mileage]])=0, "None", IF(Table5[[#This Row],[Mileage]]<10000, "Low", IF(Table5[[#This Row],[Mileage]]<55000, "Average", "High"))) -> Average | G70: No | H70: 78800 | I70: Space Gray Metallic | J70: Black | K70: Rear-wheel Drive | L70: 14 | M70: No | N70: 4.7
A71: 70 | B71: Mercedes-Benz | C71: 2019 | D71: Used | E71: 38545 | F71: =IF((Table5[[#This Row],[Mileage]])=0, "None", IF(Table5[[#This Row],[Mileage]]<10000, "Low", IF(Table5[[#This Row],[Mileage]]<55000, "Average", "High"))) -> Average | G71: No | H71: 48999 | I71: Gray | J71: Black | K71: All-wheel Drive | L71: 21 | M71: No | N71: 4.5
A72: 71 | B72: BMW | C72: 2019 | D72: Used | E72: 31010 | F72: =IF((Table5[[#This Row],[Mileage]])=0, "None", IF(Table5[[#This Row],[Mileage]]<10000, "Low", IF(Table5[[#This Row],[Mileage]]<55000, "Average", "High"))) -> Average | G72: No | H72: 53895 | I72: San Marino Blue Metallic | J72: Black | K72: Rear-wheel Drive | L72: 14 | M72: No
A73: 72 | B73: Ford | C73: 2003 | D73: Used | E73: 199574 | F73: =IF((Table5[[#This Row],[Mileage]])=0, "None", IF(Table5[[#This Row],[Mileage]]<10000, "Low", IF(Table5[[#This Row],[Mileage]]<55000, "Average", "High"))) -> High | G73: Yes | H73: 25975 | I73: Black Clearcoat | J73: Medium Pebble | K73: Four-wheel Drive | L73: 0 | M73: No | N73: 4.9
A74: 73 | B74: BMW | C74: 2014 | D74: Used | E74: 78188 | F74: =IF((Table5[[#This Row],[Mileage]])=0, "None", IF(Table5[[#This Row],[Mileage]]<10000, "Low", IF(Table5[[#This Row],[Mileage]]<55000, "Average", "High"))) -> High | G74: No | H74: 28990 | I74: Blue | J74: Black | K74: Rear-wheel Drive | L74: 16 | M74: Yes | N74: 2.7
A75: 74 | B75: Lexus | C75: 2024 | D75: New | E75: 0 | F75: =IF((Table5[[#This Row],[Mileage]])=0, "None", IF(Table5[[#This Row],[Mileage]]<10000, "Low", IF(Table5[[#This Row],[Mileage]]<55000, "Average", "High"))) -> None | G75: No | H75: 115425 | I75: Infrared | J75: Black W/ Satin Metallic Trim | K75: Rear-wheel Drive | L75: 15 | M75: No | N75: 4.9
A76: 75 | B76: Audi | C76: 2021 | D76: Used | E76: 60120 | F76: =IF((Table5[[#This Row],[Mileage]])=0, "None", IF(Table5[[#This Row],[Mileage]]<10000, "Low", IF(Table5[[#This Row],[Mileage]]<55000, "Average", "High"))) -> High | G76: No | H76: 49980 | I76: Florett Silver Metallic | J76: Black | K76: All-wheel Drive | L76: 15 | M76: Yes | N76: 4.7
A77: 76 | B77: McLaren | C77: 2016 | D77: Used | E77: 852 | F77: =IF((Table5[[#This Row],[Mileage]])=0, "None", IF(Table5[[#This Row],[Mileage]]<10000, "Low", IF(Table5[[#This Row],[Mileage]]<55000, "Average", "High"))) -> Low | G77: Yes | H77: 339800 | I77: Storm Grey | J77: Carbon Black with McLaren Orange | K77: Rear-wheel Drive | L77: 16 | M77: No | N77: 4.7
A78: 77 | B78: Porsche | C78: 2017 | D78: Used | E78: 41311 | F78: =IF((Table5[[#This Row],[Mileage]])=0, "None", IF(Table5[[#This Row],[Mileage]]<10000, "Low", IF(Table5[[#This Row],[Mileage]]<55000, "Average", "High"))) -> Average | G78: No | H78: 45911 | I78: Black | J78: Black | K78: Rear-wheel Drive | L78: 21 | M78: No
A79: 78 | B79: Nissan | C79: 2005 | D79: Used | E79: 46347 | F79: =IF((Table5[[#This Row],[Mileage]])=0, "None", IF(Table5[[#This Row],[Mileage]]<10000, "Low", IF(Table5[[#This Row],[Mileage]]<55000, "Average", "High"))) -> Average | G79: No | H79: 16500 | I79: Daytona Blue | J79: Beige | K79: Rear-wheel Drive | L79: 18 | M79: No | N79: 4.7
A80: 79 | B80: Audi | C80: 2008 | D80: Used | E80: 86447 | F80: =IF((Table5[[#This Row],[Mileage]])=0, "None", IF(Table5[[#This Row],[Mileage]]<10000, "Low", IF(Table5[[#This Row],[Mileage]]<55000, "Average", "High"))) -> High | G80: No | H80: 15500 | I80: - | J80: - | K80: Unkown | L80: - | M80: No | N80: 4.4
A81: 80 | B81: INFINITI | C81: 2009 | D81: Used | E81: 94164 | F81: =IF((Table5[[#This Row],[Mileage]])=0, "None", IF(Table5[[#This Row],[Mileage]]<10000, "Low", IF(Table5[[#This Row],[Mileage]]<55000, "Average", "High"))) -> High | G81: No | H81: 15800 | I81: Moonlight White | J81: Black | K81: Rear-wheel Drive | L81: 17 | M81: No | N81: 4.7
A82: 81 | B82: Lotus | C82: 2005 | D82: Used | E82: 19127 | F82: =IF((Table5[[#This Row],[Mileage]])=0, "None", IF(Table5[[#This Row],[Mileage]]<10000, "Low", IF(Table5[[#This Row],[Mileage]]<55000, "Average", "High"))) -> Average | G82: No | H82: 59800 | I82: GREY | J82: - | K82: - | L82: - | M82: No
A83: 82 | B83: Lincoln | C83: 1988 | D83: Used | E83: 72980 | F83: =IF((Table5[[#This Row],[Mileage]])=0, "None", IF(Table5[[#This Row],[Mileage]]<10000, "Low", IF(Table5[[#This Row],[Mileage]]<55000, "Average", "High"))) -> High | G83: No | H83: 16950 | I83: ROSE | J83: Rose | K83: Rear-wheel Drive | L83: 17 | M83: No | N83: 4.3
A84: 83 | B84: BMW | C84: 2010 | D84: Used | E84: 28006 | F84: =IF((Table5[[#This Row],[Mileage]])=0, "None", IF(Table5[[#This Row],[Mileage]]<10000, "Low", IF(Table5[[#This Row],[Mileage]]<55000, "Average", "High"))) -> Average | G84: No | H84: 31995 | I84: Blue | J84: Black | K84: Rear-wheel Drive | L84: 11 | M84: No | N84: 2.3
A85: 84 | B85: Cadillac | C85: 2022 | D85: Used | E85: 58099 | F85: =IF((Table5[[#This Row],[Mileage]])=0, "None", IF(Table5[[#This Row],[Mileage]]<10000, "Low", IF(Table5[[#This Row],[Mileage]]<55000, "Average", "High"))) -> High | G85: No | H85: 73995 | I85: Black Raven | J85: Jet Black With Jet Black Accents | K85: Rear-wheel Drive | L85: 13 | M85: No | N85: 4.6
A86: 85 | B86: Audi | C86: 2011 | D86: Used | E86: 90001 | F86: =IF((Table5[[#This Row],[Mileage]])=0, "None", IF(Table5[[#This Row],[Mileage]]<10000, "Low", IF(Table5[[#This Row],[Mileage]]<55000, "Average", "High"))) -> High | G86: No | H86: 15495 | I86: Black | J86: Madras Brown | K86: All-wheel Drive | L86: 21 | M86: Yes | N86: 2.3
A87: 86 | B87: Ferrari | C87: 1983 | D87: Used | E87: 32252 | F87: =IF((Table5[[#This Row],[Mileage]])=0, "None", IF(Table5[[#This Row],[Mileage]]<10000, "Low", IF(Table5[[#This Row],[Mileage]]<55000, "Average", "High"))) -> Average | G87: Yes | H87: 299900 | I87: Red | J87: Beige | K87: Unkown | L87: - | M87: No
A88: 87 | B88: Volkswagen | C88: 2019 | D88: Used | E88: 98185 | F88: =IF((Table5[[#This Row],[Mileage]])=0, "None", IF(Table5[[#This Row],[Mileage]]<10000, "Low", IF(Table5[[#This Row],[Mileage]]<55000, "Average", "High"))) -> High | G88: Yes | H88: 12200 | I88: Platinum Gray Metallic | J88: Titan Black | K88: All-wheel Drive | L88: 22 | M88: No | N88: 4.6
A89: 88 | B89: Rolls | C89: 2009 | D89: Used | E89: 52756 | F89: =IF((Table5[[#This Row],[Mileage]])=0, "None", IF(Table5[[#This Row],[Mileage]]<10000, "Low", IF(Table5[[#This Row],[Mileage]]<55000, "Average", "High"))) -> Average | G89: No | H89: 139800 | I89: Diamond Black | J89: Moccasin | K89: Rear-wheel Drive | L89: 11 | M89: No
A90: 89 | B90: Genesis | C90: 2023 | D90: New | E90: 5 | F90: =IF((Table5[[#This Row],[Mileage]])=0, "None", IF(Table5[[#This Row],[Mileage]]<10000, "Low", IF(Table5[[#This Row],[Mileage]]<55000, "Average", "High"))) -> Low | G90: No | H90: 89485 | I90: Makalu Gray Matte | J90: Urban Brown/Glacier White | K90: All-wheel Drive | L90: 17 | M90: No | N90: 4.1
A91: 90 | B91: Chevrolet | C91: 2015 | D91: Used | E91: 105307 | F91: =IF((Table5[[#This Row],[Mileage]])=0, "None", IF(Table5[[#This Row],[Mileage]]<10000, "Low", IF(Table5[[#This Row],[Mileage]]<55000, "Average", "High"))) -> High | G91: No | H91: 14995 | I91: Silver Ice Metallic | J91: Dark Titanium/Jet Black | K91: Front-wheel Drive | L91: 22 | M91: No
A92: 91 | B92: Chevrolet | C92: 2018 | D92: Used | E92: 112099 | F92: =IF((Table5[[#This Row],[Mileage]])=0, "None", IF(Table5[[#This Row],[Mileage]]<10000, "Low", IF(Table5[[#This Row],[Mileage]]<55000, "Average", "High"))) -> High | G92: No | H92: 15995 | I92: Mosaic Black Metallic | J92: Jet Black | K92: Front-wheel Drive | L92: 22 | M92: No
A93: 92 | B93: Dodge | C93: 2015 | D93: Used | E93: 132502 | F93: =IF((Table5[[#This Row],[Mileage]])=0, "None", IF(Table5[[#This Row],[Mileage]]<10000, "Low", IF(Table5[[#This Row],[Mileage]]<55000, "Average", "High"))) -> High | G93: Yes | H93: 14995 | I93: Deep Cherry Red Crystal Pearlcoat | J93: Black | K93: Rear-wheel Drive | L93: 18 | M93: Yes
A94: 93 | B94: INFINITI | C94: 2012 | D94: Used | E94: 84766 | F94: =IF((Table5[[#This Row],[Mileage]])=0, "None", IF(Table5[[#This Row],[Mileage]]<10000, "Low", IF(Table5[[#This Row],[Mileage]]<55000, "Average", "High"))) -> High | G94: No | H94: 11949 | I94: Graphite Shadow | J94: Graphite | K94: All-wheel Drive | L94: 18 | M94: Yes | N94: 4.6
A95: 94 | B95: Ford | C95: 2019 | D95: Used | E95: 66533 | F95: =IF((Table5[[#This Row],[Mileage]])=0, "None", IF(Table5[[#This Row],[Mileage]]<10000, "Low", IF(Table5[[#This Row],[Mileage]]<55000, "Average", "High"))) -> High | G95: Yes | H95: 15903 | I95: Ingot Silver | J95: Charcoal Black | K95: Four-wheel Drive | L95: 22 | M95: No | N95: 4.5
A96: 95 | B96: Subaru | C96: 2019 | D96: Used | E96: 53038 | F96: =IF((Table5[[#This Row],[Mileage]])=0, "None", IF(Table5[[#This Row],[Mileage]]<10000, "Low", IF(Table5[[#This Row],[Mileage]]<55000, "Average", "High"))) -> Average | G96: Yes | H96: 30990 | I96: Dark Gray Metallic | J96: Black | K96: All-wheel Drive | L96: 17 | M96: Yes | N96: 4.9
A97: 96 | B97: Volkswagen | C97: 2018 | D97: Certified | E97: 41540 | F97: =IF((Table5[[#This Row],[Mileage]])=0, "None", IF(Table5[[#This Row],[Mileage]]<10000, "Low", IF(Table5[[#This Row],[Mileage]]<55000, "Average", "High"))) -> Average | G97: Yes | H97: 32490 | I97: Indium Gray Metallic | J97: Titan Black | K97: All-wheel Drive | L97: 21 | M97: No | N97: 4.9
A98: 97 | B98: Ford | C98: 2012 | D98: Used | E98: 115225 | F98: =IF((Table5[[#This Row],[Mileage]])=0, "None", IF(Table5[[#This Row],[Mileage]]<10000, "Low", IF(Table5[[#This Row],[Mileage]]<55000, "Average", "High"))) -> High | G98: Yes | H98: 14980 | I98: White | J98: Gray | K98: Rear-wheel Drive | L98: 16 | M98: No
A99: 98 | B99: Chevrolet | C99: 2021 | D99: Used | E99: 29804 | F99: =IF((Table5[[#This Row],[Mileage]])=0, "None", IF(Table5[[#This Row],[Mileage]]<10000, "Low", IF(Table5[[#This Row],[Mileage]]<55000, "Average", "High"))) -> Average | G99: No | H99: 21000 | I99: Silver Ice Metallic | J99: Jet Black | K99: Front-wheel Drive | L99: 29 | M99: No | N99: 4.5
A100: 99 | B100: Jeep | C100: 2017 | D100: Used | E100: 97142 | F100: =IF((Table5[[#This Row],[Mileage]])=0, "None", IF(Table5[[#This Row],[Mileage]]<10000, "Low", IF(Table5[[#This Row],[Mileage]]<55000, "Average", "High"))) -> High | G100: No | H100: 24895 | I100: Bright White Clearcoat | J100: Black | K100: Four-wheel Drive | L100: 16 | M100: Yes | N100: 4.7
...

Sheet Views
A1: View_ID | B1: Car_ID | C1: Viewer_Name | D1: Viewer_Gender | E1: View_Month | F1: Condition | G1: Make | H1: Drive
A2: 1 | B2: 12 | C2: Alice | D2: Female | E2: January | F2: =VLOOKUP(B2,'Clean Sheet'!A:N,4,FALSE) -> Used | G2: =_xlfn.XLOOKUP(Views!B2,'Clean Sheet'!A:A,'Clean Sheet'!B:B) -> BMW | H2: =_xlfn.XLOOKUP(Views!B2,'Clean Sheet'!A:A,'Clean Sheet'!K:K) -> Rear-wheel Drive
A3: 2 | B3: 23 | C3: Bob | D3: Male | E3: December | F3: =VLOOKUP(B3,'Clean Sheet'!A:N,4,FALSE) -> Used | G3: =_xlfn.XLOOKUP(Views!B3,'Clean Sheet'!A:A,'Clean Sheet'!B:B) -> Chevrolet | H3: =_xlfn.XLOOKUP(Views!B3,'Clean Sheet'!A:A,'Clean Sheet'!K:K) -> Rear-wheel Drive
A4: 3 | B4: 34 | C4: Carol | D4: Female | E4: March | F4: =VLOOKUP(B4,'Clean Sheet'!A:N,4,FALSE) -> Used | G4: =_xlfn.XLOOKUP(Views!B4,'Clean Sheet'!A:A,'Clean Sheet'!B:B) -> Toyota | H4: =_xlfn.XLOOKUP(Views!B4,'Clean Sheet'!A:A,'Clean Sheet'!K:K) -> Front-wheel Drive
A5: 4 | B5: 45 | C5: David | D5: Male | E5: February | F5: =VLOOKUP(B5,'Clean Sheet'!A:N,4,FALSE) -> Used | G5: =_xlfn.XLOOKUP(Views!B5,'Clean Sheet'!A:A,'Clean Sheet'!B:B) -> Toyota | H5: =_xlfn.XLOOKUP(Views!B5,'Clean Sheet'!A:A,'Clean Sheet'!K:K) -> Front-wheel Drive
A6: 5 | B6: 5 | C6: Eve | D6: Female | E6: April | F6: =VLOOKUP(B6,'Clean Sheet'!A:N,4,FALSE) -> Used | G6: =_xlfn.XLOOKUP(Views!B6,'Clean Sheet'!A:A,'Clean Sheet'!B:B) -> BMW | H6: =_xlfn.XLOOKUP(Views!B6,'Clean Sheet'!A:A,'Clean Sheet'!K:K) -> All-wheel Drive
A7: 6 | B7: 21 | C7: Frank | D7: Male | E7: January | F7: =VLOOKUP(B7,'Clean Sheet'!A:N,4,FALSE) -> Used | G7: =_xlfn.XLOOKUP(Views!B7,'Clean Sheet'!A:A,'Clean Sheet'!B:B) -> BMW | H7: =_xlfn.XLOOKUP(Views!B7,'Clean Sheet'!A:A,'Clean Sheet'!K:K) -> Rear-wheel Drive
A8: 7 | B8: 10 | C8: Grace | D8: Female | E8: February | F8: =VLOOKUP(B8,'Clean Sheet'!A:N,4,FALSE) -> Used | G8: =_xlfn.XLOOKUP(Views!B8,'Clean Sheet'!A:A,'Clean Sheet'!B:B) -> Ford | H8: =_xlfn.XLOOKUP(Views!B8,'Clean Sheet'!A:A,'Clean Sheet'!K:K) -> Rear-wheel Drive
A9: 8 | B9: 3 | C9: Henry | D9: Male | E9: March | F9: =VLOOKUP(B9,'Clean Sheet'!A:N,4,FALSE) -> Used | G9: =_xlfn.XLOOKUP(Views!B9,'Clean Sheet'!A:A,'Clean Sheet'!B:B) -> McLaren | H9: =_xlfn.XLOOKUP(Views!B9,'Clean Sheet'!A:A,'Clean Sheet'!K:K) -> Rear-wheel Drive
A10: 9 | B10: 27 | C10: Ivy | D10: Female | E10: April | F10: =VLOOKUP(B10,'Clean Sheet'!A:N,4,FALSE) -> Used | G10: =_xlfn.XLOOKUP(Views!B10,'Clean Sheet'!A:A,'Clean Sheet'!B:B) -> Pontiac | H10: =_xlfn.XLOOKUP(Views!B10,'Clean Sheet'!A:A,'Clean Sheet'!K:K) -> Rear-wheel Drive
A11: 10 | B11: 38 | C11: Jack | D11: Male | E11: January | F11: =VLOOKUP(B11,'Clean Sheet'!A:N,4,FALSE) -> Used | G11: =_xlfn.XLOOKUP(Views!B11,'Clean Sheet'!A:A,'Clean Sheet'!B:B) -> Jeep | H11: =_xlfn.XLOOKUP(Views!B11,'Clean Sheet'!A:A,'Clean Sheet'!K:K) -> Four-wheel Drive
A12: 11 | B12: 15 | C12: Kelly | D12: Female | E12: May | F12: =VLOOKUP(B12,'Clean Sheet'!A:N,4,FALSE) -> Used | G12: =_xlfn.XLOOKUP(Views!B12,'Clean Sheet'!A:A,'Clean Sheet'!B:B) -> BMW | H12: =_xlfn.XLOOKUP(Views!B12,'Clean Sheet'!A:A,'Clean Sheet'!K:K) -> Front-wheel Drive
A13: 12 | B13: 50 | C13: Liam | D13: Male | E13: June | F13: =VLOOKUP(B13,'Clean Sheet'!A:N,4,FALSE) -> Used | G13: =_xlfn.XLOOKUP(Views!B13,'Clean Sheet'!A:A,'Clean Sheet'!B:B) -> Volkswagen | H13: =_xlfn.XLOOKUP(Views!B13,'Clean Sheet'!A:A,'Clean Sheet'!K:K) -> All-wheel Drive
... A17: 16 | B17: 7 | C17: Paul | D17: Male | E17: October | F17: =VLOOKUP(B17,'Clean Sheet'!A:N,4,FALSE) -> Used | G17: =_xlfn.XLOOKUP(Views!B17,'Clean Sheet'!A:A,'Clean Sheet'!B:B) -> Cadillac | H17: =_xlfn.XLOOKUP(Views!B17,'Clean Sheet'!A:A,'Clean Sheet'!K:K) -> All-wheel Drive
A18: 17 | B18: 29 | C18: Quinn | D18: Female | E18: November | F18: =VLOOKUP(B18,'Clean Sheet'!A:N,4,FALSE) -> Used | G18: =_xlfn.XLOOKUP(Views!B18,'Clean Sheet'!A:A,'Clean Sheet'!B:B) -> Triumph | H18: All-wheel Drive
A19: 18 | B19: 55 | C19: Ryan | D19: Male | E19: December | F19: =VLOOKUP(B19,'Clean Sheet'!A:N,4,FALSE) -> Used | G19: =_xlfn.XLOOKUP(Views!B19,'Clean Sheet'!A:A,'Clean Sheet'!B:B) -> Ford | H19: =_xlfn.XLOOKUP(Views!B19,'Clean Sheet'!A:A,'Clean Sheet'!K:K) -> Four-wheel Drive
A20: 19 | B20: 14 | C20: Sophia | D20: Female | E20: January | F20: =VLOOKUP(B20,'Clean Sheet'!A:N,4,FALSE) -> Used | G20: =_xlfn.XLOOKUP(Views!B20,'Clean Sheet'!A:A,'Clean Sheet'!B:B) -> Volkswagen | H20: =_xlfn.XLOOKUP(Views!B20,'Clean Sheet'!A:A,'Clean Sheet'!K:K) -> Front-wheel Drive
A21: 20 | B21: 24 | C21: Thomas | D21: Male | E21: February | F21: =VLOOKUP(B21,'Clean Sheet'!A:N,4,FALSE) -> Used | G21: =_xlfn.XLOOKUP(Views!B21,'Clean Sheet'!A:A,'Clean Sheet'!B:B) -> Mercedes-Benz | H21: =_xlfn.XLOOKUP(Views!B21,'Clean Sheet'!A:A,'Clean Sheet'!K:K) -> All-wheel Drive
A22: 21 | B22: 6 | C22: Uma | D22: Female | E22: March | F22: =VLOOKUP(B22,'Clean Sheet'!A:N,4,FALSE) -> Used | G22: =_xlfn.XLOOKUP(Views!B22,'Clean Sheet'!A:A,'Clean Sheet'!B:B) -> Jeep | H22: =_xlfn.XLOOKUP(Views!B22,'Clean Sheet'!A:A,'Clean Sheet'!K:K) -> Four-wheel Drive
A23: 22 | B23: 41 | C23: Victor | D23: Male | E23: April | F23: =VLOOKUP(B23,'Clean Sheet'!A:N,4,FALSE) -> Used | G23: =_xlfn.XLOOKUP(Views!B23,'Clean Sheet'!A:A,'Clean Sheet'!B:B) -> Porsche | H23: =_xlfn.XLOOKUP(Views!B23,'Clean Sheet'!A:A,'Clean Sheet'!K:K) -> Rear-wheel Drive
A24: 23 | B24: 9 | C24: Wendy | D24: Female | E24: May | F24: =VLOOKUP(B24,'Clean Sheet'!A:N,4,FALSE) -> Used | G24: =_xlfn.XLOOKUP(Views!B24,'Clean Sheet'!A:A,'Clean Sheet'!B:B) -> Chrysler | H24: =_xlfn.XLOOKUP(Views!B24,'Clean Sheet'!A:A,'Clean Sheet'!K:K) -> Front-wheel Drive
A25: 24 | B25: 33 | C25: Xavier | D25: Male | E25: June | F25: =VLOOKUP(B25,'Clean Sheet'!A:N,4,FALSE) -> Used | G25: =_xlfn.XLOOKUP(Views!B25,'Clean Sheet'!A:A,'Clean Sheet'!B:B) -> Scion | H25: =_xlfn.XLOOKUP(Views!B25,'Clean Sheet'!A:A,'Clean Sheet'!K:K) -> Front-wheel Drive
A26: 25 | B26: 44 | C26: Yara | D26: Female | E26: July | F26: =VLOOKUP(B26,'Clean Sheet'!A:N,4,FALSE) -> Used | G26: =_xlfn.XLOOKUP(Views!B26,'Clean Sheet'!A:A,'Clean Sheet'!B:B) -> Toyota | H26: =_xlfn.XLOOKUP(Views!B26,'Clean Sheet'!A:A,'Clean Sheet'!K:K) -> Front-wheel Drive

Sheet Pivot Tables
A1: What is the average price for each car condition? | E1: What is the car history of the top 10 cars, with the highest average price?
A2: Make | B2: (All) | E2: Car Make | F2: Average of Mileage | G2: Count of Accident | H2: Average of Price
E3: Bugatti | F3: 10890 | G3: 1 | H3: 1699800
A4: Car Condition | B4: Avg Price Per Condition | E4: Lamborghini | F4: 9260.6 | G4: 15 | H4: 298496.53
A5: Certified | B5: 50682.116 | E5: Ferrari | F5: 13969.828 | G5: 29 | H5: 247003.45
A6: New | B6: 50491.347 | E6: McLaren | F6: 5184 | G6: 6 | H6: 238506.67
A7: Used | B7: 31788.65 | E7: Rolls | F7: 26206.056 | G7: 18 | H7: 186205
A8: Grand Total | B8: 40223.805 | E8: Bentley | F8: 22107.889 | G8: 9 | H8: 151555.67
E9: Aston | F9: 20491.812 | G9: 16 | H9: 110417.75
A10: What percentage of cars make up "High", "Average", "Low", "None" in car milage? | E10: Delorean | F10: 495 | G10: 1 | H10: 100989
A11: Milage Category | B11: Number of Cars | C11: Avg of Price | E11: Maserati | F11: 15441.129 | G11: 31 | H11: 74482.323
A12: Low | B12: 0.397446 | C12: 53903.741 | E12: Rivian | F12: 12305.947 | G12: 19 | H12: 72091.895
A13: High | B13: 0.2744758 | C13: 18805.769 | E13: Grand Total | F13: 15845.241 | G13: 145 | H13: 172644.48
A14: Average | B14: 0.26801198 | C14: 38636.691
A15: None | B15: 0.060066215 | C15: 54658.913 | E15: Which is the best month to attract car consumers? | I15: What are the top 10 makes with the highest mileage average?
A16: Grand Total | B16: 1 | C16: 40223.805 | E16: Months | F16: Count of View_ID | I16: Make | J16: Average of Mileage
E17: January | F17: 4 | I17: Hummer | J17: 99791.6
A18: Which wheel drive is viewed the most? What gender is viewing? | E18: February | F18: 3 | I18: INFINITI | J18: 64676.696
A19: Row Labels | B19: Count of View_ID | E19: March | F19: 3 | I19: Isuzu | J19: 114824
A20: All-wheel Drive | B20: 5 | E20: April | F20: 3 | I20: Mercury | J20: 94835.333
A21: Female | B21: 2 | E21: May | F21: 2 | I21: Mitsubishi | J21: 68436.083
